Workbook
Name Attendance: #REF!
Name Attendance: '[1]HK Attendance Sheet Aug''2020'!#REF!
Name dd: #REF!
Name dd: #REF!
Name dd: #REF!
Name dd: #REF!
Name dd: #REF!
Name dd: #REF!
Name Designation: #REF!
Name Designation: #REF!
Name Designation: #REF!
Name Designation: #REF!
Name Designation: #REF!
Name Designation: #REF!
Name Designation: #REF!
Name Designation: #REF!
Name Designation: #REF!
Name Designation: #REF!
Name Designation: #REF!
Name Designation: #REF!
Name Designation: #REF!
Name ff: #REF!
Name ff: #REF!
Name ff: #REF!
Name ff: #REF!
Name ff: #REF!
Name ff: #REF!
Name lljo: #REF!
Name lljo: #REF!
Name lljo: #REF!
Name lljo: #REF!
Name lljo: #REF!
Name lljo: #REF!
Name O: 'Inside Meter '!$B$1048566
Name odm: #REF!
Name odm: #REF!
Name odm: #REF!
Name odm: #REF!
Name odm: #REF!
Name odm: #REF!
Name ONDOT: #REF!
Name ONDOT: #REF!
Name ONDOT: #REF!
Name ONDOT: #REF!
Name ONDOT: #REF!
Name ONDOT: #REF!
Name ONDOT: #REF!
Name ONDOT: #REF!
Name ONDOT: #REF!
Name ONDOT: #REF!
Name ONDOT: #REF!
Name ONDOT: #REF!
Name ram: #REF!
Name ram: #REF!
Name ram: #REF!
Name ram: #REF!
Name ram: #REF!
Name ram: #REF!
Name ramji: #REF!
Name ramji: #REF!

Sheet Summary
B2: =R5&" Consumption Report Summary of "& TEXT($R$4," MMM YY") -> SOC Consumption Report Summary of Feb 26
Q3: SheetTool
Q4: Date | R4: 46054
Q5: Company Name | R5: SOC
C7: =R5&" Electricity & DG" -> SOC Electricity & DG | F7: Unit | I7: Order | J7: Total Stock | K7: Usage Stock | L7: Closing Stock | M7: Usage Amount | N7: Closing Amount | O7: Order Amount
C8: Inside Meter | D8: ELC Reading UPS Room | E8: Electricity | F8: ='Inside Meter '!F39 -> 1078 | H8: Bisleri_Consu | I8: =Bisleri_Consu!I9 -> 0 | J8: =Bisleri_Consu!N9 -> 20 | K8: =Bisleri_Consu!AT9 -> 12 | L8: =Bisleri_Consu!AU9 -> 8 | M8: =Bisleri_Consu!AV9 -> 1754.22 | N8: =Bisleri_Consu!AW9 -> 915.28 | O8: =Bisleri_Consu!AX9 -> 0
E9: HVAC | F9: ='Inside Meter '!I39 -> 7947.6 | H9: Medical_Items | I9: =Medical_Items!I27 -> 22 | J9: =Medical_Items!N27 -> 119 | K9: =Medical_Items!AT27 -> 7 | L9: =Medical_Items!AU27 -> 112 | M9: =Medical_Items!AV27 -> 494.32 | N9: =Medical_Items!AW27 -> 3265.99 | O9: =Medical_Items!AX27 -> 1879.08
D10: Reading AHU Room (Water Chiller) | E10: BTU Reading | F10: ='Inside Meter '!O39 -> 42553.86 | H10: Stationery | I10: =Stationery!H123 -> 81 | J10: =Stationery!I123 -> 1344 | K10: =Stationery!AO123 -> 183 | L10: =Stationery!AP123 -> 1181 | M10: =Stationery!AQ123 -> 4216 | N10: =Stationery!AR123 -> 16182.1 | O10: =Stationery!AS123 -> 4248
C11: OutSide Meter | D11: Mantri Office Utility MSEB and DG Meter | E11: Utility EB (KWH) | F11: ='OutSide Meter'!F38 -> 6640 | H11: HK Material | I11: ='HK Material'!I81 -> 1405 | J11: ='HK Material'!J81 -> 1984 | K11: ='HK Material'!AP81 -> 795 | L11: ='HK Material'!AQ81 -> 1189 | M11: ='HK Material'!AR81 -> 23747 | N11: ='HK Material'!AS81 -> 51402.5 | O11: ='HK Material'!AT81 -> 43843
E12: Utility DG (KWH) | F12: ='OutSide Meter'!J38 -> 80 | H12: Food Consu | I12: ='Food Consu'!J37 -> 0 | J12: =I12 -> 0 | K12: ='Food Consu'!J37 -> 0 | L12: =K12 -> 0 | M12: ='Food Consu'!N37 -> 0 | N12: ='Food Consu'!N37 -> 0 | O12: ='Food Consu'!M37 -> 0
E13: Utility EB (KVAH) | F13: ='OutSide Meter'!P38 -> 6960 | H13: Veebha Tea&Coffee | I13: ='Veebha Tea&Coffee'!I10 -> 0 | J13: ='Veebha Tea&Coffee'!N10 -> 164 | K13: ='Veebha Tea&Coffee'!AT10 -> 8 | L13: ='Veebha Tea&Coffee'!AU10 -> 156 | M13: ='Veebha Tea&Coffee'!AV10 -> 1280 | N13: ='Veebha Tea&Coffee'!AW10 -> 24960 | O13: ='Veebha Tea&Coffee'!AX10 -> 0
E14: Utility DG (KVAH) | F14: ='OutSide Meter'!T38 -> 0 | H14: Sumant Tea&Coffee | I14: ='Sumant Tea&Coffee'!I12 -> 2062 | J14: ='Sumant Tea&Coffee'!N12 -> 3153 | K14: ='Sumant Tea&Coffee'!AT12 -> 27 | L14: ='Sumant Tea&Coffee'!AU12 -> 3126 | M14: ='Sumant Tea&Coffee'!AV12 -> 4518.96 | N14: ='Sumant Tea&Coffee'!AW12 -> 19120.56 | O14: ='Sumant Tea&Coffee'!AX12 -> 12816.96
D15: Mantri Building Meter | E15: (KWH) | F15: ='OutSide Meter'!Y38 -> 89894 | H15: Toner Consu | I15: ='Toner Consu'!I15 -> 2 | J15: ='Toner Consu'!N15 -> 10 | K15: ='Toner Consu'!AT15 -> 5 | L15: ='Toner Consu'!AU15 -> 5 | M15: ='Toner Consu'!AV15 -> 4400 | N15: ='Toner Consu'!AW15 -> 6000 | O15: ='Toner Consu'!AX15 -> 2400
E16: (KVAH) | F16: ='OutSide Meter'!AB38 -> 96612 | H16: Water | I16: =Water!D36 -> 259 | J16: =Water!D36 -> 259 | K16: =Water!G36 -> 269 | L16: =Water!J41 -> 0 | M16: =K16*Water!B3 -> 9415 | N16: =Water!J41*Water!B3 -> 0 | O16: =Water!D36*Water!B3 -> 9065
D17: A - Wing Chiller Panel | E17: EB | F17: ='OutSide Meter'!AG38 -> 90.6578 | H17: Gallent SG | I17: NA | J17: NA | K17: NA | L17: NA | M17: ='Gallant SG'!AS12 -> 34721.867 | N17: ='Gallant SG'!AS12 -> 34721.867 | O17: ='Gallant SG'!AS12 -> 34721.867
E18: DG | F18: ='OutSide Meter'!AJ38 -> 278.9934 | H18: OOPL SG | I18: NA | J18: NA | K18: NA | L18: NA | M18: ='OOPL SG '!AR16 -> 88091.667 | N18: =M18 -> 88091.667 | O18: =N18 -> 88091.667
H19: Imperial HK | I19: NA | J19: NA | K19: NA | L19: NA | M19: ='Imperial HK'!AR23 -> 113108.17 | N19: =M19 -> 113108.17 | O19: =N19 -> 113108.17
H20: Extra Bill | I20: NA | J20: NA | K20: NA | L20: NA | M20: ='Extra Bills'!I99 -> 0 | N20: =M20 -> 0 | O20: =N20 -> 0

Sheet Extra Bills
B2: Company Name | C2: Expenses Type | D2: BILL DATE | E2: VENDOR NAME | F2: Office No | G2: BILL MONTH | H2: BILL NO | I2: BASIC VALUE | J2: CGST | K2: SGST | L2: TOTAL
B99: TOTAL | I99: =SUM(I6:I98) -> 0 | L99: =SUM(L6:L98) -> 0

Sheet Inside Meter 
B2: =Summary!$R$5&" Home Meter Reading "&TEXT(Summary!$R$4,"MMM YY") -> SOC Home Meter Reading Feb 26
D3: ELC Reading UPS Room | M3: Reading AHU Room (Water Chiller)
D4: Electricity | G4: HVAC | M4: BTU Reading
B5: Auto | C5: Auto | F5: Auto | I5: Auto | K5: Auto | L5: Auto | O5: Auto
B6: Date | C6: Day | D6: Opening | E6: Closening | F6: Cons | G6: Opening | H6: Closening | I6: Cons | K6: Date | L6: Day | M6: Opening | N6: Closening | O6: Cons
B7: =B8-1 -> 46053 | C7: =TEXT(B7,"DDD") -> Sat | D7: 284123 | E7: 284161.5 | F7: =E7-D7 -> 38.5 | G7: 1327218 | H7: 1327526.1 | I7: =H7-G7 -> 308.1 | K7: =K8-1 -> 46053 | L7: =TEXT(K7,"DDD") -> Sat | M7: 1425197.5 | N7: 1425762.4 | O7: =N7-M7 -> 564.92
B8: =Summary!R4 -> 46054 | C8: =TEXT(B8,"DDD") -> Sun | D8: =E7 -> 284161.5 | E8: 284212.1 | F8: =E8-D8 -> 50.6 | G8: =H7 -> 1327526.1 | H8: 1327821.7 | I8: =H8-G8 -> 295.6 | K8: =Summary!R4 -> 46054 | L8: =TEXT(K8,"DDD") -> Sun | M8: =N7 -> 1425762.4 | N8: 1425844.3 | O8: =N8-M8 -> 81.9
B9: =B8+1 -> 46055 | C9: =TEXT(B9,"DDD") -> Mon | D9: =E8 -> 284212.1 | E9: 284273.1 | F9: =E9-D9 -> 61 | G9: =H8 -> 1327821.7 | H9: 1328331.1 | I9: =H9-G9 -> 509.4 | K9: =K8+1 -> 46055 | L9: =TEXT(K9,"DDD") -> Mon | M9: =N8 -> 1425844.3 | N9: 1430437.5 | O9: =N9-M9 -> 4593.15
B10: =B9+1 -> 46056 | C10: =TEXT(B10,"DDD") -> Tue | D10: =E9 -> 284273.1 | E10: 284352.7 | F10: =E10-D10 -> 79.6 | G10: =H9 -> 1328331.1 | H10: 1328873.6 | I10: =H10-G10 -> 542.5 | K10: =K9+1 -> 46056 | L10: =TEXT(K10,"DDD") -> Tue | M10: =N9 -> 1430437.5 | N10: 1433787.1 | O10: =N10-M10 -> 3349.64
B11: =B10+1 -> 46057 | C11: =TEXT(B11,"DDD") -> Wed | D11: =E10 -> 284352.7 | E11: 284414.6 | F11: =E11-D11 -> 61.9 | G11: =H10 -> 1328873.6 | H11: 1329398.2 | I11: =H11-G11 -> 524.6 | K11: =K10+1 -> 46057 | L11: =TEXT(K11,"DDD") -> Wed | M11: =N10 -> 1433787.1 | N11: 1436046.3 | O11: =N11-M11 -> 2259.19
B12: =B11+1 -> 46058 | C12: =TEXT(B12,"DDD") -> Thu | D12: =E11 -> 284414.6 | E12: 284490.6 | F12: =E12-D12 -> 76 | G12: =H11 -> 1329398.2 | H12: 1329947.3 | I12: =H12-G12 -> 549.1 | K12: =K11+1 -> 46058 | L12: =TEXT(K12,"DDD") -> Thu | M12: =N11 -> 1436046.3 | N12: 1436576.2 | O12: =N12-M12 -> 529.93
B13: =B12+1 -> 46059 | C13: =TEXT(B13,"DDD") -> Fri | D13: =E12 -> 284490.6 | E13: 284544.1 | F13: =E13-D13 -> 53.5 | G13: =H12 -> 1329947.3 | H13: 1330433.6 | I13: =H13-G13 -> 486.3 | K13: =K12+1 -> 46059 | L13: =TEXT(K13,"DDD") -> Fri | M13: =N12 -> 1436576.2 | N13: 1437899.2 | O13: =N13-M13 -> 1322.98
B14: =B13+1 -> 46060 | C14: =TEXT(B14,"DDD") -> Sat | D14: =E13 -> 284544.1 | E14: 284598.4 | F14: =E14-D14 -> 54.3 | G14: =H13 -> 1330433.6 | H14: 1330752.6 | I14: =H14-G14 -> 319 | K14: =K13+1 -> 46060 | L14: =TEXT(K14,"DDD") -> Sat | M14: =N13 -> 1437899.2 | N14: 1438070.8 | O14: =N14-M14 -> 171.58
B15: =B14+1 -> 46061 | C15: =TEXT(B15,"DDD") -> Sun | D15: =E14 -> 284598.4 | E15: 284631.5 | F15: =E15-D15 -> 33.1 | G15: =H14 -> 1330752.6 | H15: 1330971.8 | I15: =H15-G15 -> 219.2 | K15: =K14+1 -> 46061 | L15: =TEXT(K15,"DDD") -> Sun | M15: =N14 -> 1438070.8 | N15: 1438130.8 | O15: =N15-M15 -> 59.99
B16: =B15+1 -> 46062 | C16: =TEXT(B16,"DDD") -> Mon | D16: =E15 -> 284631.5 | E16: 284712.5 | F16: =E16-D16 -> 81 | G16: =H15 -> 1330971.8 | H16: 1331525.3 | I16: =H16-G16 -> 553.5 | K16: =K15+1 -> 46062 | L16: =TEXT(K16,"DDD") -> Mon | M16: =N15 -> 1438130.8 | N16: 1444832.1 | O16: =N16-M16 -> 6701.34
B17: =B16+1 -> 46063 | C17: =TEXT(B17,"DDD") -> Tue | D17: =E16 -> 284712.5 | E17: 284776.1 | F17: =E17-D17 -> 63.6 | G17: =H16 -> 1331525.3 | H17: 1332065.3 | I17: =H17-G17 -> 540 | K17: =K16+1 -> 46063 | L17: =TEXT(K17,"DDD") -> Tue | M17: =N16 -> 1444832.1 | N17: 1449575 | O17: =N17-M17 -> 4742.83
B18: =B17+1 -> 46064 | C18: =TEXT(B18,"DDD") -> Wed | D18: =E17 -> 284776.1 | E18: 284852 | F18: =E18-D18 -> 75.9 | G18: =H17 -> 1332065.3 | H18: 1332629.3 | I18: =H18-G18 -> 564 | K18: =K17+1 -> 46064 | L18: =TEXT(K18,"DDD") -> Wed | M18: =N17 -> 1449575 | N18: 1454891.2 | O18: =N18-M18 -> 5316.19
B19: =B18+1 -> 46065 | C19: =TEXT(B19,"DDD") -> Thu | D19: =E18 -> 284852 | E19: 284922.5 | F19: =E19-D19 -> 70.5 | G19: =H18 -> 1332629.3 | H19: 1333201.2 | I19: =H19-G19 -> 571.9 | K19: =K18+1 -> 46065 | L19: =TEXT(K19,"DDD") -> Thu | M19: =N18 -> 1454891.2 | N19: 1458490.3 | O19: =N19-M19 -> 3599.14
B20: =B19+1 -> 46066 | C20: =TEXT(B20,"DDD") -> Fri | D20: =E19 -> 284922.5 | E20: 284991 | F20: =E20-D20 -> 68.5 | G20: =H19 -> 1333201.2 | H20: 1333741.3 | I20: =H20-G20 -> 540.1 | K20: =K19+1 -> 46066 | L20: =TEXT(K20,"DDD") -> Fri | M20: =N19 -> 1458490.3 | N20: 1460190.4 | O20: =N20-M20 -> 1700.12
... B24: =B23+1 -> 46070 | C24: =TEXT(B24,"DDD") -> Tue | D24: =E23 -> 285160.5 | E24: 285239.5 | F24: =E24-D24 -> 79 | G24: =H23 -> 1334918.5 | H24: 1335473.7 | I24: =H24-G24 -> 555.2 | K24: =K23+1 -> 46070 | L24: =TEXT(K24,"DDD") -> Tue | M24: =N23 -> 1464270.6 | N24: 1468316.3 | O24: =N24-M24 -> 4045.66
B25: =B24+1 -> 46071 | C25: =TEXT(B25,"DDD") -> Wed | D25: =E24 -> 285239.5 | F25: =E25-D25 -> -285239.5 | G25: =H24 -> 1335473.7 | I25: =H25-G25 -> -1335473.7 | K25: =K24+1 -> 46071 | L25: =TEXT(K25,"DDD") -> Wed | M25: =N24 -> 1468316.3 | O25: =N25-M25 -> -1468316.3
B26: =B25+1 -> 46072 | C26: =TEXT(B26,"DDD") -> Thu | D26: =E25 -> 0 | F26: =E26-D26 -> 0 | G26: =H25 -> 0 | I26: =H26-G26 -> 0 | K26: =K25+1 -> 46072 | L26: =TEXT(K26,"DDD") -> Thu | M26: =N25 -> 0 | O26: =N26-M26 -> 0
B27: =B26+1 -> 46073 | C27: =TEXT(B27,"DDD") -> Fri | D27: =E26 -> 0 | F27: =E27-D27 -> 0 | G27: =H26 -> 0 | I27: =H27-G27 -> 0 | K27: =K26+1 -> 46073 | L27: =TEXT(K27,"DDD") -> Fri | M27: =N26 -> 0 | O27: =N27-M27 -> 0
B28: =B27+1 -> 46074 | C28: =TEXT(B28,"DDD") -> Sat | D28: =E27 -> 0 | F28: =E28-D28 -> 0 | G28: =H27 -> 0 | I28: =H28-G28 -> 0 | K28: =K27+1 -> 46074 | L28: =TEXT(K28,"DDD") -> Sat | M28: =N27 -> 0 | O28: =N28-M28 -> 0
B29: =B28+1 -> 46075 | C29: =TEXT(B29,"DDD") -> Sun | D29: =E28 -> 0 | F29: =E29-D29 -> 0 | G29: =H28 -> 0 | I29: =H29-G29 -> 0 | K29: =K28+1 -> 46075 | L29: =TEXT(K29,"DDD") -> Sun | M29: =N28 -> 0 | O29: =N29-M29 -> 0
B30: =B29+1 -> 46076 | C30: =TEXT(B30,"DDD") -> Mon | D30: =E29 -> 0 | F30: =E30-D30 -> 0 | G30: =H29 -> 0 | I30: =H30-G30 -> 0 | K30: =K29+1 -> 46076 | L30: =TEXT(K30,"DDD") -> Mon | M30: =N29 -> 0 | O30: =N30-M30 -> 0
B31: =B30+1 -> 46077 | C31: =TEXT(B31,"DDD") -> Tue | D31: =E30 -> 0 | F31: =E31-D31 -> 0 | G31: =H30 -> 0 | I31: =H31-G31 -> 0 | K31: =K30+1 -> 46077 | L31: =TEXT(K31,"DDD") -> Tue | M31: =N30 -> 0 | O31: =N31-M31 -> 0
B32: =B31+1 -> 46078 | C32: =TEXT(B32,"DDD") -> Wed | D32: =E31 -> 0 | F32: =E32-D32 -> 0 | G32: =H31 -> 0 | I32: =H32-G32 -> 0 | K32: =K31+1 -> 46078 | L32: =TEXT(K32,"DDD") -> Wed | M32: =N31 -> 0 | O32: =N32-M32 -> 0
B33: =B32+1 -> 46079 | C33: =TEXT(B33,"DDD") -> Thu | D33: =E32 -> 0 | F33: =E33-D33 -> 0 | G33: =H32 -> 0 | I33: =H33-G33 -> 0 | K33: =K32+1 -> 46079 | L33: =TEXT(K33,"DDD") -> Thu | M33: =N32 -> 0 | O33: =N33-M33 -> 0
B34: =B33+1 -> 46080 | C34: =TEXT(B34,"DDD") -> Fri | D34: =E33 -> 0 | F34: =E34-D34 -> 0 | G34: =H33 -> 0 | I34: =H34-G34 -> 0 | K34: =K33+1 -> 46080 | L34: =TEXT(K34,"DDD") -> Fri | M34: =N33 -> 0 | O34: =N34-M34 -> 0
B35: =B34+1 -> 46081 | C35: =TEXT(B35,"DDD") -> Sat | D35: =E34 -> 0 | F35: =E35-D35 -> 0 | G35: =H34 -> 0 | I35: =H35-G35 -> 0 | K35: =K34+1 -> 46081 | L35: =TEXT(K35,"DDD") -> Sat | M35: =N34 -> 0 | O35: =N35-M35 -> 0
B36: =B35+1 -> 46082 | C36: =TEXT(B36,"DDD") -> Sun | D36: =E35 -> 0 | F36: =E36-D36 -> 0 | G36: =H35 -> 0 | I36: =H36-G36 -> 0 | K36: =K35+1 -> 46082 | L36: =TEXT(K36,"DDD") -> Sun | M36: =N35 -> 0 | O36: =N36-M36 -> 0
... B38: =B37+1 -> 46084 | C38: =TEXT(B38,"DDD") -> Tue | D38: =E37 -> 0 | F38: =E38-D38 -> 0 | G38: =H37 -> 0 | I38: =H38-G38 -> 0 | K38: =K37+1 -> 46084 | L38: =TEXT(K38,"DDD") -> Tue | M38: =N37 -> 0 | O38: =N38-M38 -> 0
B39: TOTAL | F39: =SUMIF(F8:F38, ">=0") -> 1078 | I39: =SUMIF(I8:I38, ">=0") -> 7947.6 | O39: =SUMIF(O8:O38, ">=0") -> 42553.86

Sheet OutSide Meter
B2: =Summary!$R$5&" MSEDCL Office Utility MSEB and DG Meter Reading "&TEXT(Summary!R$4,"MMM YY") -> SOC MSEDCL Office Utility MSEB and DG Meter Reading Feb 26 | L2: =Summary!$R$5&" MSEDCL Office Utility MSEB and DG Meter Reading "&TEXT(Summary!R4,"MMM YY") -> SOC MSEDCL Office Utility MSEB and DG Meter Reading Feb 26 | V2: =Summary!$R$5&" Building Meter Reading "&TEXT(Summary!R4,"MMM YY") -> SOC Building Meter Reading Feb 26 | AD2: ="A - Wing Chiller Panel "&TEXT(Summary!R4,"MMM YY") -> A - Wing Chiller Panel Feb 26
C3: Utility EB (KWH) | G3: Utility DG (KWH) | M3: Utility EB (KVAH) | Q3: Utility DG (KVAH) | V3: Date | W3: (KWH) | Z3: (KVAH) | AE3: EB | AH3: DG
B4: Auto | F4: Auto | J4: Auto | L4: Auto | P4: Auto | T4: Auto | V4: Auto | Y4: Auto | AB4: Auto | AD4: Auto | AG4: Auto | AJ4: Auto
B5: Date | C5: Opening | D5: Closening | E5: MF | F5: MWH Cons | G5: Opening | H5: Closening | I5: MF | J5: MWH Cons | L5: Date | M5: Opening | N5: Closening | O5: MF | P5: MWH Cons | Q5: Opening | R5: Closening | S5: MF | T5: MWH Cons | W5: Opening | X5: Closening | Y5: MWH Cons | Z5: Opening | AA5: Closening | AB5: MWH Cons | AD5: Date | AE5: Opening | AF5: Closening | AG5: MWH Cons | AH5: Opening | AI5: Closening | AJ5: MWH Cons
B6: =B7-1 -> 46053 | C6: 4689 | D6: 4694 | E6: 40 | F6: =E6*(D6-C6) -> 200 | G6: 14 | H6: 16 | I6: 40 | J6: =I6*(H6-G6) -> 80 | L6: =L7-1 -> 46053 | M6: 4819 | N6: 4824 | O6: 40 | P6: =O6*(N6-M6) -> 200 | Q6: 15 | R6: 16 | S6: 0 | T6: =S6*(R6-Q6) -> 0 | V6: =V7-1 -> 46053 | W6: 73097 | X6: 73415 | Y6: =X6-W6 -> 318 | Z6: 78880 | AA6: 79212 | AB6: =AA6-Z6 -> 332 | AD6: =AD7-1 -> 46053 | AE6: 2542.9686 | AF6: 2545.819 | AG6: =AF6-AE6 -> 2.8504 | AH6: 2107.74 | AI6: 2382.7286 | AJ6: =AI6-AH6 -> 274.9886
B7: =Summary!R4 -> 46054 | C7: =D6 -> 4694 | D7: 4699 | E7: 40 | F7: =E7*(D7-C7) -> 200 | G7: =H6 -> 16 | H7: 16 | I7: 40 | J7: =I7*(H7-G7) -> 0 | L7: =Summary!R4 -> 46054 | M7: =N6 -> 4824 | N7: 4829 | O7: 40 | P7: =O7*(N7-M7) -> 200 | Q7: =R6 -> 16 | R7: 16 | S7: 0 | T7: =S7*(R7-Q7) -> 0 | V7: =Summary!R4 -> 46054 | W7: =X6 -> 73415 | X7: 73671 | Y7: =X7-W7 -> 256 | Z7: =AA6 -> 79212 | AA7: 79480 | AB7: =AA7-Z7 -> 268 | AD7: =Summary!R4 -> 46054 | AE7: =AF6 -> 2545.819 | AF7: 2548.097 | AG7: =AF7-AE7 -> 2.278 | AH7: =AI6 -> 2382.7286 | AI7: 2382.7286 | AJ7: =AI7-AH7 -> 0
B8: =B7+1 -> 46055 | C8: =D7 -> 4699 | D8: 4705 | E8: 40 | F8: =E8*(D8-C8) -> 240 | G8: =H7 -> 16 | H8: 16 | I8: 40 | J8: =I8*(H8-G8) -> 0 | L8: =L7+1 -> 46055 | M8: =N7 -> 4829 | N8: 4835 | O8: 40 | P8: =O8*(N8-M8) -> 240 | Q8: =R7 -> 16 | R8: 16 | S8: 0 | T8: =S8*(R8-Q8) -> 0 | V8: =V7+1 -> 46055 | W8: =X7 -> 73671 | X8: 73999 | Y8: =X8-W8 -> 328 | Z8: =AA7 -> 79480 | AA8: 79822 | AB8: =AA8-Z8 -> 342 | AD8: =AD7+1 -> 46055 | AE8: =AF7 -> 2548.097 | AF8: 2551.982 | AG8: =AF8-AE8 -> 3.885 | AH8: =AI7 -> 2382.7286 | AI8: 2382.7286 | AJ8: =AI8-AH8 -> 0
B9: =B8+1 -> 46056 | C9: =D8 -> 4705 | D9: 4710 | E9: 40 | F9: =E9*(D9-C9) -> 200 | G9: =H8 -> 16 | H9: 16 | I9: 40 | J9: =I9*(H9-G9) -> 0 | L9: =L8+1 -> 46056 | M9: =N8 -> 4835 | N9: 4841 | O9: 40 | P9: =O9*(N9-M9) -> 240 | Q9: =R8 -> 16 | R9: 16 | S9: 0 | T9: =S9*(R9-Q9) -> 0 | V9: =V8+1 -> 46056 | W9: =X8 -> 73999 | X9: 74288 | Y9: =X9-W9 -> 289 | Z9: =AA8 -> 79822 | AA9: 80140 | AB9: =AA9-Z9 -> 318 | AD9: =AD8+1 -> 46056 | AE9: =AF8 -> 2551.982 | AF9: 2555.409 | AG9: =AF9-AE9 -> 3.427 | AH9: =AI8 -> 2382.7286 | AI9: 2382.7286 | AJ9: =AI9-AH9 -> 0
B10: =B9+1 -> 46057 | C10: =D9 -> 4710 | D10: 4713 | E10: 40 | F10: =E10*(D10-C10) -> 120 | G10: =H9 -> 16 | H10: 16 | I10: 40 | J10: =I10*(H10-G10) -> 0 | L10: =L9+1 -> 46057 | M10: =N9 -> 4841 | N10: 4845 | O10: 40 | P10: =O10*(N10-M10) -> 160 | Q10: =R9 -> 16 | R10: 16 | S10: 0 | T10: =S10*(R10-Q10) -> 0 | V10: =V9+1 -> 46057 | W10: =X9 -> 74288 | X10: 74683 | Y10: =X10-W10 -> 395 | Z10: =AA9 -> 80140 | AA10: 80559 | AB10: =AA10-Z10 -> 419 | AD10: =AD9+1 -> 46057 | AE10: =AF9 -> 2555.409 | AF10: 2557.4954 | AG10: =AF10-AE10 -> 2.0864 | AH10: =AI9 -> 2382.7286 | AI10: 2382.7286 | AJ10: =AI10-AH10 -> 0
B11: =B10+1 -> 46058 | C11: =D10 -> 4713 | D11: 4720 | E11: 40 | F11: =E11*(D11-C11) -> 280 | G11: =H10 -> 16 | H11: 16 | I11: 40 | J11: =I11*(H11-G11) -> 0 | L11: =L10+1 -> 46058 | M11: =N10 -> 4845 | N11: 4851 | O11: 40 | P11: =O11*(N11-M11) -> 240 | Q11: =R10 -> 16 | R11: 16 | S11: 0 | T11: =S11*(R11-Q11) -> 0 | V11: =V10+1 -> 46058 | W11: =X10 -> 74683 | X11: 75102 | Y11: =X11-W11 -> 419 | Z11: =AA10 -> 80559 | AA11: 81010 | AB11: =AA11-Z11 -> 451 | AD11: =AD10+1 -> 46058 | AE11: =AF10 -> 2557.4954 | AF11: 2561.111 | AG11: =AF11-AE11 -> 3.6156 | AH11: =AI10 -> 2382.7286 | AI11: 2382.7286 | AJ11: =AI11-AH11 -> 0
B12: =B11+1 -> 46059 | C12: =D11 -> 4720 | D12: 4728 | E12: 40 | F12: =E12*(D12-C12) -> 320 | G12: =H11 -> 16 | H12: 16 | I12: 40 | J12: =I12*(H12-G12) -> 0 | L12: =L11+1 -> 46059 | M12: =N11 -> 4851 | N12: 4859 | O12: 40 | P12: =O12*(N12-M12) -> 320 | Q12: =R11 -> 16 | R12: 16 | S12: 0 | T12: =S12*(R12-Q12) -> 0 | V12: =V11+1 -> 46059 | W12: =X11 -> 75102 | X12: 75526 | Y12: =X12-W12 -> 424 | Z12: =AA11 -> 81010 | AA12: 81466 | AB12: =AA12-Z12 -> 456 | AD12: =AD11+1 -> 46059 | AE12: =AF11 -> 2561.111 | AF12: 2564.7158 | AG12: =AF12-AE12 -> 3.6048 | AH12: =AI11 -> 2382.7286 | AI12: 2382.7286 | AJ12: =AI12-AH12 -> 0
B13: =B12+1 -> 46060 | C13: =D12 -> 4728 | D13: 4735 | E13: 40 | F13: =E13*(D13-C13) -> 280 | G13: =H12 -> 16 | H13: 16 | I13: 40 | J13: =I13*(H13-G13) -> 0 | L13: =L12+1 -> 46060 | M13: =N12 -> 4859 | N13: 4866 | O13: 40 | P13: =O13*(N13-M13) -> 280 | Q13: =R12 -> 16 | R13: 16 | S13: 0 | T13: =S13*(R13-Q13) -> 0 | V13: =V12+1 -> 46060 | W13: =X12 -> 75526 | X13: 75948 | Y13: =X13-W13 -> 422 | Z13: =AA12 -> 81466 | AA13: 82351 | AB13: =AA13-Z13 -> 885 | AD13: =AD12+1 -> 46060 | AE13: =AF12 -> 2564.7158 | AF13: 2568.4182 | AG13: =AF13-AE13 -> 3.7024 | AH13: =AI12 -> 2382.7286 | AI13: 2382.7286 | AJ13: =AI13-AH13 -> 0
B14: =B13+1 -> 46061 | C14: =D13 -> 4735 | D14: 4743 | E14: 40 | F14: =E14*(D14-C14) -> 320 | G14: =H13 -> 16 | H14: 16 | I14: 40 | J14: =I14*(H14-G14) -> 0 | L14: =L13+1 -> 46061 | M14: =N13 -> 4866 | N14: 4875 | O14: 40 | P14: =O14*(N14-M14) -> 360 | Q14: =R13 -> 16 | R14: 16 | S14: 0 | T14: =S14*(R14-Q14) -> 0 | V14: =V13+1 -> 46061 | W14: =X13 -> 75948 | X14: 76779 | Y14: =X14-W14 -> 831 | Z14: =AA13 -> 82351 | AA14: 82784 | AB14: =AA14-Z14 -> 433 | AD14: =AD13+1 -> 46061 | AE14: =AF13 -> 2568.4182 | AF14: 2572.03 | AG14: =AF14-AE14 -> 3.6118 | AH14: =AI13 -> 2382.7286 | AI14: 2382.7286 | AJ14: =AI14-AH14 -> 0
B15: =B14+1 -> 46062 | C15: =D14 -> 4743 | D15: 4750 | E15: 40 | F15: =E15*(D15-C15) -> 280 | G15: =H14 -> 16 | H15: 16 | I15: 40 | J15: =I15*(H15-G15) -> 0 | L15: =L14+1 -> 46062 | M15: =N14 -> 4875 | N15: 4883 | O15: 40 | P15: =O15*(N15-M15) -> 320 | Q15: =R14 -> 16 | R15: 16 | S15: 0 | T15: =S15*(R15-Q15) -> 0 | V15: =V14+1 -> 46062 | W15: =X14 -> 76779 | X15: 77087 | Y15: =X15-W15 -> 308 | Z15: =AA14 -> 82784 | AA15: 83133 | AB15: =AA15-Z15 -> 349 | AD15: =AD14+1 -> 46062 | AE15: =AF14 -> 2572.03 | AF15: 2575.6252 | AG15: =AF15-AE15 -> 3.5952 | AH15: =AI14 -> 2382.7286 | AI15: 2382.7286 | AJ15: =AI15-AH15 -> 0
B16: =B15+1 -> 46063 | C16: =D15 -> 4750 | D16: 4756 | E16: 40 | F16: =E16*(D16-C16) -> 240 | G16: =H15 -> 16 | H16: 16 | I16: 40 | J16: =I16*(H16-G16) -> 0 | L16: =L15+1 -> 46063 | M16: =N15 -> 4883 | N16: 4889 | O16: 40 | P16: =O16*(N16-M16) -> 240 | Q16: =R15 -> 16 | R16: 16 | S16: 0 | T16: =S16*(R16-Q16) -> 0 | V16: =V15+1 -> 46063 | W16: =X15 -> 77087 | X16: 77298 | Y16: =X16-W16 -> 211 | Z16: =AA15 -> 83133 | AA16: 83316 | AB16: =AA16-Z16 -> 183 | AD16: =AD15+1 -> 46063 | AE16: =AF15 -> 2575.6252 | AF16: 2577.9838 | AG16: =AF16-AE16 -> 2.3586 | AH16: =AI15 -> 2382.7286 | AI16: 2382.7286 | AJ16: =AI16-AH16 -> 0
B17: =B16+1 -> 46064 | C17: =D16 -> 4756 | D17: 4759 | E17: 40 | F17: =E17*(D17-C17) -> 120 | G17: =H16 -> 16 | H17: 16 | I17: 40 | J17: =I17*(H17-G17) -> 0 | L17: =L16+1 -> 46064 | M17: =N16 -> 4889 | N17: 4892 | O17: 40 | P17: =O17*(N17-M17) -> 120 | Q17: =R16 -> 16 | R17: 16 | S17: 0 | T17: =S17*(R17-Q17) -> 0 | V17: =V16+1 -> 46064 | W17: =X16 -> 77298 | X17: 77720 | Y17: =X17-W17 -> 422 | Z17: =AA16 -> 83316 | AA17: 83759 | AB17: =AA17-Z17 -> 443 | AD17: =AD16+1 -> 46064 | AE17: =AF16 -> 2577.9838 | AF17: 2579.9116 | AG17: =AF17-AE17 -> 1.9278 | AH17: =AI16 -> 2382.7286 | AI17: 2382.7286 | AJ17: =AI17-AH17 -> 0
B18: =B17+1 -> 46065 | C18: =D17 -> 4759 | D18: 4765 | E18: 40 | F18: =E18*(D18-C18) -> 240 | G18: =H17 -> 16 | H18: 16 | I18: 40 | J18: =I18*(H18-G18) -> 0 | L18: =L17+1 -> 46065 | M18: =N17 -> 4892 | N18: 4898 | O18: 40 | P18: =O18*(N18-M18) -> 240 | Q18: =R17 -> 16 | R18: 16 | S18: 0 | T18: =S18*(R18-Q18) -> 0 | V18: =V17+1 -> 46065 | W18: =X17 -> 77720 | X18: 78171 | Y18: =X18-W18 -> 451 | Z18: =AA17 -> 83759 | AA18: 84232 | AB18: =AA18-Z18 -> 473 | AD18: =AD17+1 -> 46065 | AE18: =AF17 -> 2579.9116 | AF18: 2583.906 | AG18: =AF18-AE18 -> 3.9944 | AH18: =AI17 -> 2382.7286 | AI18: 2382.7286 | AJ18: =AI18-AH18 -> 0
B19: =B18+1 -> 46066 | C19: =D18 -> 4765 | D19: 4773 | E19: 40 | F19: =E19*(D19-C19) -> 320 | G19: =H18 -> 16 | H19: 16 | I19: 40 | J19: =I19*(H19-G19) -> 0 | L19: =L18+1 -> 46066 | M19: =N18 -> 4898 | N19: 4908 | O19: 40 | P19: =O19*(N19-M19) -> 400 | Q19: =R18 -> 16 | R19: 16 | S19: 0 | T19: =S19*(R19-Q19) -> 0 | V19: =V18+1 -> 46066 | W19: =X18 -> 78171 | X19: 78635 | Y19: =X19-W19 -> 464 | Z19: =AA18 -> 84232 | AA19: 84722 | AB19: =AA19-Z19 -> 490 | AD19: =AD18+1 -> 46066 | AE19: =AF18 -> 2583.906 | AF19: 2588.1932 | AG19: =AF19-AE19 -> 4.2872 | AH19: =AI18 -> 2382.7286 | AI19: 2382.7286 | AJ19: =AI19-AH19 -> 0
... B22: =B21+1 -> 46069 | C22: =D21 -> 4788 | D22: 4796 | E22: 40 | F22: =E22*(D22-C22) -> 320 | G22: =H21 -> 16 | H22: 16 | I22: 40 | J22: =I22*(H22-G22) -> 0 | L22: =L21+1 -> 46069 | M22: =N21 -> 4922 | N22: 4930 | O22: 40 | P22: =O22*(N22-M22) -> 320 | Q22: =R21 -> 16 | R22: 16 | S22: 0 | T22: =S22*(R22-Q22) -> 0 | V22: =V21+1 -> 46069 | W22: =X21 -> 79397 | X22: 79816 | Y22: =X22-W22 -> 419 | Z22: =AA21 -> 85516 | AA22: 85967 | AB22: =AA22-Z22 -> 451 | AD22: =AD21+1 -> 46069 | AE22: =AF21 -> 2595.7468 | AF22: 2600.2302 | AG22: =AF22-AE22 -> 4.4834 | AH22: =AI21 -> 2382.7286 | AI22: 2382.7286 | AJ22: =AI22-AH22 -> 0
B23: =B22+1 -> 46070 | C23: =D22 -> 4796 | D23: 4801 | E23: 40 | F23: =E23*(D23-C23) -> 200 | G23: =H22 -> 16 | H23: 16 | I23: 40 | J23: =I23*(H23-G23) -> 0 | L23: =L22+1 -> 46070 | M23: =N22 -> 4930 | N23: 4935 | O23: 40 | P23: =O23*(N23-M23) -> 200 | Q23: =R22 -> 16 | R23: 16 | S23: 0 | T23: =S23*(R23-Q23) -> 0 | V23: =V22+1 -> 46070 | W23: =X22 -> 79816 | Y23: =X23-W23 -> -79816 | Z23: =AA22 -> 85967 | AB23: =AA23-Z23 -> -85967 | AD23: =AD22+1 -> 46070 | AE23: =AF22 -> 2600.2302 | AF23: 2603.7626 | AG23: =AF23-AE23 -> 3.5324 | AH23: =AI22 -> 2382.7286 | AI23: 2382.7286 | AJ23: =AI23-AH23 -> 0
B24: =B23+1 -> 46071 | C24: =D23 -> 4801 | D24: 4804 | E24: 40 | F24: =E24*(D24-C24) -> 120 | G24: =H23 -> 16 | H24: 16 | I24: 40 | J24: =I24*(H24-G24) -> 0 | L24: =L23+1 -> 46071 | M24: =N23 -> 4935 | N24: 4940 | O24: 40 | P24: =O24*(N24-M24) -> 200 | Q24: =R23 -> 16 | R24: 16 | S24: 0 | T24: =S24*(R24-Q24) -> 0 | V24: =V23+1 -> 46071 | W24: =X23 -> 0 | X24: 80092 | Y24: =X24-W24 -> 80092 | Z24: =AA23 -> 0 | AA24: 86285 | AB24: =AA24-Z24 -> 86285 | AD24: =AD23+1 -> 46071 | AE24: =AF23 -> 2603.7626 | AF24: 2606.125 | AG24: =AF24-AE24 -> 2.3624 | AH24: =AI23 -> 2382.7286 | AI24: 2382.7286 | AJ24: =AI24-AH24 -> 0
B25: =B24+1 -> 46072 | C25: =D24 -> 4804 | D25: 4811 | E25: 40 | F25: =E25*(D25-C25) -> 280 | G25: =H24 -> 16 | H25: 16 | I25: 40 | J25: =I25*(H25-G25) -> 0 | L25: =L24+1 -> 46072 | M25: =N24 -> 4940 | N25: 4947 | O25: 40 | P25: =O25*(N25-M25) -> 280 | Q25: =R24 -> 16 | R25: 16 | S25: 0 | T25: =S25*(R25-Q25) -> 0 | V25: =V24+1 -> 46072 | W25: =X24 -> 80092 | X25: 80532 | Y25: =X25-W25 -> 440 | Z25: =AA24 -> 86285 | AA25: 86711 | AB25: =AA25-Z25 -> 426 | AD25: =AD24+1 -> 46072 | AE25: =AF24 -> 2606.125 | AF25: 2610.2896 | AG25: =AF25-AE25 -> 4.1646 | AH25: =AI24 -> 2382.7286 | AI25: 2382.7286 | AJ25: =AI25-AH25 -> 0
B26: =B25+1 -> 46073 | C26: =D25 -> 4811 | D26: 4819 | E26: 40 | F26: =E26*(D26-C26) -> 320 | G26: =H25 -> 16 | H26: 16 | I26: 40 | J26: =I26*(H26-G26) -> 0 | L26: =L25+1 -> 46073 | M26: =N25 -> 4947 | N26: 4955 | O26: 40 | P26: =O26*(N26-M26) -> 320 | Q26: =R25 -> 16 | R26: 16 | S26: 0 | T26: =S26*(R26-Q26) -> 0 | V26: =V25+1 -> 46073 | W26: =X25 -> 80532 | X26: 80990 | Y26: =X26-W26 -> 458 | Z26: =AA25 -> 86711 | AA26: 87196 | AB26: =AA26-Z26 -> 485 | AD26: =AD25+1 -> 46073 | AE26: =AF25 -> 2610.2896 | AF26: 2614.6504 | AG26: =AF26-AE26 -> 4.3608 | AH26: =AI25 -> 2382.7286 | AI26: 2382.7286 | AJ26: =AI26-AH26 -> 0
B27: =B26+1 -> 46074 | C27: =D26 -> 4819 | D27: 4826 | E27: 40 | F27: =E27*(D27-C27) -> 280 | G27: =H26 -> 16 | H27: 16 | I27: 40 | J27: =I27*(H27-G27) -> 0 | L27: =L26+1 -> 46074 | M27: =N26 -> 4955 | N27: 4963 | O27: 40 | P27: =O27*(N27-M27) -> 320 | Q27: =R26 -> 16 | R27: 16 | S27: 0 | T27: =S27*(R27-Q27) -> 0 | V27: =V26+1 -> 46074 | W27: =X26 -> 80990 | X27: 81443 | Y27: =X27-W27 -> 453 | Z27: =AA26 -> 87196 | AA27: 87686 | AB27: =AA27-Z27 -> 490 | AD27: =AD26+1 -> 46074 | AE27: =AF26 -> 2614.6504 | AF27: 2618.82 | AG27: =AF27-AE27 -> 4.1696 | AH27: =AI26 -> 2382.7286 | AI27: 2382.7286 | AJ27: =AI27-AH27 -> 0
B28: =B27+1 -> 46075 | C28: =D27 -> 4826 | D28: 4834 | E28: 40 | F28: =E28*(D28-C28) -> 320 | G28: =H27 -> 16 | H28: 16 | I28: 40 | J28: =I28*(H28-G28) -> 0 | L28: =L27+1 -> 46075 | M28: =N27 -> 4963 | N28: 4971 | O28: 40 | P28: =O28*(N28-M28) -> 320 | Q28: =R27 -> 16 | R28: 16 | S28: 0 | T28: =S28*(R28-Q28) -> 0 | V28: =V27+1 -> 46075 | W28: =X27 -> 81443 | X28: 81888 | Y28: =X28-W28 -> 445 | Z28: =AA27 -> 87686 | AA28: 88164 | AB28: =AA28-Z28 -> 478 | AD28: =AD27+1 -> 46075 | AE28: =AF27 -> 2618.82 | AF28: 2622.95 | AG28: =AF28-AE28 -> 4.13 | AH28: =AI27 -> 2382.7286 | AI28: 2382.7286 | AJ28: =AI28-AH28 -> 0
B29: =B28+1 -> 46076 | C29: =D28 -> 4834 | D29: 4842 | E29: 40 | F29: =E29*(D29-C29) -> 320 | G29: =H28 -> 16 | H29: 16 | I29: 40 | J29: =I29*(H29-G29) -> 0 | L29: =L28+1 -> 46076 | M29: =N28 -> 4971 | N29: 4979 | O29: 40 | P29: =O29*(N29-M29) -> 320 | Q29: =R28 -> 16 | R29: 16 | S29: 0 | T29: =S29*(R29-Q29) -> 0 | V29: =V28+1 -> 46076 | W29: =X28 -> 81888 | X29: 82313 | Y29: =X29-W29 -> 425 | Z29: =AA28 -> 88164 | AA29: 88619 | AB29: =AA29-Z29 -> 455 | AD29: =AD28+1 -> 46076 | AE29: =AF28 -> 2622.95 | AF29: 2626.6646 | AG29: =AF29-AE29 -> 3.7146 | AH29: =AI28 -> 2382.7286 | AI29: 2382.7286 | AJ29: =AI29-AH29 -> 0
B30: =B29+1 -> 46077 | C30: =D29 -> 4842 | D30: 4847 | E30: 40 | F30: =E30*(D30-C30) -> 200 | G30: =H29 -> 16 | H30: 16 | I30: 40 | J30: =I30*(H30-G30) -> 0 | L30: =L29+1 -> 46077 | M30: =N29 -> 4979 | N30: 4984 | O30: 40 | P30: =O30*(N30-M30) -> 200 | Q30: =R29 -> 16 | R30: 16 | S30: 0 | T30: =S30*(R30-Q30) -> 0 | V30: =V29+1 -> 46077 | W30: =X29 -> 82313 | X30: 82640 | Y30: =X30-W30 -> 327 | Z30: =AA29 -> 88619 | AA30: 88972 | AB30: =AA30-Z30 -> 353 | AD30: =AD29+1 -> 46077 | AE30: =AF29 -> 2626.6646 | AF30: 2629.2758 | AG30: =AF30-AE30 -> 2.6112 | AH30: =AI29 -> 2382.7286 | AI30: 2386.7334 | AJ30: =AI30-AH30 -> 4.0048
B31: =B30+1 -> 46078 | C31: =D30 -> 4847 | D31: 4850 | E31: 40 | F31: =E31*(D31-C31) -> 120 | G31: =H30 -> 16 | H31: 16 | I31: 40 | J31: =I31*(H31-G31) -> 0 | L31: =L30+1 -> 46078 | M31: =N30 -> 4984 | N31: 4987 | O31: 40 | P31: =O31*(N31-M31) -> 120 | Q31: =R30 -> 16 | R31: 16 | S31: 0 | T31: =S31*(R31-Q31) -> 0 | V31: =V30+1 -> 46078 | W31: =X30 -> 82640 | X31: 82891 | Y31: =X31-W31 -> 251 | Z31: =AA30 -> 88972 | AA31: 89225 | AB31: =AA31-Z31 -> 253 | AD31: =AD30+1 -> 46078 | AE31: =AF30 -> 2629.2758 | AF31: 2631.3432 | AG31: =AF31-AE31 -> 2.0674 | AH31: =AI30 -> 2386.7334 | AI31: 2386.7334 | AJ31: =AI31-AH31 -> 0
B32: =B31+1 -> 46079 | C32: =D31 -> 4850 | D32: 4855 | E32: 40 | F32: =E32*(D32-C32) -> 200 | G32: =H31 -> 16 | H32: 16 | I32: 40 | J32: =I32*(H32-G32) -> 0 | L32: =L31+1 -> 46079 | M32: =N31 -> 4987 | N32: 4993 | O32: 40 | P32: =O32*(N32-M32) -> 240 | Q32: =R31 -> 16 | R32: 16 | S32: 0 | T32: =S32*(R32-Q32) -> 0 | V32: =V31+1 -> 46079 | W32: =X31 -> 82891 | X32: 83175 | Y32: =X32-W32 -> 284 | Z32: =AA31 -> 89225 | AA32: 89525 | AB32: =AA32-Z32 -> 300 | AD32: =AD31+1 -> 46079 | AE32: =AF31 -> 2631.3432 | AF32: 2633.6264 | AG32: =AF32-AE32 -> 2.2832 | AH32: =AI31 -> 2386.7334 | AI32: 2386.7334 | AJ32: =AI32-AH32 -> 0
B33: =B32+1 -> 46080 | C33: =D32 -> 4855 | E33: 40 | F33: =E33*(D33-C33) -> -194200 | G33: =H32 -> 16 | I33: 40 | J33: =I33*(H33-G33) -> -640 | L33: =L32+1 -> 46080 | M33: =N32 -> 4993 | O33: 40 | P33: =O33*(N33-M33) -> -199720 | Q33: =R32 -> 16 | S33: 0 | T33: =S33*(R33-Q33) -> 0 | V33: =V32+1 -> 46080 | W33: =X32 -> 83175 | Y33: =X33-W33 -> -83175 | Z33: =AA32 -> 89525 | AB33: =AA33-Z33 -> -89525 | AD33: =AD32+1 -> 46080 | AE33: =AF32 -> 2633.6264 | AG33: =AF33-AE33 -> -2633.6264 | AH33: =AI32 -> 2386.7334 | AJ33: =AI33-AH33 -> -2386.7334
B34: =B33+1 -> 46081 | C34: =D33 -> 0 | E34: 40 | F34: =E34*(D34-C34) -> 0 | G34: =H33 -> 0 | I34: 40 | J34: =I34*(H34-G34) -> 0 | L34: =L33+1 -> 46081 | M34: =N33 -> 0 | O34: 40 | P34: =O34*(N34-M34) -> 0 | Q34: =R33 -> 0 | S34: 0 | T34: =S34*(R34-Q34) -> 0 | V34: =V33+1 -> 46081 | W34: =X33 -> 0 | Y34: =X34-W34 -> 0 | Z34: =AA33 -> 0 | AB34: =AA34-Z34 -> 0 | AD34: =AD33+1 -> 46081 | AE34: =AF33 -> 0 | AG34: =AF34-AE34 -> 0 | AH34: =AI33 -> 0 | AJ34: =AI34-AH34 -> 0
B35: =B34+1 -> 46082 | C35: =D34 -> 0 | E35: 40 | F35: =E35*(D35-C35) -> 0 | G35: =H34 -> 0 | I35: 40 | J35: =I35*(H35-G35) -> 0 | L35: =L34+1 -> 46082 | M35: =N34 -> 0 | O35: 40 | P35: =O35*(N35-M35) -> 0 | Q35: =R34 -> 0 | S35: 0 | T35: =S35*(R35-Q35) -> 0 | V35: =V34+1 -> 46082 | W35: =X34 -> 0 | Y35: =X35-W35 -> 0 | Z35: =AA34 -> 0 | AB35: =AA35-Z35 -> 0 | AD35: =AD34+1 -> 46082 | AE35: =AF34 -> 0 | AG35: =AF35-AE35 -> 0 | AH35: =AI34 -> 0 | AJ35: =AI35-AH35 -> 0
B36: =B35+1 -> 46083 | C36: =D35 -> 0 | E36: 40 | F36: =E36*(D36-C36) -> 0 | G36: =H35 -> 0 | I36: 40 | J36: =I36*(H36-G36) -> 0 | L36: =L35+1 -> 46083 | M36: =N35 -> 0 | O36: 40 | P36: =O36*(N36-M36) -> 0 | Q36: =R35 -> 0 | S36: 0 | T36: =S36*(R36-Q36) -> 0 | V36: =V35+1 -> 46083 | W36: =X35 -> 0 | Y36: =X36-W36 -> 0 | Z36: =AA35 -> 0 | AB36: =AA36-Z36 -> 0 | AD36: =AD35+1 -> 46083 | AE36: =AF35 -> 0 | AG36: =AF36-AE36 -> 0 | AH36: =AI35 -> 0 | AJ36: =AI36-AH36 -> 0
B37: =B36+1 -> 46084 | C37: =D36 -> 0 | E37: 40 | F37: =E37*(D37-C37) -> 0 | G37: =H36 -> 0 | I37: 40 | J37: =I37*(H37-G37) -> 0 | L37: =L36+1 -> 46084 | M37: =N36 -> 0 | O37: 40 | P37: =O37*(N37-M37) -> 0 | Q37: =R36 -> 0 | S37: 0 | T37: =S37*(R37-Q37) -> 0 | V37: =V36+1 -> 46084 | W37: =X36 -> 0 | Y37: =X37-W37 -> 0 | Z37: =AA36 -> 0 | AB37: =AA37-Z37 -> 0 | AD37: =AD36+1 -> 46084 | AE37: =AF36 -> 0 | AG37: =AF37-AE37 -> 0 | AH37: =AI36 -> 0 | AJ37: =AI37-AH37 -> 0
B38: TOTAL | F38: =SUMIF(F6:F37, ">=0") -> 6640 | J38: =SUMIF(J6:J37, ">=0") -> 80 | P38: =SUMIF(P6:P37, ">=0") -> 6960 | T38: =SUMIF(T6:T37, ">=0") -> 0 | Y38: =SUMIF(Y6:Y37, ">=0") -> 89894 | AB38: =SUMIF(AB6:AB37, ">=0") -> 96612 | AG38: =SUMIF(AG6:AG37, ">=0") -> 90.6578 | AJ38: =SUMIF(AJ6:AJ37, ">=0") -> 278.9934

Sheet Bisleri_Consu
B2: =Summary!R5&" Bisleri Material Consumption for the Month of "& TEXT(Summary!R4," MMM YY") -> SOC Bisleri Material Consumption for the Month of Feb 26
N4: Auto | O4: =TEXT(O5,"ddd") -> Sun | P4: =TEXT(P5,"ddd") -> Mon | Q4: =TEXT(Q5,"ddd") -> Tue | R4: =TEXT(R5,"ddd") -> Wed | S4: =TEXT(S5,"ddd") -> Thu | T4: =TEXT(T5,"ddd") -> Fri | U4: =TEXT(U5,"ddd") -> Sat | V4: =TEXT(V5,"ddd") -> Sun | ... AS4: =TEXT(AS5,"ddd") -> Tue | AT4: Auto | AU4: Auto | AV4: Auto | AW4: Auto | AX4: Auto | BA4: Auto
B5: Sr. No. | C5: Vendor | D5: Particulars | E5: Brand | F5: Units | G5: Rate | H5: Opening | I5: Order | J5: Office Order 1 | K5: Office Order 2 | L5: Other Sources | M5: Remark | N5: Total Stock | O5: =Summary!R4 -> 46054 | P5: =O5+1 -> 46055 | Q5: =P5+1 -> 46056 | R5: =Q5+1 -> 46057 | S5: =R5+1 -> 46058 | T5: =S5+1 -> 46059 | U5: =T5+1 -> 46060 | V5: =U5+1 -> 46061 | W5: =V5+1 -> 46062 | ... AS5: =AR5+1 -> 46084 | AT5: Usage Stock | AU5: Closing Stock | AV5: Usage Amount | AW5: Closing Amount | AX5: Order Amount | AY5: CGST | AZ5: SGST | BA5: Order Amount With GST
B6: 1 | C6: Bisleri | D6: Bottle | E6: Bisleri | F6: 500ML | G6: 152.54 | H6: 10 | N6: =SUM(H6:L6) -> 10 | P6: 1 | Q6: 1 | S6: 1 | T6: 1 | W6: 1 | X6: 1 | Y6: 1 | Z6: 1 | AA6: 1 | AD6: 1 | AT6: =SUM(O6:AS6) -> 10 | AU6: =N6-AT6 -> 0 | AV6: =AT6*G6 -> 1525.4 | AW6: =AU6*G6 -> 0 | AX6: =I6*G6 -> 0 | AY6: 9 | AZ6: 9 | BA6: =AX6*SUM(AY6:AZ6)%+AX6 -> 0
B7: 2 | C7: Bisleri | D7: Bottle | E7: Bisleri | F7: 250 ML | G7: 114.41 | H7: 10 | N7: =SUM(H7:L7) -> 10 | P7: 1 | AA7: 1 | AT7: =SUM(O7:AS7) -> 2 | AU7: =N7-AT7 -> 8 | AV7: =AT7*G7 -> 228.82 | AW7: =AU7*G7 -> 915.28 | AX7: =I7*G7 -> 0 | BA7: =AX7*SUM(AY7:AZ7)%+AX7 -> 0
B8: 3 | N8: =SUM(H8:L8) -> 0 | AT8: =SUM(O8:AS8) -> 0 | AU8: =N8-AT8 -> 0 | AV8: =AT8*G8 -> 0 | AW8: =AU8*G8 -> 0 | AX8: =I8*G8 -> 0 | BA8: =AX8*SUM(AY8:AZ8)%+AX8 -> 0
D9: Total | H9: =SUM(H6:H8) -> 20 | I9: =SUM(I6:I8) -> 0 | N9: =SUM(N6:N8) -> 20 | O9: =SUM(O6:O8) -> 0 | P9: =SUM(P6:P8) -> 2 | Q9: =SUM(Q6:Q8) -> 1 | R9: =SUM(R6:R8) -> 0 | S9: =SUM(S6:S8) -> 1 | T9: =SUM(T6:T8) -> 1 | U9: =SUM(U6:U8) -> 0 | ... AR9: =SUM(AR6:AR8) -> 0 | AT9: =SUM(AT6:AT8) -> 12 | AU9: =SUM(AU6:AU8) -> 8 | AV9: =SUM(AV6:AV8) -> 1754.22 | AW9: =SUM(AW6:AW8) -> 915.28 | AX9: =SUM(AX6:AX8) -> 0 | AY9: =SUM(AY6:AY8) -> 9 | AZ9: =SUM(AZ6:AZ8) -> 9 | BA9: =SUM(BA6:BA8) -> 0

Sheet Medical_Items
B2: =Summary!R5&" Medical Material Consumption for the Month of "& TEXT(Summary!R4," MMM YY") -> SOC Medical Material Consumption for the Month of Feb 26
N4: Auto | O4: =TEXT(O5,"ddd") -> Sun | P4: =TEXT(P5,"ddd") -> Mon | Q4: =TEXT(Q5,"ddd") -> Tue | R4: =TEXT(R5,"ddd") -> Wed | S4: =TEXT(S5,"ddd") -> Thu | T4: =TEXT(T5,"ddd") -> Fri | U4: =TEXT(U5,"ddd") -> Sat | V4: =TEXT(V5,"ddd") -> Sun | ... AS4: =TEXT(AS5,"ddd") -> Tue | AT4: Auto | AU4: Auto | AV4: Auto | AW4: Auto | AX4: Auto | BA4: Auto
B5: Sr. No. | C5: Vendor | D5: Particulars | E5: Brand | F5: Units | G5: Rate | H5: Opening | I5: Order | J5: Office Order 1 | K5: Office Order 2 | L5: Other Sources | M5: Remark | N5: Total Stock | O5: =Summary!R4 -> 46054 | P5: =O5+1 -> 46055 | Q5: =P5+1 -> 46056 | R5: =Q5+1 -> 46057 | S5: =R5+1 -> 46058 | T5: =S5+1 -> 46059 | U5: =T5+1 -> 46060 | V5: =U5+1 -> 46061 | W5: =V5+1 -> 46062 | ... AS5: =AR5+1 -> 46084 | AT5: Usage Stock | AU5: Closing Stock | AV5: Usage Amount | AW5: Closing Amount | AX5: Order Amount | AY5: CGST | AZ5: SGST | BA5: Order Amount With GST
B6: 1 | D6: Volini Spray | E6: Volini | F6: Nos | G6: 220 | H6: 3 | I6: 6 | N6: =SUM(H6:L6) -> 9 | R6: 1 | X6: 1 | AT6: =SUM(O6:AS6) -> 2 | AU6: =N6-AT6 -> 7 | AV6: =AT6*G6 -> 440 | AW6: =AU6*G6 -> 1540 | AX6: =I6*G6 -> 1320 | AY6: 9 | AZ6: 9 | BA6: =AX6*SUM(AY6:AZ6)%+AX6 -> 1557.6
B7: 2 | D7: Cipladine Cream | F7: Nos | G7: 52.71 | H7: 1 | I7: 1 | N7: =SUM(H7:L7) -> 2 | AT7: =SUM(O7:AS7) -> 0 | AU7: =N7-AT7 -> 2 | AV7: =AT7*G7 -> 0 | AW7: =AU7*G7 -> 105.42 | AX7: =I7*G7 -> 52.71 | AY7: 9 | AZ7: 9 | BA7: =AX7*SUM(AY7:AZ7)%+AX7 -> 62.1978
B8: 3 | D8: Cipladine Powder | F8: Nos | G8: 90 | H8: 2 | N8: =SUM(H8:L8) -> 2 | AT8: =SUM(O8:AS8) -> 0 | AU8: =N8-AT8 -> 2 | AV8: =AT8*G8 -> 0 | AW8: =AU8*G8 -> 180 | AX8: =I8*G8 -> 0 | AY8: 9 | AZ8: 9 | BA8: =AX8*SUM(AY8:AZ8)%+AX8 -> 0
B9: 4 | D9: Soframycin Cream | F9: Nos | G9: 55.77 | H9: 0 | I9: 1 | N9: =SUM(H9:L9) -> 1 | AT9: =SUM(O9:AS9) -> 0 | AU9: =N9-AT9 -> 1 | AV9: =AT9*G9 -> 0 | AW9: =AU9*G9 -> 55.77 | AX9: =I9*G9 -> 55.77 | AY9: 9 | AZ9: 9 | BA9: =AX9*SUM(AY9:AZ9)%+AX9 -> 65.8086
B10: 5 | D10: Betnovate Cream | F10: Nos | G10: 23.3 | H10: 0 | N10: =SUM(H10:L10) -> 0 | AT10: =SUM(O10:AS10) -> 0 | AU10: =N10-AT10 -> 0 | AV10: =AT10*G10 -> 0 | AW10: =AU10*G10 -> 0 | AX10: =I10*G10 -> 0 | AY10: 9 | AZ10: 9 | BA10: =AX10*SUM(AY10:AZ10)%+AX10 -> 0
B11: 6 | D11: Volini Gel | E11: Volini | F11: Nos | G11: 76 | H11: 3 | N11: =SUM(H11:L11) -> 3 | AT11: =SUM(O11:AS11) -> 0 | AU11: =N11-AT11 -> 3 | AV11: =AT11*G11 -> 0 | AW11: =AU11*G11 -> 228 | AX11: =I11*G11 -> 0 | AY11: 9 | AZ11: 9 | BA11: =AX11*SUM(AY11:AZ11)%+AX11 -> 0
B12: 7 | D12: ORS Powder 20gm | F12: PKT | G12: 22.66 | H12: 22 | I12: 10 | N12: =SUM(H12:L12) -> 32 | R12: 1 | X12: 1 | AT12: =SUM(O12:AS12) -> 2 | AU12: =N12-AT12 -> 30 | AV12: =AT12*G12 -> 45.32 | AW12: =AU12*G12 -> 679.8 | AX12: =I12*G12 -> 226.6 | AY12: 9 | AZ12: 9 | BA12: =AX12*SUM(AY12:AZ12)%+AX12 -> 267.388
B13: 8 | D13: Cotton absorbent big | F13: Roll | G13: 15 | H13: 0 | N13: =SUM(H13:L13) -> 0 | AT13: =SUM(O13:AS13) -> 0 | AU13: =N13-AT13 -> 0 | AV13: =AT13*G13 -> 0 | AW13: =AU13*G13 -> 0 | AX13: =I13*G13 -> 0 | AY13: 9 | AZ13: 9 | BA13: =AX13*SUM(AY13:AZ13)%+AX13 -> 0
B14: 9 | D14: Cotton absorbent Small | F14: Nos | G14: 15 | H14: 2 | N14: =SUM(H14:L14) -> 2 | AT14: =SUM(O14:AS14) -> 0 | AU14: =N14-AT14 -> 2 | AV14: =AT14*G14 -> 0 | AW14: =AU14*G14 -> 30 | AX14: =I14*G14 -> 0 | AY14: 9 | AZ14: 9 | BA14: =AX14*SUM(AY14:AZ14)%+AX14 -> 0
B15: 10 | D15: Cotton Roll | F15: Roll | H15: 0 | N15: =SUM(H15:L15) -> 0 | AT15: =SUM(O15:AS15) -> 0 | AU15: =N15-AT15 -> 0 | AV15: =AT15*G15 -> 0 | AW15: =AU15*G15 -> 0 | AX15: =I15*G15 -> 0 | AY15: 9 | AZ15: 9 | BA15: =AX15*SUM(AY15:AZ15)%+AX15 -> 0
B16: 11 | D16: Glucon-D (Glucose) | F16: Nos | G16: 56 | H16: 2 | I16: 4 | N16: =SUM(H16:L16) -> 6 | AT16: =SUM(O16:AS16) -> 0 | AU16: =N16-AT16 -> 6 | AV16: =AT16*G16 -> 0 | AW16: =AU16*G16 -> 336 | AX16: =I16*G16 -> 224 | AY16: 9 | AZ16: 9 | BA16: =AX16*SUM(AY16:AZ16)%+AX16 -> 264.32
B17: 12 | D17: Seser | F17: Nos | H17: 0 | N17: =SUM(H17:L17) -> 0 | AT17: =SUM(O17:AS17) -> 0 | AU17: =N17-AT17 -> 0 | AV17: =AT17*G17 -> 0 | AW17: =AU17*G17 -> 0 | AX17: =I17*G17 -> 0 | AY17: 9 | AZ17: 9 | BA17: =AX17*SUM(AY17:AZ17)%+AX17 -> 0
B18: 13 | D18: Fixation Tape | F18: Nos | G18: 91 | H18: 0 | N18: =SUM(H18:L18) -> 0 | AT18: =SUM(O18:AS18) -> 0 | AU18: =N18-AT18 -> 0 | AV18: =AT18*G18 -> 0 | AW18: =AU18*G18 -> 0 | AX18: =I18*G18 -> 0 | AY18: 9 | AZ18: 9 | BA18: =AX18*SUM(AY18:AZ18)%+AX18 -> 0
B19: 14 | D19: Gauze Bandage Small | F19: Nos | H19: 10 | N19: =SUM(H19:L19) -> 10 | AT19: =SUM(O19:AS19) -> 0 | AU19: =N19-AT19 -> 10 | AV19: =AT19*G19 -> 0 | AW19: =AU19*G19 -> 0 | AX19: =I19*G19 -> 0 | AY19: 9 | AZ19: 9 | BA19: =AX19*SUM(AY19:AZ19)%+AX19 -> 0
B20: 15 | D20: Whisper choice | F20: Pkt | H20: 3 | N20: =SUM(H20:L20) -> 3 | AT20: =SUM(O20:AS20) -> 0 | AU20: =N20-AT20 -> 3 | AV20: =AT20*G20 -> 0 | AW20: =AU20*G20 -> 0 | AX20: =I20*G20 -> 0 | AY20: 9 | AZ20: 9 | BA20: =AX20*SUM(AY20:AZ20)%+AX20 -> 0
B21: 16 | D21: Hansaplast Spot (Round) | F21: Nos | G21: 2 | H21: 24 | N21: =SUM(H21:L21) -> 24 | AT21: =SUM(O21:AS21) -> 0 | AU21: =N21-AT21 -> 24 | AV21: =AT21*G21 -> 0 | AW21: =AU21*G21 -> 48 | AX21: =I21*G21 -> 0 | AY21: 9 | AZ21: 9 | BA21: =AX21*SUM(AY21:AZ21)%+AX21 -> 0
B22: 17 | D22: Hansaplast Bandage | F22: Nos | G22: 3 | H22: 24 | N22: =SUM(H22:L22) -> 24 | S22: 3 | AT22: =SUM(O22:AS22) -> 3 | AU22: =N22-AT22 -> 21 | AV22: =AT22*G22 -> 9 | AW22: =AU22*G22 -> 63 | AX22: =I22*G22 -> 0 | AY22: 9 | AZ22: 9 | BA22: =AX22*SUM(AY22:AZ22)%+AX22 -> 0
B23: 18 | D23: Dettol Small | F23: Nos | H23: 1 | N23: =SUM(H23:L23) -> 1 | AT23: =SUM(O23:AS23) -> 0 | AU23: =N23-AT23 -> 1 | AV23: =AT23*G23 -> 0 | AW23: =AU23*G23 -> 0 | AX23: =I23*G23 -> 0 | AY23: 9 | AZ23: 9 | BA23: =AX23*SUM(AY23:AZ23)%+AX23 -> 0
H24: 0 | N24: =SUM(H24:L24) -> 0 | AT24: =SUM(O24:AS24) -> 0 | AU24: =N24-AT24 -> 0 | AV24: =AT24*G24 -> 0 | AW24: =AU24*G24 -> 0 | AX24: =I24*G24 -> 0 | AY24: 9 | AZ24: 9 | BA24: =AX24*SUM(AY24:AZ24)%+AX24 -> 0
H25: 0 | N25: =SUM(H25:L25) -> 0 | AT25: =SUM(O25:AS25) -> 0 | AU25: =N25-AT25 -> 0 | AV25: =AT25*G25 -> 0 | AW25: =AU25*G25 -> 0 | AX25: =I25*G25 -> 0 | AY25: 9 | AZ25: 9 | BA25: =AX25*SUM(AY25:AZ25)%+AX25 -> 0
H26: 0 | N26: =SUM(H26:L26) -> 0 | AT26: =SUM(O26:AS26) -> 0 | AU26: =N26-AT26 -> 0 | AV26: =AT26*G26 -> 0 | AW26: =AU26*G26 -> 0 | AX26: =I26*G26 -> 0 | BA26: =AX26*SUM(AY26:AZ26)%+AX26 -> 0
D27: Total | H27: =SUM(H6:H26) -> 97 | I27: =SUM(I6:I26) -> 22 | N27: =SUM(N6:N26) -> 119 | O27: =SUM(O6:O26) -> 0 | P27: =SUM(P6:P26) -> 0 | Q27: =SUM(Q6:Q26) -> 0 | R27: =SUM(R6:R26) -> 2 | S27: =SUM(S6:S26) -> 3 | T27: =SUM(T6:T26) -> 0 | U27: =SUM(U6:U26) -> 0 | ... AR27: =SUM(AR6:AR26) -> 0 | AT27: =SUM(AT6:AT26) -> 7 | AU27: =SUM(AU6:AU26) -> 112 | AV27: =SUM(AV6:AV26) -> 494.32 | AW27: =SUM(AW6:AW26) -> 3265.99 | AX27: =SUM(AX6:AX26) -> 1879.08 | AY27: =SUM(AY6:AY26) -> 180 | AZ27: =SUM(AZ6:AZ26) -> 180 | BA27: =SUM(BA6:BA26) -> 2217.3144

Sheet Stationery
B2: =Summary!R5&" Stationary Material Consumption for the Month of "& TEXT(Summary!R4," MMM YY") -> SOC Stationary Material Consumption for the Month of Feb 26
I4: Auto | J4: =TEXT(J5,"ddd") -> Sun | K4: =TEXT(K5,"ddd") -> Mon | L4: =TEXT(L5,"ddd") -> Tue | M4: =TEXT(M5,"ddd") -> Wed | N4: =TEXT(N5,"ddd") -> Thu | O4: =TEXT(O5,"ddd") -> Fri | P4: =TEXT(P5,"ddd") -> Sat | Q4: =TEXT(Q5,"ddd") -> Sun | ... AN4: =TEXT(AN5,"ddd") -> Tue | AO4: Auto | AP4: Auto | AQ4: Auto | AR4: Auto | AS4: Auto | AV4: Auto
B5: Sr. No. | C5: Particulars | D5: Brand | E5: Units | F5: Rate | G5: Opening | H5: Order | I5: Total Stock | J5: =Summary!R4 -> 46054 | K5: =J5+1 -> 46055 | L5: =K5+1 -> 46056 | M5: =L5+1 -> 46057 | N5: =M5+1 -> 46058 | O5: =N5+1 -> 46059 | P5: =O5+1 -> 46060 | Q5: =P5+1 -> 46061 | R5: =Q5+1 -> 46062 | ... AN5: =AM5+1 -> 46084 | AO5: Usage Stock | AP5: Closing Stock | AQ5: Usage Amount | AR5: Closing Amount | AS5: Order Amount | AT5: CGST | AU5: SGST | AV5: Order Amount With GST | AW5: ACTUAL STOCK
B6: 1 | C6: Spring File | D6: Rajal/Vagad | E6: Nos. | F6: 12 | G6: 10 | I6: =G6+H6 -> 10 | AO6: =SUM(J6:AN6) -> 0 | AP6: =I6-AO6 -> 10 | AQ6: =AO6*F6 -> 0 | AR6: =AP6*F6 -> 120 | AS6: =H6*F6 -> 0 | AV6: =AS6*SUM(AT6:AU6)%+AS6 -> 0
B7: 2 | C7: White Envelop A4 Size | D7: Jemine | E7: Nos. | F7: 3.5 | G7: 25 | I7: =G7+H7 -> 25 | AO7: =SUM(J7:AN7) -> 0 | AP7: =I7-AO7 -> 25 | AQ7: =AO7*F7 -> 0 | AR7: =AP7*F7 -> 87.5 | AS7: =H7*F7 -> 0 | AV7: =AS7*SUM(AT7:AU7)%+AS7 -> 0
B8: 3 | C8: Box File | D8: Rajal/Vagad | E8: Nos. | F8: 62 | G8: 13 | I8: =G8+H8 -> 13 | M8: 2 | V8: 2 | AO8: =SUM(J8:AN8) -> 4 | AP8: =I8-AO8 -> 9 | AQ8: =AO8*F8 -> 248 | AR8: =AP8*F8 -> 558 | AS8: =H8*F8 -> 0 | AV8: =AS8*SUM(AT8:AU8)%+AS8 -> 0
B9: 4 | C9: Writing Pad No. 1 | D9: Vedant | E9: Nos. | F9: 20 | G9: 11 | H9: 10 | I9: =G9+H9 -> 21 | K9: 1 | R9: 3 | V9: 1 | AO9: =SUM(J9:AN9) -> 5 | AP9: =I9-AO9 -> 16 | AQ9: =AO9*F9 -> 100 | AR9: =AP9*F9 -> 320 | AS9: =H9*F9 -> 200 | AV9: =AS9*SUM(AT9:AU9)%+AS9 -> 200
B10: 5 | C10: Conference Pad | D10: Vedant | E10: Nos. | F10: 6.5 | G10: 16 | I10: =G10+H10 -> 16 | AO10: =SUM(J10:AN10) -> 0 | AP10: =I10-AO10 -> 16 | AQ10: =AO10*F10 -> 0 | AR10: =AP10*F10 -> 104 | AS10: =H10*F10 -> 0 | AV10: =AS10*SUM(AT10:AU10)%+AS10 -> 0
B11: 6 | C11: Cheque Envelops | D11: Jemine | E11: Nos. | F11: 1.25 | G11: 16 | I11: =G11+H11 -> 16 | AO11: =SUM(J11:AN11) -> 0 | AP11: =I11-AO11 -> 16 | AQ11: =AO11*F11 -> 0 | AR11: =AP11*F11 -> 20 | AS11: =H11*F11 -> 0 | AV11: =AS11*SUM(AT11:AU11)%+AS11 -> 0
B12: 7 | C12: Cello Tape 1" | D12: Wonder | E12: Nos. | F12: 12 | G12: 8 | H12: 5 | I12: =G12+H12 -> 13 | S12: 1 | AO12: =SUM(J12:AN12) -> 1 | AP12: =I12-AO12 -> 12 | AQ12: =AO12*F12 -> 12 | AR12: =AP12*F12 -> 144 | AS12: =H12*F12 -> 60 | AV12: =AS12*SUM(AT12:AU12)%+AS12 -> 60
B13: 8 | C13: Cello Tape 2" | D13: Wonder | E13: Nos. | F13: 24 | G13: 4 | H13: 5 | I13: =G13+H13 -> 9 | K13: 2 | S13: 1 | AO13: =SUM(J13:AN13) -> 3 | AP13: =I13-AO13 -> 6 | AQ13: =AO13*F13 -> 72 | AR13: =AP13*F13 -> 144 | AS13: =H13*F13 -> 120 | AV13: =AS13*SUM(AT13:AU13)%+AS13 -> 120
B14: 9 | C14: Calculator | E14: Nos. | G14: 1 | I14: =G14+H14 -> 1 | AO14: =SUM(J14:AN14) -> 0 | AP14: =I14-AO14 -> 1 | AQ14: =AO14*F14 -> 0 | AR14: =AP14*F14 -> 0 | AS14: =H14*F14 -> 0
B15: 10 | C15: Natraj Ball Pen | D15: Natraj | E15: Nos. | F15: 2.9 | G15: 33 | H15: 20 | I15: =G15+H15 -> 53 | K15: 5 | M15: 3 | R15: 3 | AO15: =SUM(J15:AN15) -> 11 | AP15: =I15-AO15 -> 42 | AQ15: =AO15*F15 -> 31.9 | AR15: =AP15*F15 -> 121.8 | AS15: =H15*F15 -> 58 | AV15: =AS15*SUM(AT15:AU15)%+AS15 -> 58
B16: 11 | C16: Foam tape new brand | D16: Wonder | E16: Nos. | F16: 35 | G16: 3 | I16: =G16+H16 -> 3 | AO16: =SUM(J16:AN16) -> 0 | AP16: =I16-AO16 -> 3 | AQ16: =AO16*F16 -> 0 | AR16: =AP16*F16 -> 105 | AS16: =H16*F16 -> 0 | AV16: =AS16*SUM(AT16:AU16)%+AS16 -> 0
B17: 12 | C17: File Tag | D17: Local Brand | E17: Pkt | F17: 80 | G17: 0 | I17: =G17+H17 -> 0 | AO17: =SUM(J17:AN17) -> 0 | AP17: =I17-AO17 -> 0 | AQ17: =AO17*F17 -> 0 | AR17: =AP17*F17 -> 0 | AS17: =H17*F17 -> 0 | AV17: =AS17*SUM(AT17:AU17)%+AS17 -> 0
B18: 13 | C18: White Board Markar Blue | D18: Camlin | E18: Nos. | F18: 21 | G18: 19 | I18: =G18+H18 -> 19 | AO18: =SUM(J18:AN18) -> 0 | AP18: =I18-AO18 -> 19 | AQ18: =AO18*F18 -> 0 | AR18: =AP18*F18 -> 399 | AS18: =H18*F18 -> 0 | AV18: =AS18*SUM(AT18:AU18)%+AS18 -> 0
B19: 14 | C19: White Board Markar Black | D19: Camlin | E19: Nos. | F19: 21 | G19: 20 | I19: =G19+H19 -> 20 | AO19: =SUM(J19:AN19) -> 0 | AP19: =I19-AO19 -> 20 | AQ19: =AO19*F19 -> 0 | AR19: =AP19*F19 -> 420 | AS19: =H19*F19 -> 0 | AV19: =AS19*SUM(AT19:AU19)%+AS19 -> 0
B20: 15 | C20: White Board Markar Red | D20: Camlin | E20: Nos. | F20: 21 | G20: 10 | I20: =G20+H20 -> 10 | AO20: =SUM(J20:AN20) -> 0 | AP20: =I20-AO20 -> 10 | AQ20: =AO20*F20 -> 0 | AR20: =AP20*F20 -> 210 | AS20: =H20*F20 -> 0 | AV20: =AS20*SUM(AT20:AU20)%+AS20 -> 0
B21: 16 | C21: Paint Marker | D21: Camlin | E21: Nos. | F21: 60 | G21: 0 | I21: =G21+H21 -> 0 | AO21: =SUM(J21:AN21) -> 0 | AP21: =I21-AO21 -> 0 | AQ21: =AO21*F21 -> 0 | AR21: =AP21*F21 -> 0 | AS21: =H21*F21 -> 0 | AV21: =AS21*SUM(AT21:AU21)%+AS21 -> 0
B22: 17 | C22: Permanent Marker | D22: Camlin | E22: Nos. | F22: 17.5 | G22: 6 | I22: =G22+H22 -> 6 | K22: 1 | AO22: =SUM(J22:AN22) -> 1 | AP22: =I22-AO22 -> 5 | AQ22: =AO22*F22 -> 17.5 | AR22: =AP22*F22 -> 87.5 | AS22: =H22*F22 -> 0 | AV22: =AS22*SUM(AT22:AU22)%+AS22 -> 0
B23: 18 | C23: Stapler No. 10 | D23: Kangaro | E23: Nos. | F23: 38 | G23: 4 | I23: =G23+H23 -> 4 | AO23: =SUM(J23:AN23) -> 0 | AP23: =I23-AO23 -> 4 | AQ23: =AO23*F23 -> 0 | AR23: =AP23*F23 -> 152 | AS23: =H23*F23 -> 0 | AV23: =AS23*SUM(AT23:AU23)%+AS23 -> 0
B24: 19 | C24: Staplar Pin Small | D24: Kangaro | E24: Box | F24: 120 | G24: 26 | I24: =G24+H24 -> 26 | AO24: =SUM(J24:AN24) -> 0 | AP24: =I24-AO24 -> 26 | AQ24: =AO24*F24 -> 0 | AR24: =AP24*F24 -> 3120 | AS24: =H24*F24 -> 0 | AV24: =AS24*SUM(AT24:AU24)%+AS24 -> 0
B25: 20 | C25: Glue Stic 8 gms | D25: Camlin | E25: Nos. | F25: 18 | G25: 3 | I25: =G25+H25 -> 3 | AO25: =SUM(J25:AN25) -> 0 | AP25: =I25-AO25 -> 3 | AQ25: =AO25*F25 -> 0 | AR25: =AP25*F25 -> 54 | AS25: =H25*F25 -> 0 | AV25: =AS25*SUM(AT25:AU25)%+AS25 -> 0
B26: 21 | C26: White Board Duster | D26: Prime | E26: Nos. | F26: 45 | G26: 10 | I26: =G26+H26 -> 10 | AO26: =SUM(J26:AN26) -> 0 | AP26: =I26-AO26 -> 10 | AQ26: =AO26*F26 -> 0 | AR26: =AP26*F26 -> 450 | AS26: =H26*F26 -> 0 | AV26: =AS26*SUM(AT26:AU26)%+AS26 -> 0
B27: 22 | C27: "U"Clip 26 mm | D27: Luxury | E27: Box | F27: 10 | G27: 6 | I27: =G27+H27 -> 6 | AO27: =SUM(J27:AN27) -> 0 | AP27: =I27-AO27 -> 6 | AQ27: =AO27*F27 -> 0 | AR27: =AP27*F27 -> 60 | AS27: =H27*F27 -> 0 | AV27: =AS27*SUM(AT27:AU27)%+AS27 -> 0
B28: 23 | C28: "V"Clip | D28: Luxury | E28: Box | F28: 9 | G28: 0 | I28: =G28+H28 -> 0 | AO28: =SUM(J28:AN28) -> 0 | AP28: =I28-AO28 -> 0 | AQ28: =AO28*F28 -> 0 | AR28: =AP28*F28 -> 0 | AS28: =H28*F28 -> 0 | AV28: =AS28*SUM(AT28:AU28)%+AS28 -> 0
B29: 24 | C29: Sharpener | D29: Natraj | E29: Nos. | F29: 2.8 | G29: 2 | I29: =G29+H29 -> 2 | AO29: =SUM(J29:AN29) -> 0 | AP29: =I29-AO29 -> 2 | AQ29: =AO29*F29 -> 0 | AR29: =AP29*F29 -> 5.6 | AS29: =H29*F29 -> 0 | AV29: =AS29*SUM(AT29:AU29)%+AS29 -> 0
B30: 25 | C30: Eraser | D30: Natraj | E30: Nos. | F30: 2.8 | G30: 6 | I30: =G30+H30 -> 6 | K30: 2 | AO30: =SUM(J30:AN30) -> 2 | AP30: =I30-AO30 -> 4 | AQ30: =AO30*F30 -> 5.6 | AR30: =AP30*F30 -> 11.2 | AS30: =H30*F30 -> 0 | AV30: =AS30*SUM(AT30:AU30)%+AS30 -> 0
B31: 26 | C31: Sketch Pen | D31: Pikpens | E31: Pkt | F31: 22 | G31: 1 | I31: =G31+H31 -> 1 | AO31: =SUM(J31:AN31) -> 0 | AP31: =I31-AO31 -> 1 | AQ31: =AO31*F31 -> 0 | AR31: =AP31*F31 -> 22 | AS31: =H31*F31 -> 0 | AV31: =AS31*SUM(AT31:AU31)%+AS31 -> 0
B32: 27 | C32: Post it Pad 3*3 | D32: Past it | E32: Nos. | F32: 28 | G32: 10 | I32: =G32+H32 -> 10 | M32: 1 | AO32: =SUM(J32:AN32) -> 1 | AP32: =I32-AO32 -> 9 | AQ32: =AO32*F32 -> 28 | AR32: =AP32*F32 -> 252 | AS32: =H32*F32 -> 0 | AV32: =AS32*SUM(AT32:AU32)%+AS32 -> 0
B33: 28 | C33: Binder Clip Big 32 mm | D33: Gorilla/Music | E33: Box. | F33: 35 | G33: 15 | I33: =G33+H33 -> 15 | Y33: 1 | AO33: =SUM(J33:AN33) -> 1 | AP33: =I33-AO33 -> 14 | AQ33: =AO33*F33 -> 35 | AR33: =AP33*F33 -> 490 | AS33: =H33*F33 -> 0 | AV33: =AS33*SUM(AT33:AU33)%+AS33 -> 0
B34: 29 | C34: Binder Clip 19 mm | D34: Gorilla/Music | E34: Nos. | F34: 20 | G34: 2 | I34: =G34+H34 -> 2 | Y34: 1 | AO34: =SUM(J34:AN34) -> 1 | AP34: =I34-AO34 -> 1 | AQ34: =AO34*F34 -> 20 | AR34: =AP34*F34 -> 20 | AS34: =H34*F34 -> 0 | AV34: =AS34*SUM(AT34:AU34)%+AS34 -> 0
B35: 30 | C35: Liuon Pins | D35: Lion/Leo | E35: Box | F35: 18 | G35: 4 | I35: =G35+H35 -> 4 | AO35: =SUM(J35:AN35) -> 0 | AP35: =I35-AO35 -> 4 | AQ35: =AO35*F35 -> 0 | AR35: =AP35*F35 -> 72 | AS35: =H35*F35 -> 0 | AV35: =AS35*SUM(AT35:AU35)%+AS35 -> 0
B36: 31 | C36: Push Pin | D36: Luxury | E36: Box | F36: 35 | G36: 2 | I36: =G36+H36 -> 2 | AO36: =SUM(J36:AN36) -> 0 | AP36: =I36-AO36 -> 2 | AQ36: =AO36*F36 -> 0 | AR36: =AP36*F36 -> 70 | AS36: =H36*F36 -> 0 | AV36: =AS36*SUM(AT36:AU36)%+AS36 -> 0
B37: 32 | C37: Stamp Pad Blue | D37: Camlin | E37: Nos. | F37: 38 | G37: 3 | I37: =G37+H37 -> 3 | AO37: =SUM(J37:AN37) -> 0 | AP37: =I37-AO37 -> 3 | AQ37: =AO37*F37 -> 0 | AR37: =AP37*F37 -> 114 | AS37: =H37*F37 -> 0 | AV37: =AS37*SUM(AT37:AU37)%+AS37 -> 0
B38: 33 | C38: Cutter Big | D38: Gorilla/Music | E38: Nos. | F38: 18 | G38: 1 | I38: =G38+H38 -> 1 | AO38: =SUM(J38:AN38) -> 0 | AP38: =I38-AO38 -> 1 | AQ38: =AO38*F38 -> 0 | AR38: =AP38*F38 -> 18 | AS38: =H38*F38 -> 0 | AV38: =AS38*SUM(AT38:AU38)%+AS38 -> 0
B39: 34 | C39: Red Adhesive Tape Double Side | D39: Local Brand | E39: Nos. | F39: 360 | G39: 0 | I39: =G39+H39 -> 0 | AO39: =SUM(J39:AN39) -> 0 | AP39: =I39-AO39 -> 0 | AQ39: =AO39*F39 -> 0 | AR39: =AP39*F39 -> 0 | AS39: =H39*F39 -> 0 | AV39: =AS39*SUM(AT39:AU39)%+AS39 -> 0
B40: 35 | C40: Fevicol Bottle Small | D40: Pidilite | E40: Nos. | F40: 29 | G40: 2 | I40: =G40+H40 -> 2 | AO40: =SUM(J40:AN40) -> 0 | AP40: =I40-AO40 -> 2 | AQ40: =AO40*F40 -> 0 | AR40: =AP40*F40 -> 58 | AS40: =H40*F40 -> 0 | AV40: =AS40*SUM(AT40:AU40)%+AS40 -> 0
B41: 36 | C41: Stamp Ink | D41: Camlin | E41: Bottle | F41: 28 | G41: 2 | I41: =G41+H41 -> 2 | AO41: =SUM(J41:AN41) -> 0 | AP41: =I41-AO41 -> 2 | AQ41: =AO41*F41 -> 0 | AR41: =AP41*F41 -> 56 | AS41: =H41*F41 -> 0 | AV41: =AS41*SUM(AT41:AU41)%+AS41 -> 0
B42: 37 | C42: Stapler Pin Big | D42: Kangaro | E42: Box | F42: 16 | G42: 11 | I42: =G42+H42 -> 11 | AO42: =SUM(J42:AN42) -> 0 | AP42: =I42-AO42 -> 11 | AQ42: =AO42*F42 -> 0 | AR42: =AP42*F42 -> 176 | AS42: =H42*F42 -> 0 | AV42: =AS42*SUM(AT42:AU42)%+AS42 -> 0
B43: 38 | C43: Plastics Folder "L" | D43: Music | E43: Nos. | F43: 6.5 | G43: 33 | I43: =G43+H43 -> 33 | V43: 1 | W43: 1 | AO43: =SUM(J43:AN43) -> 2 | AP43: =I43-AO43 -> 31 | AQ43: =AO43*F43 -> 13 | AR43: =AP43*F43 -> 201.5 | AS43: =H43*F43 -> 0 | AV43: =AS43*SUM(AT43:AU43)%+AS43 -> 0
B44: 39 | C44: Register Book Big 3 Quire | D44: Vedant | E44: Nos. | F44: 90 | G44: 0 | H44: 5 | I44: =G44+H44 -> 5 | AO44: =SUM(J44:AN44) -> 0 | AP44: =I44-AO44 -> 5 | AQ44: =AO44*F44 -> 0 | AR44: =AP44*F44 -> 450 | AS44: =H44*F44 -> 450 | AV44: =AS44*SUM(AT44:AU44)%+AS44 -> 450
B45: 40 | C45: Register Book Small 2 Quire | D45: Vedant | E45: Nos. | F45: 60 | G45: 2 | H45: 5 | I45: =G45+H45 -> 7 | K45: 1 | L45: 1 | Z45: 1 | AO45: =SUM(J45:AN45) -> 3 | AP45: =I45-AO45 -> 4 | AQ45: =AO45*F45 -> 180 | AR45: =AP45*F45 -> 240 | AS45: =H45*F45 -> 300 | AV45: =AS45*SUM(AT45:AU45)%+AS45 -> 300
B46: 41 | C46: ID Card Holder | D46: Music | E46: Nos. | F46: 5.5 | G46: 12 | I46: =G46+H46 -> 12 | R46: 2 | Y46: 10 | AO46: =SUM(J46:AN46) -> 12 | AP46: =I46-AO46 -> 0 | AQ46: =AO46*F46 -> 66 | AR46: =AP46*F46 -> 0 | AS46: =H46*F46 -> 0 | AV46: =AS46*SUM(AT46:AU46)%+AS46 -> 0
B47: 42 | C47: Cheque Book Plastic Folder | D47: Local Brand | E47: Nos. | F47: 28 | G47: 0 | I47: =G47+H47 -> 0 | AO47: =SUM(J47:AN47) -> 0 | AP47: =I47-AO47 -> 0 | AQ47: =AO47*F47 -> 0 | AR47: =AP47*F47 -> 0 | AS47: =H47*F47 -> 0 | AV47: =AS47*SUM(AT47:AU47)%+AS47 -> 0
B48: 43 | C48: Correction Pen Metal Point | D48: Camlin | E48: Nos. | F48: 28 | G48: 2 | I48: =G48+H48 -> 2 | AO48: =SUM(J48:AN48) -> 0 | AP48: =I48-AO48 -> 2 | AQ48: =AO48*F48 -> 0 | AR48: =AP48*F48 -> 56 | AS48: =H48*F48 -> 0 | AV48: =AS48*SUM(AT48:AU48)%+AS48 -> 0
B49: 44 | C49: Pencil (Natraj/ Apsara) | D49: Apsara | E49: Box | F49: 36 | G49: 1 | I49: =G49+H49 -> 1 | AO49: =SUM(J49:AN49) -> 0 | AP49: =I49-AO49 -> 1 | AQ49: =AO49*F49 -> 0 | AR49: =AP49*F49 -> 36 | AS49: =H49*F49 -> 0 | AV49: =AS49*SUM(AT49:AU49)%+AS49 -> 0
B50: 45 | C50: A4 Size Cloth Green Envelope | D50: Pidilite | E50: Bottle | F50: 9 | G50: 23 | I50: =G50+H50 -> 23 | Y50: 10 | AO50: =SUM(J50:AN50) -> 10 | AP50: =I50-AO50 -> 13 | AQ50: =AO50*F50 -> 90 | AR50: =AP50*F50 -> 117 | AS50: =H50*F50 -> 0 | AV50: =AS50*SUM(AT50:AU50)%+AS50 -> 0
B51: 46 | C51: Scissor (Small) | D51: Gorilla/Music | E51: Nos. | F51: 32 | G51: 1 | I51: =G51+H51 -> 1 | AO51: =SUM(J51:AN51) -> 0 | AP51: =I51-AO51 -> 1 | AQ51: =AO51*F51 -> 0 | AR51: =AP51*F51 -> 32 | AS51: =H51*F51 -> 0 | AV51: =AS51*SUM(AT51:AU51)%+AS51 -> 0
B52: 47 | C52: Fevi Kwik 0.5 gms | D52: Pidilite | E52: Nos. | F52: 4.5 | G52: 6 | I52: =G52+H52 -> 6 | AO52: =SUM(J52:AN52) -> 0 | AP52: =I52-AO52 -> 6 | AQ52: =AO52*F52 -> 0 | AR52: =AP52*F52 -> 27 | AS52: =H52*F52 -> 0 | AV52: =AS52*SUM(AT52:AU52)%+AS52 -> 0
B53: 48 | C53: Temporary ID Card | D53: Local Brand | E53: Nos. | F53: 1.5 | G53: 0 | I53: =G53+H53 -> 0 | AO53: =SUM(J53:AN53) -> 0 | AP53: =I53-AO53 -> 0 | AQ53: =AO53*F53 -> 0 | AR53: =AP53*F53 -> 0 | AS53: =H53*F53 -> 0 | AV53: =AS53*SUM(AT53:AU53)%+AS53 -> 0
B54: 49 | C54: Highlighter Pen | D54: Camlin | E54: Nos. | F54: 18 | G54: 5 | I54: =G54+H54 -> 5 | AO54: =SUM(J54:AN54) -> 0 | AP54: =I54-AO54 -> 5 | AQ54: =AO54*F54 -> 0 | AR54: =AP54*F54 -> 90 | AS54: =H54*F54 -> 0 | AV54: =AS54*SUM(AT54:AU54)%+AS54 -> 0
B55: 50 | C55: Magnetic Button | D55: Music | E55: Nos. | F55: 70 | G55: 1 | I55: =G55+H55 -> 1 | AO55: =SUM(J55:AN55) -> 0 | AP55: =I55-AO55 -> 1 | AQ55: =AO55*F55 -> 0 | AR55: =AP55*F55 -> 70 | AS55: =H55*F55 -> 0 | AV55: =AS55*SUM(AT55:AU55)%+AS55 -> 0
B56: 51 | C56: Cmos Battery | D56: Intex | E56: Nos. | F56: 15 | G56: 6 | I56: =G56+H56 -> 6 | AO56: =SUM(J56:AN56) -> 0 | AP56: =I56-AO56 -> 6 | AQ56: =AO56*F56 -> 0 | AR56: =AP56*F56 -> 90 | AS56: =H56*F56 -> 0 | AV56: =AS56*SUM(AT56:AU56)%+AS56 -> 0
B57: 52 | C57: A/4 Image Copier Paper | D57: Andhara/Century | E57: Box | F57: 230 | G57: 5 | H57: 10 | I57: =G57+H57 -> 15 | K57: 4 | N57: 3 | O57: 1 | Q57: 1 | U57: 2 | V57: 1 | AO57: =SUM(J57:AN57) -> 12 | AP57: =I57-AO57 -> 3 | AQ57: =AO57*F57 -> 2760 | AR57: =AP57*F57 -> 690 | AS57: =H57*F57 -> 2300 | AV57: =AS57*SUM(AT57:AU57)%+AS57 -> 2300
B58: 53 | C58: Pen Stand Round | D58: Music | E58: Nos. | F58: 45 | G58: 2 | I58: =G58+H58 -> 2 | AO58: =SUM(J58:AN58) -> 0 | AP58: =I58-AO58 -> 2 | AQ58: =AO58*F58 -> 0 | AR58: =AP58*F58 -> 90 | AS58: =H58*F58 -> 0 | AV58: =AS58*SUM(AT58:AU58)%+AS58 -> 0
B59: 54 | C59: Button Folder (Cloth Patti) | D59: Local Brand | E59: Nos. | F59: 45 | G59: 4 | I59: =G59+H59 -> 4 | AO59: =SUM(J59:AN59) -> 0 | AP59: =I59-AO59 -> 4 | AQ59: =AO59*F59 -> 0 | AR59: =AP59*F59 -> 180 | AS59: =H59*F59 -> 0 | AV59: =AS59*SUM(AT59:AU59)%+AS59 -> 0
B60: 55 | C60: Brown Tape | D60: Wonder | E60: Nos. | F60: 24 | G60: 5 | I60: =G60+H60 -> 5 | S60: 1 | AO60: =SUM(J60:AN60) -> 1 | AP60: =I60-AO60 -> 4 | AQ60: =AO60*F60 -> 24 | AR60: =AP60*F60 -> 96 | AS60: =H60*F60 -> 0 | AV60: =AS60*SUM(AT60:AU60)%+AS60 -> 0
B61: 56 | C61: Sticker Labelbig size | D61: Mark | E61: pkt | F61: 110 | G61: 1 | I61: =G61+H61 -> 1 | AO61: =SUM(J61:AN61) -> 0 | AP61: =I61-AO61 -> 1 | AQ61: =AO61*F61 -> 0 | AR61: =AP61*F61 -> 110 | AS61: =H61*F61 -> 0 | AV61: =AS61*SUM(AT61:AU61)%+AS61 -> 0
B62: 57 | C62: Patti File | D62: Local Brand | E62: Nos. | F62: 25 | G62: 0 | I62: =G62+H62 -> 0 | AO62: =SUM(J62:AN62) -> 0 | AP62: =I62-AO62 -> 0 | AQ62: =AO62*F62 -> 0 | AR62: =AP62*F62 -> 0 | AS62: =H62*F62 -> 0 | AV62: =AS62*SUM(AT62:AU62)%+AS62 -> 0
B63: 58 | C63: Nippo Battery -AA | D63: Nippo | E63: Nos. | F63: 10.5 | G63: 8 | I63: =G63+H63 -> 8 | AO63: =SUM(J63:AN63) -> 0 | AP63: =I63-AO63 -> 8 | AQ63: =AO63*F63 -> 0 | AR63: =AP63*F63 -> 84 | AS63: =H63*F63 -> 0 | AV63: =AS63*SUM(AT63:AU63)%+AS63 -> 0
B64: 59 | C64: Nippo Battery -AAA | D64: Nippo | E64: Nos. | F64: 10.5 | G64: 20 | I64: =G64+H64 -> 20 | AO64: =SUM(J64:AN64) -> 0 | AP64: =I64-AO64 -> 20 | AQ64: =AO64*F64 -> 0 | AR64: =AP64*F64 -> 210 | AS64: =H64*F64 -> 0 | AV64: =AS64*SUM(AT64:AU64)%+AS64 -> 0
B65: 60 | C65: 9 V Battery | D65: HW | E65: Nos. | F65: 45 | G65: 5 | I65: =G65+H65 -> 5 | AO65: =SUM(J65:AN65) -> 0 | AP65: =I65-AO65 -> 5 | AQ65: =AO65*F65 -> 0 | AR65: =AP65*F65 -> 225 | AS65: =H65*F65 -> 0 | AV65: =AS65*SUM(AT65:AU65)%+AS65 -> 0
B66: 61 | C66: Notice Bord Pin | D66: Local Brand | E66: Nos. | F66: 45 | G66: 0 | I66: =G66+H66 -> 0 | AO66: =SUM(J66:AN66) -> 0 | AP66: =I66-AO66 -> 0 | AQ66: =AO66*F66 -> 0 | AR66: =AP66*F66 -> 0 | AS66: =H66*F66 -> 0 | AV66: =AS66*SUM(AT66:AU66)%+AS66 -> 0
B67: 62 | C67: CD Marker Pen | D67: Camlin | E67: Nos. | F67: 9 | G67: 4 | I67: =G67+H67 -> 4 | AO67: =SUM(J67:AN67) -> 0 | AP67: =I67-AO67 -> 4 | AQ67: =AO67*F67 -> 0 | AR67: =AP67*F67 -> 36 | AS67: =H67*F67 -> 0 | AV67: =AS67*SUM(AT67:AU67)%+AS67 -> 0
B68: 63 | C68: Piani file | D68: Local Brand | E68: Nos. | F68: 240 | G68: 0 | I68: =G68+H68 -> 0 | AO68: =SUM(J68:AN68) -> 0 | AP68: =I68-AO68 -> 0 | AQ68: =AO68*F68 -> 0 | AR68: =AP68*F68 -> 0 | AS68: =H68*F68 -> 0 | AV68: =AS68*SUM(AT68:AU68)%+AS68 -> 0
B69: 64 | C69: Ball Pen Black Writometer | D69: Camlin/Kores | E69: Box | F69: 30 | G69: 0 | I69: =G69+H69 -> 0 | AO69: =SUM(J69:AN69) -> 0 | AP69: =I69-AO69 -> 0 | AQ69: =AO69*F69 -> 0 | AR69: =AP69*F69 -> 0 | AS69: =H69*F69 -> 0 | AV69: =AS69*SUM(AT69:AU69)%+AS69 -> 0
B70: 65 | C70: White Board 2*3 | D70: Local Brand | E70: Nos. | F70: 600 | G70: 0 | I70: =G70+H70 -> 0 | AO70: =SUM(J70:AN70) -> 0 | AP70: =I70-AO70 -> 0 | AQ70: =AO70*F70 -> 0 | AR70: =AP70*F70 -> 0 | AS70: =H70*F70 -> 0 | AV70: =AS70*SUM(AT70:AU70)%+AS70 -> 0
B71: 66 | C71: Ball Pen with stand | D71: Moserbaer | E71: Nos. | F71: 45 | G71: 0 | I71: =G71+H71 -> 0 | AO71: =SUM(J71:AN71) -> 0 | AP71: =I71-AO71 -> 0 | AQ71: =AO71*F71 -> 0 | AR71: =AP71*F71 -> 0 | AS71: =H71*F71 -> 0 | AV71: =AS71*SUM(AT71:AU71)%+AS71 -> 0
B72: 67 | C72: Radium Sunboard | D72: Local Brand | E72: Nos. | F72: 200 | G72: 0 | I72: =G72+H72 -> 0 | AO72: =SUM(J72:AN72) -> 0 | AP72: =I72-AO72 -> 0 | AQ72: =AO72*F72 -> 0 | AR72: =AP72*F72 -> 0 | AS72: =H72*F72 -> 0 | AV72: =AS72*SUM(AT72:AU72)%+AS72 -> 0
... B79: 74 | C79: XEROX | D79: Andhara/Century | E79: Nos. | F79: 0.9 | G79: 0 | I79: =G79+H79 -> 0 | AO79: =SUM(J79:AN79) -> 0 | AP79: =I79-AO79 -> 0 | AQ79: =AO79*F79 -> 0 | AR79: =AP79*F79 -> 0 | AS79: =H79*F79 -> 0 | AV79: =AS79*SUM(AT79:AU79)%+AS79 -> 0
B80: 75 | C80: Duro Cell AA | D80: Local Brand | E80: Pkt | F80: 38 | G80: 3 | H80: 20 | I80: =G80+H80 -> 23 | AO80: =SUM(J80:AN80) -> 0 | AP80: =I80-AO80 -> 23 | AQ80: =AO80*F80 -> 0 | AR80: =AP80*F80 -> 874 | AS80: =H80*F80 -> 760 | AV80: =AS80*SUM(AT80:AU80)%+AS80 -> 760
B81: 76 | C81: Duro Cell AAA | D81: Duro | E81: Nos. | F81: 38 | G81: 19 | I81: =G81+H81 -> 19 | AO81: =SUM(J81:AN81) -> 0 | AP81: =I81-AO81 -> 19 | AQ81: =AO81*F81 -> 0 | AR81: =AP81*F81 -> 722 | AS81: =H81*F81 -> 0 | AV81: =AS81*SUM(AT81:AU81)%+AS81 -> 0
B82: 77 | C82: Marker Tie 100 mm | D82: Andhara/Century | E82: Pic | F82: 150 | G82: 0 | I82: =G82+H82 -> 0 | AO82: =SUM(J82:AN82) -> 0 | AP82: =I82-AO82 -> 0 | AQ82: =AO82*F82 -> 0 | AR82: =AP82*F82 -> 0 | AS82: =H82*F82 -> 0 | AV82: =AS82*SUM(AT82:AU82)%+AS82 -> 0
B83: 78 | C83: Masking Tape 1" | D83: Pidilite | E83: Bottle | F83: 35 | G83: 4 | I83: =G83+H83 -> 4 | K83: 1 | AO83: =SUM(J83:AN83) -> 1 | AP83: =I83-AO83 -> 3 | AQ83: =AO83*F83 -> 35 | AR83: =AP83*F83 -> 105 | AS83: =H83*F83 -> 0 | AV83: =AS83*SUM(AT83:AU83)%+AS83 -> 0
B84: 79 | C84: Paper try 4in1 | D84: Local Brand | E84: Nos. | F84: 800 | G84: 0 | I84: =G84+H84 -> 0 | AO84: =SUM(J84:AN84) -> 0 | AP84: =I84-AO84 -> 0 | AQ84: =AO84*F84 -> 0 | AR84: =AP84*F84 -> 0 | AS84: =H84*F84 -> 0 | AV84: =AS84*SUM(AT84:AU84)%+AS84 -> 0
B85: 80 | C85: Plastic Envelope Folder | D85: Local Brand | E85: Nos. | F85: 28 | G85: 0 | I85: =G85+H85 -> 0 | AO85: =SUM(J85:AN85) -> 0 | AP85: =I85-AO85 -> 0 | AQ85: =AO85*F85 -> 0 | AR85: =AP85*F85 -> 0 | AS85: =H85*F85 -> 0 | AV85: =AS85*SUM(AT85:AU85)%+AS85 -> 0
B86: 81 | C86: Punch Folder | D86: Local Brand | E86: Nos. | F86: 5.5 | G86: 5 | I86: =G86+H86 -> 5 | AO86: =SUM(J86:AN86) -> 0 | AP86: =I86-AO86 -> 5 | AQ86: =AO86*F86 -> 0 | AR86: =AP86*F86 -> 27.5 | AS86: =H86*F86 -> 0 | AV86: =AS86*SUM(AT86:AU86)%+AS86 -> 0
B87: 82 | C87: Id Card Printing | D87: Local Brand | E87: Nos. | F87: 20 | G87: 0 | I87: =G87+H87 -> 0 | AO87: =SUM(J87:AN87) -> 0 | AP87: =I87-AO87 -> 0 | AQ87: =AO87*F87 -> 0 | AR87: =AP87*F87 -> 0 | AS87: =H87*F87 -> 0 | AV87: =AS87*SUM(AT87:AU87)%+AS87 -> 0
B88: 83 | C88: Sprial Pad No 90 | D88: Local Brand | E88: Nos. | F88: 95 | G88: 0 | I88: =G88+H88 -> 0 | AO88: =SUM(J88:AN88) -> 0 | AP88: =I88-AO88 -> 0 | AQ88: =AO88*F88 -> 0 | AR88: =AP88*F88 -> 0 | AS88: =H88*F88 -> 0 | AV88: =AS88*SUM(AT88:AU88)%+AS88 -> 0
B89: 84 | C89: A4Executive Bond Paper 100gsm | D89: Local Brand | E89: Nos. | F89: 380 | G89: 0 | I89: =G89+H89 -> 0 | AO89: =SUM(J89:AN89) -> 0 | AP89: =I89-AO89 -> 0 | AQ89: =AO89*F89 -> 0 | AR89: =AP89*F89 -> 0 | AS89: =H89*F89 -> 0 | AV89: =AS89*SUM(AT89:AU89)%+AS89 -> 0
B90: 85 | C90: Masking Tape 2" | D90: Local Brand | E90: Nos. | F90: 35 | G90: 5 | I90: =G90+H90 -> 5 | AO90: =SUM(J90:AN90) -> 0 | AP90: =I90-AO90 -> 5 | AQ90: =AO90*F90 -> 0 | AR90: =AP90*F90 -> 175 | AS90: =H90*F90 -> 0 | AV90: =AS90*SUM(AT90:AU90)%+AS90 -> 0
B91: 86 | C91: File separator | D91: Local Brand | E91: PKT | F91: 55 | G91: 2 | I91: =G91+H91 -> 2 | M91: 1 | AO91: =SUM(J91:AN91) -> 1 | AP91: =I91-AO91 -> 1 | AQ91: =AO91*F91 -> 55 | AR91: =AP91*F91 -> 55 | AS91: =H91*F91 -> 0 | AV91: =AS91*SUM(AT91:AU91)%+AS91 -> 0
B92: 87 | C92: Stapler Big HP- 45 | D92: Kangaro | E92: Nos. | F92: 245 | G92: 0 | I92: =G92+H92 -> 0 | AO92: =SUM(J92:AN92) -> 0 | AP92: =I92-AO92 -> 0 | AQ92: =AO92*F92 -> 0 | AR92: =AP92*F92 -> 0 | AS92: =H92*F92 -> 0 | AV92: =AS92*SUM(AT92:AU92)%+AS92 -> 0
B93: 88 | C93: Camllin Cd Marker Pen | D93: Local Brand | E93: Pkt | F93: 15 | G93: 0 | I93: =G93+H93 -> 0 | AO93: =SUM(J93:AN93) -> 0 | AP93: =I93-AO93 -> 0 | AQ93: =AO93*F93 -> 0 | AR93: =AP93*F93 -> 0 | AS93: =H93*F93 -> 0 | AV93: =AS93*SUM(AT93:AU93)%+AS93 -> 0
B94: 89 | C94: Id Card Cover Double | D94: Local Brand | E94: Nos. | F94: 5.5 | G94: 0 | I94: =G94+H94 -> 0 | AO94: =SUM(J94:AN94) -> 0 | AP94: =I94-AO94 -> 0 | AQ94: =AO94*F94 -> 0 | AR94: =AP94*F94 -> 0 | AS94: =H94*F94 -> 0 | AV94: =AS94*SUM(AT94:AU94)%+AS94 -> 0
B95: 90 | C95: Good Night Refill | D95: Local Brand | E95: Nos. | F95: 72 | G95: 3 | I95: =G95+H95 -> 3 | AO95: =SUM(J95:AN95) -> 0 | AP95: =I95-AO95 -> 3 | AQ95: =AO95*F95 -> 0 | AR95: =AP95*F95 -> 216 | AS95: =H95*F95 -> 0 | AV95: =AS95*SUM(AT95:AU95)%+AS95 -> 0
B96: 91 | C96: Oreva Spikeguard 4mtr | D96: Oreva | E96: Nos. | F96: 450 | G96: 0 | I96: =G96+H96 -> 0 | AO96: =SUM(J96:AN96) -> 0 | AP96: =I96-AO96 -> 0 | AQ96: =AO96*F96 -> 0 | AR96: =AP96*F96 -> 0 | AS96: =H96*F96 -> 0 | AV96: =AS96*SUM(AT96:AU96)%+AS96 -> 0
B97: 92 | C97: A/4 Photo Frame | D97: Local Brand | E97: Nos. | F97: 180 | G97: 0 | I97: =G97+H97 -> 0 | AO97: =SUM(J97:AN97) -> 0 | AP97: =I97-AO97 -> 0 | AQ97: =AO97*F97 -> 0 | AR97: =AP97*F97 -> 0 | AS97: =H97*F97 -> 0 | AV97: =AS97*SUM(AT97:AU97)%+AS97 -> 0
B98: 93 | C98: Post it Pad 3 x 3- 3 colour | D98: Past it | E98: Nos. | F98: 35 | G98: 2 | I98: =G98+H98 -> 2 | AO98: =SUM(J98:AN98) -> 0 | AP98: =I98-AO98 -> 2 | AQ98: =AO98*F98 -> 0 | AR98: =AP98*F98 -> 70 | AS98: =H98*F98 -> 0 | AV98: =AS98*SUM(AT98:AU98)%+AS98 -> 0
B99: 94 | C99: Green Envelope A3 Size | D99: Local Brand | E99: Nos. | F99: 6.5 | G99: 61 | I99: =G99+H99 -> 61 | N99: 1 | S99: 1 | AO99: =SUM(J99:AN99) -> 2 | AP99: =I99-AO99 -> 59 | AQ99: =AO99*F99 -> 13 | AR99: =AP99*F99 -> 383.5 | AS99: =H99*F99 -> 0 | AV99: =AS99*SUM(AT99:AU99)%+AS99 -> 0
B100: 95 | C100: Green Envelope Small Size | D100: Local Brand | E100: Nos. | F100: 6.5 | G100: 42 | I100: =G100+H100 -> 42 | AO100: =SUM(J100:AN100) -> 0 | AP100: =I100-AO100 -> 42 | AQ100: =AO100*F100 -> 0 | AR100: =AP100*F100 -> 273 | AS100: =H100*F100 -> 0 | AV100: =AS100*SUM(AT100:AU100)%+AS100 -> 0
B101: 96 | C101: Ball Pen | D101: Local Brand | E101: Nos. | F101: 10 | G101: 4 | I101: =G101+H101 -> 4 | K101: 1 | AO101: =SUM(J101:AN101) -> 1 | AP101: =I101-AO101 -> 3 | AQ101: =AO101*F101 -> 10 | AR101: =AP101*F101 -> 30 | AS101: =H101*F101 -> 0 | AV101: =AS101*SUM(AT101:AU101)%+AS101 -> 0
B102: 97 | C102: Blinder Clip 25mm | D102: Bosch | E102: Nos. | F102: 35 | G102: 0 | I102: =G102+H102 -> 0 | AO102: =SUM(J102:AN102) -> 0 | AP102: =I102-AO102 -> 0 | AQ102: =AO102*F102 -> 0 | AR102: =AP102*F102 -> 0 | AS102: =H102*F102 -> 0 | AV102: =AS102*SUM(AT102:AU102)%+AS102 -> 0
B103: 98 | C103: Cable Tag 150 mm big | D103: Local Brand | E103: Nos. | F103: 75 | G103: 0 | I103: =G103+H103 -> 0 | AO103: =SUM(J103:AN103) -> 0 | AP103: =I103-AO103 -> 0 | AQ103: =AO103*F103 -> 0 | AR103: =AP103*F103 -> 0 | AS103: =H103*F103 -> 0 | AV103: =AS103*SUM(AT103:AU103)%+AS103 -> 0
B104: 99 | C104: Sticker Label | D104: Local Brand | E104: Nos. | F104: 110 | G104: 0 | I104: =G104+H104 -> 0 | AO104: =SUM(J104:AN104) -> 0 | AP104: =I104-AO104 -> 0 | AQ104: =AO104*F104 -> 0 | AR104: =AP104*F104 -> 0 | AS104: =H104*F104 -> 0 | AV104: =AS104*SUM(AT104:AU104)%+AS104 -> 0
B105: 100 | C105: Sudarshan Dairy 100 pages | D105: Local Brand | E105: Nos. | F105: 150 | G105: 0 | I105: =G105+H105 -> 0 | AO105: =SUM(J105:AN105) -> 0 | AP105: =I105-AO105 -> 0 | AQ105: =AO105*F105 -> 0 | AR105: =AP105*F105 -> 0 | AS105: =H105*F105 -> 0 | AV105: =AS105*SUM(AT105:AU105)%+AS105 -> 0
B106: 101 | C106: Sheet Protector A4 (100) | D106: Local Brand | E106: Nos. | F106: 3.5 | G106: 169 | I106: =G106+H106 -> 169 | AO106: =SUM(J106:AN106) -> 0 | AP106: =I106-AO106 -> 169 | AQ106: =AO106*F106 -> 0 | AR106: =AP106*F106 -> 591.5 | AS106: =H106*F106 -> 0 | AV106: =AS106*SUM(AT106:AU106)%+AS106 -> 0
B107: 102 | C107: Sheet Protector A4 (240) | D107: Local Brand | E107: Nos. | F107: 3.5 | G107: 139 | I107: =G107+H107 -> 139 | N107: 50 | AO107: =SUM(J107:AN107) -> 50 | AP107: =I107-AO107 -> 89 | AQ107: =AO107*F107 -> 175 | AR107: =AP107*F107 -> 311.5 | AS107: =H107*F107 -> 0
B108: 103 | C108: Sheet Protector FC Legal (240) | D108: Local Brand | E108: Nos. | F108: 4.5 | G108: 207 | I108: =G108+H108 -> 207 | N108: 50 | AO108: =SUM(J108:AN108) -> 50 | AP108: =I108-AO108 -> 157 | AQ108: =AO108*F108 -> 225 | AR108: =AP108*F108 -> 706.5 | AS108: =H108*F108 -> 0 | AV108: =AS108*SUM(AT108:AU108)%+AS108 -> 0
...

Sheet HK Material
B2: =Summary!R5&" House Keeping Material Consumption of "& TEXT(Summary!R4," MMM YY") -> SOC House Keeping Material Consumption of Feb 26
J4: Auto | K4: =TEXT(K5,"ddd") -> Sun | L4: =TEXT(L5,"ddd") -> Mon | M4: =TEXT(M5,"ddd") -> Tue | N4: =TEXT(N5,"ddd") -> Wed | O4: =TEXT(O5,"ddd") -> Thu | P4: =TEXT(P5,"ddd") -> Fri | Q4: =TEXT(Q5,"ddd") -> Sat | R4: =TEXT(R5,"ddd") -> Sun | ... AO4: =TEXT(AO5,"ddd") -> Tue | AP4: Auto | AQ4: Auto | AR4: Auto | AS4: Auto | AT4: Auto | AW4: Auto
B5: Sr. No. | C5: Vendor | D5: Particulars | E5: Brand | F5: Units | G5: Rate | H5: Opening | I5: Order | J5: Total Stock | K5: =Summary!R4 -> 46054 | L5: =K5+1 -> 46055 | M5: =L5+1 -> 46056 | N5: =M5+1 -> 46057 | O5: =N5+1 -> 46058 | P5: =O5+1 -> 46059 | Q5: =P5+1 -> 46060 | R5: =Q5+1 -> 46061 | S5: =R5+1 -> 46062 | ... AO5: =AN5+1 -> 46084 | AP5: Usage Stock | AQ5: Closing Stock | AR5: Usage Amount | AS5: Closing Amount | AT5: Order Amount | AU5: CGST | AV5: SGST | AW5: Order Amount With GST | AX5: ACTUAL STOCK
B6: 1 | C6: Maple Solution | D6: Handwash | E6: 5ltr | F6: Nos. | G6: 350 | H6: 1 | I6: 1 | J6: =H6+I6 -> 2 | R6: 1 | AP6: =SUM(K6:AO6) -> 1 | AQ6: =J6-AP6 -> 1 | AR6: =AP6*G6 -> 350 | AS6: =AQ6*G6 -> 350 | AT6: =I6*G6 -> 350 | AW6: =AT6*SUM(AU6:AV6)%+AT6 -> 350
B7: 2 | C7: Maple Solution | D7: Dish Wash Liquid | E7: Vim | F7: Nos.(500 ml) | G7: 90 | H7: 3 | I7: 2 | J7: =H7+I7 -> 5 | L7: 1 | AP7: =SUM(K7:AO7) -> 1 | AQ7: =J7-AP7 -> 4 | AR7: =AP7*G7 -> 90 | AS7: =AQ7*G7 -> 360 | AT7: =I7*G7 -> 180 | AW7: =AT7*SUM(AU7:AV7)%+AT7 -> 180
B8: 3 | C8: Maple Solution | D8: Vim Bar | E8: vim | F8: Nos. | G8: 18 | H8: 3 | J8: =H8+I8 -> 3 | Z8: 1 | AP8: =SUM(K8:AO8) -> 1 | AQ8: =J8-AP8 -> 2 | AR8: =AP8*G8 -> 18 | AS8: =AQ8*G8 -> 36 | AT8: =I8*G8 -> 0 | AW8: =AT8*SUM(AU8:AV8)%+AT8 -> 0
B9: 4 | C9: Maple Solution | D9: Nirama Powder | E9: Wheel | F9: Kg. | G9: 65 | H9: 3 | J9: =H9+I9 -> 3 | AP9: =SUM(K9:AO9) -> 0 | AQ9: =J9-AP9 -> 3 | AR9: =AP9*G9 -> 0 | AS9: =AQ9*G9 -> 195 | AT9: =I9*G9 -> 0 | AW9: =AT9*SUM(AU9:AV9)%+AT9 -> 0
B10: 5 | C10: Maple Solution | D10: Scrub Pad | E10: Local Brand | F10: Nos. | G10: 9 | H10: 7 | J10: =H10+I10 -> 7 | O10: 1 | AP10: =SUM(K10:AO10) -> 1 | AQ10: =J10-AP10 -> 6 | AR10: =AP10*G10 -> 9 | AS10: =AQ10*G10 -> 54 | AT10: =I10*G10 -> 0 | AW10: =AT10*SUM(AU10:AV10)%+AT10 -> 0
B11: 6 | C11: Maple Solution | D11: Garbage Bag (19*21) | E11: A1 | F11: Pkt -30 NOS | G11: 40 | H11: 22 | J11: =H11+I11 -> 22 | O11: 1 | AB11: 1 | AP11: =SUM(K11:AO11) -> 2 | AQ11: =J11-AP11 -> 20 | AR11: =AP11*G11 -> 80 | AS11: =AQ11*G11 -> 800 | AT11: =I11*G11 -> 0 | AW11: =AT11*SUM(AU11:AV11)%+AT11 -> 0
B12: 7 | C12: Maple Solution | D12: Garbage Bag Big | E12: Citi Clean | F12: Pkt -10 NOS | G12: 70 | H12: 10 | I12: 10 | J12: =H12+I12 -> 20 | M12: 1 | N12: 1 | Q12: 1 | S12: 1 | AA12: 1 | AP12: =SUM(K12:AO12) -> 5 | AQ12: =J12-AP12 -> 15 | AR12: =AP12*G12 -> 350 | AS12: =AQ12*G12 -> 1050 | AT12: =I12*G12 -> 700 | AW12: =AT12*SUM(AU12:AV12)%+AT12 -> 700
B13: 8 | C13: Maple Solution | D13: Yellow Duster | E13: Local Brand | F13: Pcs. | G13: 17 | H13: 3 | J13: =H13+I13 -> 3 | AP13: =SUM(K13:AO13) -> 0 | AQ13: =J13-AP13 -> 3 | AR13: =AP13*G13 -> 0 | AS13: =AQ13*G13 -> 51 | AT13: =I13*G13 -> 0 | AW13: =AT13*SUM(AU13:AV13)%+AT13 -> 0
B14: 9 | C14: Maple Solution | D14: Checks Duster | E14: Local Brand | F14: Pcs. | G14: 11 | H14: 6 | J14: =H14+I14 -> 6 | AP14: =SUM(K14:AO14) -> 0 | AQ14: =J14-AP14 -> 6 | AR14: =AP14*G14 -> 0 | AS14: =AQ14*G14 -> 66 | AT14: =I14*G14 -> 0 | AW14: =AT14*SUM(AU14:AV14)%+AT14 -> 0
B15: 10 | C15: Maple Solution | D15: Glass Duster | E15: Local Brand | F15: Pcs. | G15: 12 | H15: 4 | J15: =H15+I15 -> 4 | AP15: =SUM(K15:AO15) -> 0 | AQ15: =J15-AP15 -> 4 | AR15: =AP15*G15 -> 0 | AS15: =AQ15*G15 -> 48 | AT15: =I15*G15 -> 0 | AW15: =AT15*SUM(AU15:AV15)%+AT15 -> 0
B16: 11 | C16: Maple Solution | D16: Dish Cleaner Duster | E16: Scotch | F16: Pcs. | G16: 40 | H16: 8 | J16: =H16+I16 -> 8 | AP16: =SUM(K16:AO16) -> 0 | AQ16: =J16-AP16 -> 8 | AR16: =AP16*G16 -> 0 | AS16: =AQ16*G16 -> 320 | AT16: =I16*G16 -> 0 | AW16: =AT16*SUM(AU16:AV16)%+AT16 -> 0
B17: 12 | C17: Maple Solution | D17: Wiper (Glass) Steel | E17: Local Brand | F17: Pcs. | G17: 240 | H17: 1 | J17: =H17+I17 -> 1 | AP17: =SUM(K17:AO17) -> 0 | AQ17: =J17-AP17 -> 1 | AR17: =AP17*G17 -> 0 | AS17: =AQ17*G17 -> 240 | AT17: =I17*G17 -> 0 | AW17: =AT17*SUM(AU17:AV17)%+AT17 -> 0
B18: 13 | C18: Maple Solution | D18: Soft Broom | E18: Music | F18: Nos. | G18: 85 | H18: 0 | J18: =H18+I18 -> 0 | AP18: =SUM(K18:AO18) -> 0 | AQ18: =J18-AP18 -> 0 | AR18: =AP18*G18 -> 0 | AS18: =AQ18*G18 -> 0 | AT18: =I18*G18 -> 0 | AW18: =AT18*SUM(AU18:AV18)%+AT18 -> 0
B19: 14 | C19: Maple Solution | D19: Collin | E19: Collin | F19: Nos. | G19: 72 | H19: 0 | I19: 4 | J19: =H19+I19 -> 4 | Z19: 1 | AP19: =SUM(K19:AO19) -> 1 | AQ19: =J19-AP19 -> 3 | AR19: =AP19*G19 -> 72 | AS19: =AQ19*G19 -> 216 | AT19: =I19*G19 -> 288 | AW19: =AT19*SUM(AU19:AV19)%+AT19 -> 288
B20: 15 | C20: Maple Solution | D20: Wet Mop Refill Cotton | E20: Taj | F20: Nos. | G20: 85 | H20: 2 | J20: =H20+I20 -> 2 | AP20: =SUM(K20:AO20) -> 0 | AQ20: =J20-AP20 -> 2 | AR20: =AP20*G20 -> 0 | AS20: =AQ20*G20 -> 170 | AT20: =I20*G20 -> 0 | AW20: =AT20*SUM(AU20:AV20)%+AT20 -> 0
B21: 16 | C21: Maple Solution | D21: Dry Mop Refill | E21: Taj | F21: Nos. | G21: 85 | H21: 12 | J21: =H21+I21 -> 12 | AP21: =SUM(K21:AO21) -> 0 | AQ21: =J21-AP21 -> 12 | AR21: =AP21*G21 -> 0 | AS21: =AQ21*G21 -> 1020 | AT21: =I21*G21 -> 0 | AW21: =AT21*SUM(AU21:AV21)%+AT21 -> 0
B22: 17 | C22: Maple Solution | D22: R6 | E22: Taski | F22: Can (5 Ltr.) | G22: 640 | H22: 1 | I22: 1 | J22: =H22+I22 -> 2 | AP22: =SUM(K22:AO22) -> 0 | AQ22: =J22-AP22 -> 2 | AR22: =AP22*G22 -> 0 | AS22: =AQ22*G22 -> 1280 | AT22: =I22*G22 -> 640 | AW22: =AT22*SUM(AU22:AV22)%+AT22 -> 640
B23: 18 | C23: Maple Solution | D23: R2 | E23: Taski | F23: Can (5 Ltr.) | G23: 780 | H23: 2 | J23: =H23+I23 -> 2 | AP23: =SUM(K23:AO23) -> 0 | AQ23: =J23-AP23 -> 2 | AR23: =AP23*G23 -> 0 | AS23: =AQ23*G23 -> 1560 | AT23: =I23*G23 -> 0 | AW23: =AT23*SUM(AU23:AV23)%+AT23 -> 0
B24: 19 | C24: Maple Solution | D24: Premier Facial Tissue | E24: Premier | F24: Box | G24: 62 | H24: 8 | I24: 25 | J24: =H24+I24 -> 33 | L24: 4 | T24: 4 | Z24: 1 | AP24: =SUM(K24:AO24) -> 9 | AQ24: =J24-AP24 -> 24 | AR24: =AP24*G24 -> 558 | AS24: =AQ24*G24 -> 1488 | AT24: =I24*G24 -> 1550 | AW24: =AT24*SUM(AU24:AV24)%+AT24 -> 1550
B25: 20 | C25: Maple Solution | D25: Hand Tissue | E25: Prince | F25: Pkt | G25: 24 | H25: 14 | I25: 30 | J25: =H25+I25 -> 44 | L25: 3 | M25: 1 | O25: 2 | P25: 1 | S25: 2 | T25: 4 | W25: 1 | Z25: 3 | AP25: =SUM(K25:AO25) -> 17 | AQ25: =J25-AP25 -> 27 | AR25: =AP25*G25 -> 408 | AS25: =AQ25*G25 -> 648 | AT25: =I25*G25 -> 720 | AW25: =AT25*SUM(AU25:AV25)%+AT25 -> 720
B26: 21 | C26: Maple Solution | D26: Carpet Brush | E26: Local Brand | F26: Nos. | G26: 65 | H26: 3 | J26: =H26+I26 -> 3 | AP26: =SUM(K26:AO26) -> 0 | AQ26: =J26-AP26 -> 3 | AR26: =AP26*G26 -> 0 | AS26: =AQ26*G26 -> 195 | AT26: =I26*G26 -> 0 | AW26: =AT26*SUM(AU26:AV26)%+AT26 -> 0
B27: 22 | C27: Maple Solution | D27: Hard Broom | E27: Local Brand | F27: Nos. | G27: 35 | H27: 0 | J27: =H27+I27 -> 0 | AP27: =SUM(K27:AO27) -> 0 | AQ27: =J27-AP27 -> 0 | AR27: =AP27*G27 -> 0 | AS27: =AQ27*G27 -> 0 | AT27: =I27*G27 -> 0 | AW27: =AT27*SUM(AU27:AV27)%+AT27 -> 0
B28: 23 | C28: Maple Solution | D28: Hand Gloves Red | E28: Himalya | F28: Nos. | G28: 40 | H28: 0 | J28: =H28+I28 -> 0 | AP28: =SUM(K28:AO28) -> 0 | AQ28: =J28-AP28 -> 0 | AR28: =AP28*G28 -> 0 | AS28: =AQ28*G28 -> 0 | AT28: =I28*G28 -> 0 | AW28: =AT28*SUM(AU28:AV28)%+AT28 -> 0
B29: 24 | C29: Maple Solution | D29: Red Hit Spary | E29: Hit | F29: Nos. | G29: 215 | H29: 2 | J29: =H29+I29 -> 2 | AP29: =SUM(K29:AO29) -> 0 | AQ29: =J29-AP29 -> 2 | AR29: =AP29*G29 -> 0 | AS29: =AQ29*G29 -> 430 | AT29: =I29*G29 -> 0 | AW29: =AT29*SUM(AU29:AV29)%+AT29 -> 0
B30: 25 | C30: Maple Solution | D30: Hand Gloves blue | E30: Local Brand | F30: Set | G30: 40 | H30: 12 | J30: =H30+I30 -> 12 | AP30: =SUM(K30:AO30) -> 0 | AQ30: =J30-AP30 -> 12 | AR30: =AP30*G30 -> 0 | AS30: =AQ30*G30 -> 480 | AT30: =I30*G30 -> 0 | AW30: =AT30*SUM(AU30:AV30)%+AT30 -> 0
B31: 26 | C31: Maple Solution | D31: Dust Pan | E31: Balaji | F31: Nos. | G31: 30 | H31: 5 | J31: =H31+I31 -> 5 | AP31: =SUM(K31:AO31) -> 0 | AQ31: =J31-AP31 -> 5 | AR31: =AP31*G31 -> 0 | AS31: =AQ31*G31 -> 150 | AT31: =I31*G31 -> 0 | AW31: =AT31*SUM(AU31:AV31)%+AT31 -> 0
B32: 27 | C32: Maple Solution | D32: T - Brush Set | E32: Local Brand | F32: Nos. | G32: 145 | H32: 1 | J32: =H32+I32 -> 1 | AP32: =SUM(K32:AO32) -> 0 | AQ32: =J32-AP32 -> 1 | AR32: =AP32*G32 -> 0 | AS32: =AQ32*G32 -> 145 | AT32: =I32*G32 -> 0 | AW32: =AT32*SUM(AU32:AV32)%+AT32 -> 0
B33: 28 | C33: Maple Solution | D33: Big Dust Bin - 80 Lit | E33: Balaji | F33: Nos. | G33: 950 | H33: 0 | J33: =H33+I33 -> 0 | AP33: =SUM(K33:AO33) -> 0 | AQ33: =J33-AP33 -> 0 | AR33: =AP33*G33 -> 0 | AS33: =AQ33*G33 -> 0 | AT33: =I33*G33 -> 0 | AW33: =AT33*SUM(AU33:AV33)%+AT33 -> 0
B34: 29 | C34: Maple Solution | D34: Chock Up Pump | E34: Local Brand | F34: Nos. | G34: 45 | H34: 4 | J34: =H34+I34 -> 4 | AP34: =SUM(K34:AO34) -> 0 | AQ34: =J34-AP34 -> 4 | AR34: =AP34*G34 -> 0 | AS34: =AQ34*G34 -> 180 | AT34: =I34*G34 -> 0 | AW34: =AT34*SUM(AU34:AV34)%+AT34 -> 0
B35: 30 | C35: Maple Solution | D35: Godrej Air Freshner Bottle | E35: Local Brand | F35: Nos. | G35: 140 | H35: 4 | J35: =H35+I35 -> 4 | Z35: 1 | AP35: =SUM(K35:AO35) -> 1 | AQ35: =J35-AP35 -> 3 | AR35: =AP35*G35 -> 140 | AS35: =AQ35*G35 -> 420 | AT35: =I35*G35 -> 0 | AW35: =AT35*SUM(AU35:AV35)%+AT35 -> 0
B36: 31 | C36: Maple Solution | D36: Room Freshner | E36: Odonil | F36: Nos. | G36: 102 | H36: 2 | J36: =H36+I36 -> 2 | AP36: =SUM(K36:AO36) -> 0 | AQ36: =J36-AP36 -> 2 | AR36: =AP36*G36 -> 0 | AS36: =AQ36*G36 -> 204 | AT36: =I36*G36 -> 0 | AW36: =AT36*SUM(AU36:AV36)%+AT36 -> 0
B37: 32 | C37: Maple Solution | D37: Combi Glass Wiper | E37: Local Brand | F37: Nos. | G37: 350 | H37: 1 | J37: =H37+I37 -> 1 | AP37: =SUM(K37:AO37) -> 0 | AQ37: =J37-AP37 -> 1 | AR37: =AP37*G37 -> 0 | AS37: =AQ37*G37 -> 350 | AT37: =I37*G37 -> 0 | AW37: =AT37*SUM(AU37:AV37)%+AT37 -> 0
B38: 33 | C38: Maple Solution | D38: R5 | E38: Taski | F38: Can | G38: 900 | H38: 1 | J38: =H38+I38 -> 1 | AP38: =SUM(K38:AO38) -> 0 | AQ38: =J38-AP38 -> 1 | AR38: =AP38*G38 -> 0 | AS38: =AQ38*G38 -> 900 | AT38: =I38*G38 -> 0 | AW38: =AT38*SUM(AU38:AV38)%+AT38 -> 0
B39: 34 | C39: Maple Solution | D39: R3 | E39: Taski | F39: Can | G39: 1450 | H39: 0 | J39: =H39+I39 -> 0 | AP39: =SUM(K39:AO39) -> 0 | AQ39: =J39-AP39 -> 0 | AR39: =AP39*G39 -> 0 | AS39: =AQ39*G39 -> 0 | AT39: =I39*G39 -> 0 | AW39: =AT39*SUM(AU39:AV39)%+AT39 -> 0
B40: 35 | C40: Maple Solution | D40: R1 | E40: Taski | F40: Can | G40: 980 | H40: 2 | J40: =H40+I40 -> 2 | AP40: =SUM(K40:AO40) -> 0 | AQ40: =J40-AP40 -> 2 | AR40: =AP40*G40 -> 0 | AS40: =AQ40*G40 -> 1960 | AT40: =I40*G40 -> 0 | AW40: =AT40*SUM(AU40:AV40)%+AT40 -> 0
B41: 36 | C41: Maple Solution | D41: Bottle Brush | E41: Local Brand | F41: Nos. | G41: 30 | H41: 5 | J41: =H41+I41 -> 5 | AP41: =SUM(K41:AO41) -> 0 | AQ41: =J41-AP41 -> 5 | AR41: =AP41*G41 -> 0 | AS41: =AQ41*G41 -> 150 | AT41: =I41*G41 -> 0 | AW41: =AT41*SUM(AU41:AV41)%+AT41 -> 0
B42: 37 | C42: Maple Solution | D42: Wet Mop Set | E42: Local Brand | F42: Nos. | G42: 225 | H42: 0 | J42: =H42+I42 -> 0 | AP42: =SUM(K42:AO42) -> 0 | AQ42: =J42-AP42 -> 0 | AR42: =AP42*G42 -> 0 | AS42: =AQ42*G42 -> 0 | AT42: =I42*G42 -> 0 | AW42: =AT42*SUM(AU42:AV42)%+AT42 -> 0
B43: 38 | C43: Maple Solution | D43: Dry Mop Set | E43: Taj | F43: Nos. | G43: 265 | H43: 2 | J43: =H43+I43 -> 2 | L43: 1 | AP43: =SUM(K43:AO43) -> 1 | AQ43: =J43-AP43 -> 1 | AR43: =AP43*G43 -> 265 | AS43: =AQ43*G43 -> 265 | AT43: =I43*G43 -> 0 | AW43: =AT43*SUM(AU43:AV43)%+AT43 -> 0
B44: 39 | C44: Maple Solution | D44: Mosquito Bat | E44: Balaji | F44: Pkt | G44: 195 | H44: 0 | J44: =H44+I44 -> 0 | AP44: =SUM(K44:AO44) -> 0 | AQ44: =J44-AP44 -> 0 | AR44: =AP44*G44 -> 0 | AS44: =AQ44*G44 -> 0 | AT44: =I44*G44 -> 0 | AW44: =AT44*SUM(AU44:AV44)%+AT44 -> 0
B45: 40 | C45: Maple Solution | D45: Dettol Hand Wash | E45: Dettol | F45: Nos | G45: 175 | H45: 0 | I45: 1 | J45: =H45+I45 -> 1 | AP45: =SUM(K45:AO45) -> 0 | AQ45: =J45-AP45 -> 1 | AR45: =AP45*G45 -> 0 | AS45: =AQ45*G45 -> 175 | AT45: =I45*G45 -> 175 | AW45: =AT45*SUM(AU45:AV45)%+AT45 -> 175
B46: 41 | C46: Maple Solution | D46: Dust Bin Small | E46: Balaji | F46: Nos. | G46: 32 | H46: 0 | J46: =H46+I46 -> 0 | AP46: =SUM(K46:AO46) -> 0 | AQ46: =J46-AP46 -> 0 | AR46: =AP46*G46 -> 0 | AS46: =AQ46*G46 -> 0 | AT46: =I46*G46 -> 0 | AW46: =AT46*SUM(AU46:AV46)%+AT46 -> 0
B47: 42 | C47: Maple Solution | D47: Water Bottle | E47: G Pet | F47: Nos. | G47: 30 | H47: 2 | I47: 6 | J47: =H47+I47 -> 8 | L47: 1 | R47: 1 | AP47: =SUM(K47:AO47) -> 2 | AQ47: =J47-AP47 -> 6 | AR47: =AP47*G47 -> 60 | AS47: =AQ47*G47 -> 180 | AT47: =I47*G47 -> 180 | AW47: =AT47*SUM(AU47:AV47)%+AT47 -> 180
B48: 43 | C48: Maple Solution | D48: Scrapper | E48: Local Brand | F48: Nos. | G48: 14 | H48: 0 | J48: =H48+I48 -> 0 | AP48: =SUM(K48:AO48) -> 0 | AQ48: =J48-AP48 -> 0 | AR48: =AP48*G48 -> 0 | AS48: =AQ48*G48 -> 0 | AT48: =I48*G48 -> 0 | AW48: =AT48*SUM(AU48:AV48)%+AT48 -> 0
B49: 44 | C49: Maple Solution | D49: Paper Cup 150 ml | E49: Pooja | F49: Pkt | G49: 55 | H49: 177 | I49: 300 | J49: =H49+I49 -> 477 | L49: 9 | M49: 13 | N49: 10 | O49: 11 | P49: 13 | Q49: 6 | S49: 9 | T49: 10 | U49: 7 | V49: 10 | W49: 12 | Z49: 16 | AA49: 14 | AP49: =SUM(K49:AO49) -> 140 | AQ49: =J49-AP49 -> 337 | AR49: =AP49*G49 -> 7700 | AS49: =AQ49*G49 -> 18535 | AT49: =I49*G49 -> 16500 | AW49: =AT49*SUM(AU49:AV49)%+AT49 -> 16500
B50: 45 | C50: Maple Solution | D50: R4 | E50: Taski | F50: Can | G50: 1850 | H50: 0 | J50: =H50+I50 -> 0 | AP50: =SUM(K50:AO50) -> 0 | AQ50: =J50-AP50 -> 0 | AR50: =AP50*G50 -> 0 | AS50: =AQ50*G50 -> 0 | AT50: =I50*G50 -> 0 | AW50: =AT50*SUM(AU50:AV50)%+AT50 -> 0
B51: 46 | C51: Maple Solution | D51: Dry Mop Set 24 Blue Colur | E51: Local Brand | F51: Nos | G51: 300 | H51: 0 | J51: =H51+I51 -> 0 | AP51: =SUM(K51:AO51) -> 0 | AQ51: =J51-AP51 -> 0 | AR51: =AP51*G51 -> 0 | AS51: =AQ51*G51 -> 0 | AT51: =I51*G51 -> 0 | AW51: =AT51*SUM(AU51:AV51)%+AT51 -> 0
B52: 47 | C52: Maple Solution | D52: Rat Pad | E52: Local Brand | F52: Nos. | G52: 80 | H52: 9 | J52: =H52+I52 -> 9 | AP52: =SUM(K52:AO52) -> 0 | AQ52: =J52-AP52 -> 9 | AR52: =AP52*G52 -> 0 | AS52: =AQ52*G52 -> 720 | AT52: =I52*G52 -> 0 | AW52: =AT52*SUM(AU52:AV52)%+AT52 -> 0
B53: 48 | C53: Maple Solution | D53: Cafeteria Caddy | E53: Local Brand | F53: Nos. | G53: 350 | H53: 0 | J53: =H53+I53 -> 0 | AP53: =SUM(K53:AO53) -> 0 | AQ53: =J53-AP53 -> 0 | AR53: =AP53*G53 -> 0 | AS53: =AQ53*G53 -> 0 | AT53: =I53*G53 -> 0 | AW53: =AT53*SUM(AU53:AV53)%+AT53 -> 0
B54: 49 | C54: Maple Solution | D54: Fether brush (Small) | E54: Local Brand | F54: Nos. | G54: 35 | H54: 1 | J54: =H54+I54 -> 1 | AP54: =SUM(K54:AO54) -> 0 | AQ54: =J54-AP54 -> 1 | AR54: =AP54*G54 -> 0 | AS54: =AQ54*G54 -> 35 | AT54: =I54*G54 -> 0 | AW54: =AT54*SUM(AU54:AV54)%+AT54 -> 0
B55: 50 | C55: Maple Solution | D55: Fether brush (Big) | E55: Local Brand | F55: Nos. | G55: 45 | H55: 4 | J55: =H55+I55 -> 4 | AP55: =SUM(K55:AO55) -> 0 | AQ55: =J55-AP55 -> 4 | AR55: =AP55*G55 -> 0 | AS55: =AQ55*G55 -> 180 | AT55: =I55*G55 -> 0 | AW55: =AT55*SUM(AU55:AV55)%+AT55 -> 0
B56: 51 | C56: Maple Solution | D56: TR 101 | E56: Taski | F56: Can (5 Ltr.) | G56: 1150 | H56: 0 | J56: =H56+I56 -> 0 | AP56: =SUM(K56:AO56) -> 0 | AQ56: =J56-AP56 -> 0 | AR56: =AP56*G56 -> 0 | AS56: =AQ56*G56 -> 0 | AT56: =I56*G56 -> 0 | AW56: =AT56*SUM(AU56:AV56)%+AT56 -> 0
B57: 52 | C57: Maple Solution | D57: Nylon Scrubber | E57: Local Brand | F57: Nos. | G57: 5 | H57: 6 | J57: =H57+I57 -> 6 | AP57: =SUM(K57:AO57) -> 0 | AQ57: =J57-AP57 -> 6 | AR57: =AP57*G57 -> 0 | AS57: =AQ57*G57 -> 30 | AT57: =I57*G57 -> 0 | AW57: =AT57*SUM(AU57:AV57)%+AT57 -> 0
B58: 53 | C58: Maple Solution | D58: Empty Bottle Sanitizer | E58: Local Brand | F58: Nos. | G58: 45 | H58: 1 | J58: =H58+I58 -> 1 | AP58: =SUM(K58:AO58) -> 0 | AQ58: =J58-AP58 -> 1 | AR58: =AP58*G58 -> 0 | AS58: =AQ58*G58 -> 45 | AT58: =I58*G58 -> 0 | AW58: =AT58*SUM(AU58:AV58)%+AT58 -> 0
B59: 54 | C59: Maple Solution | D59: Yellow Spunch | E59: Local Brand | F59: Nos. | G59: 8 | H59: 5 | J59: =H59+I59 -> 5 | AP59: =SUM(K59:AO59) -> 0 | AQ59: =J59-AP59 -> 5 | AR59: =AP59*G59 -> 0 | AS59: =AQ59*G59 -> 40 | AT59: =I59*G59 -> 0 | AW59: =AT59*SUM(AU59:AV59)%+AT59 -> 0
B60: 55 | C60: Maple Solution | D60: Green Garbage bag Big | E60: Citi Clean | F60: Pkt -10 NOS | G60: 280 | H60: 1 | J60: =H60+I60 -> 1 | AP60: =SUM(K60:AO60) -> 0 | AQ60: =J60-AP60 -> 1 | AR60: =AP60*G60 -> 0 | AS60: =AQ60*G60 -> 280 | AT60: =I60*G60 -> 0 | AW60: =AT60*SUM(AU60:AV60)%+AT60 -> 0
B61: 56 | C61: Maple Solution | D61: Taski D7 | E61: Taski | F61: Can (5 Ltr.) | G61: 950 | H61: 0 | J61: =H61+I61 -> 0 | AP61: =SUM(K61:AO61) -> 0 | AQ61: =J61-AP61 -> 0 | AR61: =AP61*G61 -> 0 | AS61: =AQ61*G61 -> 0 | AT61: =I61*G61 -> 0 | AW61: =AT61*SUM(AU61:AV61)%+AT61 -> 0
... B66: 61 | C66: Maple Solution | D66: Toilet Brush round | E66: Local Brand | F66: Nos | G66: 55 | H66: 4 | J66: =H66+I66 -> 4 | AP66: =SUM(K66:AO66) -> 0 | AQ66: =J66-AP66 -> 4 | AR66: =AP66*G66 -> 0 | AS66: =AQ66*G66 -> 220 | AT66: =I66*G66 -> 0 | AW66: =AT66*SUM(AU66:AV66)%+AT66 -> 0
B67: 62 | C67: Maple Solution | D67: Tissue roll big | E67: Local Brand | F67: Nos | G67: 20 | H67: 96 | I67: 1008 | J67: =H67+I67 -> 1104 | L67: 48 | M67: 48 | N67: 48 | O67: 48 | P67: 48 | S67: 48 | T67: 48 | U67: 48 | V67: 48 | W67: 48 | Z67: 48 | AA67: 48 | AB67: 24 | AP67: =SUM(K67:AO67) -> 600 | AQ67: =J67-AP67 -> 504 | AR67: =AP67*G67 -> 12000 | AS67: =AQ67*G67 -> 10080 | AT67: =I67*G67 -> 20160 | AW67: =AT67*SUM(AU67:AV67)%+AT67 -> 20160
B68: 63 | C68: Maple Solution | D68: Hand Brush | E68: Local Brand | F68: Nos | G68: 60 | H68: 1 | J68: =H68+I68 -> 1 | AP68: =SUM(K68:AO68) -> 0 | AQ68: =J68-AP68 -> 1 | AR68: =AP68*G68 -> 0 | AS68: =AQ68*G68 -> 60 | AT68: =I68*G68 -> 0 | AW68: =AT68*SUM(AU68:AV68)%+AT68 -> 0
B69: 64 | C69: Maple Solution | D69: Acid Strong | E69: Local Brand | F69: 5Ltr | G69: 350 | H69: 1 | I69: 1 | J69: =H69+I69 -> 2 | AP69: =SUM(K69:AO69) -> 0 | AQ69: =J69-AP69 -> 2 | AR69: =AP69*G69 -> 0 | AS69: =AQ69*G69 -> 700 | AT69: =I69*G69 -> 350 | AW69: =AT69*SUM(AU69:AV69)%+AT69 -> 350
B70: 65 | C70: Maple Solution | D70: Urinal Screen | E70: Local Brand | F70: Nos | G70: 120 | H70: 4 | I70: 10 | J70: =H70+I70 -> 14 | L70: 1 | Z70: 6 | AP70: =SUM(K70:AO70) -> 7 | AQ70: =J70-AP70 -> 7 | AR70: =AP70*G70 -> 840 | AS70: =AQ70*G70 -> 840 | AT70: =I70*G70 -> 1200 | AW70: =AT70*SUM(AU70:AV70)%+AT70 -> 1200
B71: 66 | C71: Maple Solution | D71: Colour Goli Kohinoor | E71: Local Brand | F71: Pkt | G71: 40 | H71: 5 | I71: 5 | J71: =H71+I71 -> 10 | L71: 1 | Z71: 1 | AP71: =SUM(K71:AO71) -> 2 | AQ71: =J71-AP71 -> 8 | AR71: =AP71*G71 -> 80 | AS71: =AQ71*G71 -> 320 | AT71: =I71*G71 -> 200 | AW71: =AT71*SUM(AU71:AV71)%+AT71 -> 200
B72: 67 | C72: Maple Solution | D72: Himalaya Hand Sanitizer | E72: Local Brand | F72: Nos | G72: 345 | H72: 1 | J72: =H72+I72 -> 1 | AP72: =SUM(K72:AO72) -> 0 | AQ72: =J72-AP72 -> 1 | AR72: =AP72*G72 -> 0 | AS72: =AQ72*G72 -> 345 | AT72: =I72*G72 -> 0 | AW72: =AT72*SUM(AU72:AV72)%+AT72 -> 0
B73: 68 | C73: Maple Solution | D73: Odonil | E73: Local Brand | F73: Nos | G73: 38 | H73: 10 | J73: =H73+I73 -> 10 | AP73: =SUM(K73:AO73) -> 0 | AQ73: =J73-AP73 -> 10 | AR73: =AP73*G73 -> 0 | AS73: =AQ73*G73 -> 380 | AT73: =I73*G73 -> 0 | AW73: =AT73*SUM(AU73:AV73)%+AT73 -> 0
B74: 69 | C74: Maple Solution | D74: Lather tissue box | E74: Local Brand | F74: Nos | G74: 435 | H74: 0 | J74: =H74+I74 -> 0 | AP74: =SUM(K74:AO74) -> 0 | AQ74: =J74-AP74 -> 0 | AR74: =AP74*G74 -> 0 | AS74: =AQ74*G74 -> 0 | AT74: =I74*G74 -> 0 | AW74: =AT74*SUM(AU74:AV74)%+AT74 -> 0
B75: 70 | C75: Maple Solution | D75: Max M fold Tissue | E75: Local Brand | F75: Pkt | G75: 70 | H75: 18 | J75: =H75+I75 -> 18 | P75: 1 | AP75: =SUM(K75:AO75) -> 1 | AQ75: =J75-AP75 -> 17 | AR75: =AP75*G75 -> 70 | AS75: =AQ75*G75 -> 1190 | AT75: =I75*G75 -> 0 | AW75: =AT75*SUM(AU75:AV75)%+AT75 -> 0
B76: 71 | C76: Maple Solution | D76: Serving tray | E76: Local Brand | F76: Nos | G76: 350 | H76: 0 | J76: =H76+I76 -> 0 | AP76: =SUM(K76:AO76) -> 0 | AQ76: =J76-AP76 -> 0 | AR76: =AP76*G76 -> 0 | AS76: =AQ76*G76 -> 0 | AT76: =I76*G76 -> 0 | AW76: =AT76*SUM(AU76:AV76)%+AT76 -> 0
B77: 72 | C77: Maple Solution | D77: Stainless Steel Scrubber | E77: Local Brand | F77: Nos | G77: 15 | H77: 0 | J77: =H77+I77 -> 0 | AP77: =SUM(K77:AO77) -> 0 | AQ77: =J77-AP77 -> 0 | AR77: =AP77*G77 -> 0 | AS77: =AQ77*G77 -> 0 | AT77: =I77*G77 -> 0 | AW77: =AT77*SUM(AU77:AV77)%+AT77 -> 0
B78: 73 | C78: Maple Solution | D78: Hand Sainitizer Gel | E78: Local Brand | F78: 5ltr | G78: 650 | H78: 1 | I78: 1 | J78: =H78+I78 -> 2 | S78: 1 | AP78: =SUM(K78:AO78) -> 1 | AQ78: =J78-AP78 -> 1 | AR78: =AP78*G78 -> 650 | AS78: =AQ78*G78 -> 650 | AT78: =I78*G78 -> 650 | AW78: =AT78*SUM(AU78:AV78)%+AT78 -> 650
B79: 74 | C79: Maple Solution | D79: Surgical Mask | E79: Local Brand | F79: Nos. | G79: 3.5 | H79: 71 | J79: =H79+I79 -> 71 | N79: 2 | AP79: =SUM(K79:AO79) -> 2 | AQ79: =J79-AP79 -> 69 | AR79: =AP79*G79 -> 7 | AS79: =AQ79*G79 -> 241.5 | AT79: =I79*G79 -> 0 | AW79: =AT79*SUM(AU79:AV79)%+AT79 -> 0
B80: 75 | C80: Maple Solution | H80: 0 | AP80: =SUM(K80:AO80) -> 0 | AQ80: =J80-AP80 -> 0 | AR80: =AP80*G80 -> 0 | AS80: =AQ80*G80 -> 0 | AT80: =I80*G80 -> 0 | AW80: =AT80*SUM(AU80:AV80)%+AT80 -> 0
D81: Total | H81: =SUM(H6:H80) -> 579 | I81: =SUM(I6:I80) -> 1405 | J81: =SUM(J6:J80) -> 1984 | K81: =SUM(K6:K80) -> 0 | L81: =SUM(L6:L80) -> 69 | M81: =SUM(M6:M80) -> 63 | N81: =SUM(N6:N80) -> 61 | O81: =SUM(O6:O80) -> 63 | ... AT81: =SUM(AT6:AT80) -> 43843 | AW81: =SUM(AW6:AW80) -> 43843 | AX81: =SUM(AX6:AX80) -> 0
H86: 9
H87: 0

Sheet Food Consu
B2: =Summary!R5&" Food Report " & TEXT(Summary!R4,"MMMM-YYY") -> SOC Food Report February-2026
A4: Days | B4: Date | C4: Rate | E4: Datta Caters | G4: Sai Caters | J4: Auto | K4: Auto | M4: Auto | N4: Auto
C5: V/N | E5: Lunch Order | F5: Lunch Count | G5: Dinner Order | H5: Dinner Count | J5: Total Order | K5: Total Count | M5: Total Order | N5: Total Amount
A6: =TEXT(B6,"ddd") -> Sun | B6: =Summary!R4 -> 46054 | C6: =IF(OR(WEEKDAY(B6)=4, WEEKDAY(B6)=6), 75, IF(OR(WEEKDAY(B6)=1, WEEKDAY(B6)=7), 0, 70)) -> 0 | J6: =G6+E6 -> 0 | K6: =H6+F6 -> 0 | M6: =C6*J6 -> 0 | N6: =K6*$C6 -> 0
A7: =TEXT(B7,"ddd") -> Mon | B7: =B6+1 -> 46055 | C7: =IF(OR(WEEKDAY(B7)=4, WEEKDAY(B7)=6), 75, IF(OR(WEEKDAY(B7)=1, WEEKDAY(B7)=7), 0, 70)) -> 70 | J7: =G7+E7 -> 0 | K7: =H7+F7 -> 0 | M7: =C7*J7 -> 0 | N7: =K7*$C7 -> 0
A8: =TEXT(B8,"ddd") -> Tue | B8: =B7+1 -> 46056 | C8: =IF(OR(WEEKDAY(B8)=4, WEEKDAY(B8)=6), 75, IF(OR(WEEKDAY(B8)=1, WEEKDAY(B8)=7), 0, 70)) -> 70 | J8: =G8+E8 -> 0 | K8: =H8+F8 -> 0 | M8: =C8*J8 -> 0 | N8: =K8*$C8 -> 0
A9: =TEXT(B9,"ddd") -> Wed | B9: =B8+1 -> 46057 | C9: =IF(OR(WEEKDAY(B9)=4, WEEKDAY(B9)=6), 75, IF(OR(WEEKDAY(B9)=1, WEEKDAY(B9)=7), 0, 70)) -> 75 | J9: =G9+E9 -> 0 | K9: =H9+F9 -> 0 | M9: =C9*J9 -> 0 | N9: =K9*$C9 -> 0
A10: =TEXT(B10,"ddd") -> Thu | B10: =B9+1 -> 46058 | C10: =IF(OR(WEEKDAY(B10)=4, WEEKDAY(B10)=6), 75, IF(OR(WEEKDAY(B10)=1, WEEKDAY(B10)=7), 0, 70)) -> 70 | J10: =G10+E10 -> 0 | K10: =H10+F10 -> 0 | M10: =C10*J10 -> 0 | N10: =K10*$C10 -> 0
A11: =TEXT(B11,"ddd") -> Fri | B11: =B10+1 -> 46059 | C11: =IF(OR(WEEKDAY(B11)=4, WEEKDAY(B11)=6), 75, IF(OR(WEEKDAY(B11)=1, WEEKDAY(B11)=7), 0, 70)) -> 75 | J11: =G11+E11 -> 0 | K11: =H11+F11 -> 0 | M11: =C11*J11 -> 0 | N11: =K11*$C11 -> 0
A12: =TEXT(B12,"ddd") -> Sat | B12: =B11+1 -> 46060 | C12: =IF(OR(WEEKDAY(B12)=4, WEEKDAY(B12)=6), 75, IF(OR(WEEKDAY(B12)=1, WEEKDAY(B12)=7), 0, 70)) -> 0 | J12: =G12+E12 -> 0 | K12: =H12+F12 -> 0 | M12: =C12*J12 -> 0 | N12: =K12*$C12 -> 0
A13: =TEXT(B13,"ddd") -> Sun | B13: =B12+1 -> 46061 | C13: =IF(OR(WEEKDAY(B13)=4, WEEKDAY(B13)=6), 75, IF(OR(WEEKDAY(B13)=1, WEEKDAY(B13)=7), 0, 70)) -> 0 | J13: =G13+E13 -> 0 | K13: =H13+F13 -> 0 | M13: =C13*J13 -> 0 | N13: =K13*$C13 -> 0
A14: =TEXT(B14,"ddd") -> Mon | B14: =B13+1 -> 46062 | C14: =IF(OR(WEEKDAY(B14)=4, WEEKDAY(B14)=6), 75, IF(OR(WEEKDAY(B14)=1, WEEKDAY(B14)=7), 0, 70)) -> 70 | J14: =G14+E14 -> 0 | K14: =H14+F14 -> 0 | M14: =C14*J14 -> 0 | N14: =K14*$C14 -> 0
A15: =TEXT(B15,"ddd") -> Tue | B15: =B14+1 -> 46063 | C15: =IF(OR(WEEKDAY(B15)=4, WEEKDAY(B15)=6), 75, IF(OR(WEEKDAY(B15)=1, WEEKDAY(B15)=7), 0, 70)) -> 70 | J15: =G15+E15 -> 0 | K15: =H15+F15 -> 0 | M15: =C15*J15 -> 0 | N15: =K15*$C15 -> 0
A16: =TEXT(B16,"ddd") -> Wed | B16: =B15+1 -> 46064 | C16: =IF(OR(WEEKDAY(B16)=4, WEEKDAY(B16)=6), 75, IF(OR(WEEKDAY(B16)=1, WEEKDAY(B16)=7), 0, 70)) -> 75 | J16: =G16+E16 -> 0 | K16: =H16+F16 -> 0 | M16: =C16*J16 -> 0 | N16: =K16*$C16 -> 0
A17: =TEXT(B17,"ddd") -> Thu | B17: =B16+1 -> 46065 | C17: =IF(OR(WEEKDAY(B17)=4, WEEKDAY(B17)=6), 75, IF(OR(WEEKDAY(B17)=1, WEEKDAY(B17)=7), 0, 70)) -> 70 | J17: =G17+E17 -> 0 | K17: =H17+F17 -> 0 | M17: =C17*J17 -> 0 | N17: =K17*$C17 -> 0
A18: =TEXT(B18,"ddd") -> Fri | B18: =B17+1 -> 46066 | C18: =IF(OR(WEEKDAY(B18)=4, WEEKDAY(B18)=6), 75, IF(OR(WEEKDAY(B18)=1, WEEKDAY(B18)=7), 0, 70)) -> 75 | J18: =G18+E18 -> 0 | K18: =H18+F18 -> 0 | M18: =C18*J18 -> 0 | N18: =K18*$C18 -> 0
... A34: =TEXT(B34,"ddd") -> Sun | B34: =B33+1 -> 46082 | C34: =IF(OR(WEEKDAY(B34)=4, WEEKDAY(B34)=6), 75, IF(OR(WEEKDAY(B34)=1, WEEKDAY(B34)=7), 0, 70)) -> 0 | J34: =G34+E34 -> 0 | K34: =H34+F34 -> 0 | M34: =C34*J34 -> 0 | N34: =K34*$C34 -> 0
A35: =TEXT(B35,"ddd") -> Mon | B35: =B34+1 -> 46083 | C35: 75 | J35: =G35+E35 -> 0 | K35: =H35+F35 -> 0 | M35: =C35*J35 -> 0 | N35: =K35*$C35 -> 0
A36: =TEXT(B36,"ddd") -> Tue | B36: =B35+1 -> 46084 | C36: =IF(OR(WEEKDAY(B36)=4, WEEKDAY(B36)=6), 75, IF(OR(WEEKDAY(B36)=1, WEEKDAY(B36)=7), 0, 70)) -> 70 | J36: =G36+E36 -> 0 | K36: =H36+F36 -> 0 | M36: =C36*J36 -> 0 | N36: =K36*$C36 -> 0
A37: Grand Total | E37: =SUM(E6:E36) -> 0 | F37: =SUM(F6:F36) -> 0 | G37: =SUM(G6:G36) -> 0 | H37: =SUM(H6:H36) -> 0 | J37: =SUM(J6:J36) -> 0 | K37: =SUM(K6:K36) -> 0 | M37: =SUM(M6:M36) -> 0 | N37: =SUM(N6:N36) -> 0

Sheet Veebha Tea&Coffee
B2: =Summary!R5&" Veebha Material Consumption for the Month of "& TEXT(Summary!R4," MMM YY") -> SOC Veebha Material Consumption for the Month of Feb 26
N4: Auto | O4: =TEXT(O5,"ddd") -> Sun | P4: =TEXT(P5,"ddd") -> Mon | Q4: =TEXT(Q5,"ddd") -> Tue | R4: =TEXT(R5,"ddd") -> Wed | S4: =TEXT(S5,"ddd") -> Thu | T4: =TEXT(T5,"ddd") -> Fri | U4: =TEXT(U5,"ddd") -> Sat | V4: =TEXT(V5,"ddd") -> Sun | ... AS4: =TEXT(AS5,"ddd") -> Tue | AT4: Auto | AU4: Auto | AV4: Auto | AW4: Auto | AX4: Auto | BA4: Auto
B5: Sr. No. | C5: Vendor | D5: Particulars | E5: Brand | F5: Units | G5: Rate | H5: Opening | I5: Order | J5: Mantri Order Taken | K5: WTC Order Taken | L5: Other Sources | M5: Remark | N5: Total Stock | O5: =Summary!R4 -> 46054 | P5: =O5+1 -> 46055 | Q5: =P5+1 -> 46056 | R5: =Q5+1 -> 46057 | S5: =R5+1 -> 46058 | T5: =S5+1 -> 46059 | U5: =T5+1 -> 46060 | V5: =U5+1 -> 46061 | W5: =V5+1 -> 46062 | ... AS5: =AR5+1 -> 46084 | AT5: Usage Stock | AU5: Closing Stock | AV5: Usage Amount | AW5: Closing Amount | AX5: Order Amount | AY5: CGST | AZ5: SGST | BA5: Order Amount With GST
B6: 1 | C6: Veebha | D6: Tea Perimax | F6: PKT. (750ML) | G6: 160 | H6: 82 | N6: =SUM(H6:L6) -> 82 | AT6: =SUM(O6:AS6) -> 0 | AU6: =N6-AT6 -> 82 | AV6: =AT6*G6 -> 0 | AW6: =AU6*G6 -> 13120 | AX6: =I6*G6 -> 0 | BA6: =AX6*SUM(AY6:AZ6)%+AX6 -> 0
B7: 2 | C7: Veebha | D7: Coffee | F7: PKT. (750ML) | G7: 160 | H7: 82 | N7: =SUM(H7:L7) -> 82 | X7: 5 | AA7: 3 | AT7: =SUM(O7:AS7) -> 8 | AU7: =N7-AT7 -> 74 | AV7: =AT7*G7 -> 1280 | AW7: =AU7*G7 -> 11840 | AX7: =I7*G7 -> 0 | BA7: =AX7*SUM(AY7:AZ7)%+AX7 -> 0
AT8: =SUM(O8:AS8) -> 0 | AU8: =N8-AT8 -> 0 | AV8: =AT8*G8 -> 0 | AW8: =AU8*G8 -> 0 | AX8: =I8*G8 -> 0 | BA8: =AX8*SUM(AY8:AZ8)%+AX8 -> 0
AT9: =SUM(O9:AS9) -> 0 | AU9: =N9-AT9 -> 0 | AV9: =AT9*G9 -> 0 | AW9: =AU9*G9 -> 0 | AX9: =I9*G9 -> 0 | BA9: =AX9*SUM(AY9:AZ9)%+AX9 -> 0
D10: Total | H10: =SUM(H6:H9) -> 164 | I10: =SUM(I6:I9) -> 0 | N10: =SUM(N6:N9) -> 164 | O10: =SUM(O6:O9) -> 0 | P10: =SUM(P6:P9) -> 0 | Q10: =SUM(Q6:Q9) -> 0 | R10: =SUM(R6:R9) -> 0 | S10: =SUM(S6:S9) -> 0 | T10: =SUM(T6:T9) -> 0 | U10: =SUM(U6:U9) -> 0 | ... AR10: =SUM(AR6:AR9) -> 0 | AT10: =SUM(AT6:AT9) -> 8 | AU10: =SUM(AU6:AU9) -> 156 | AV10: =SUM(AV6:AV9) -> 1280 | AW10: =SUM(AW6:AW9) -> 24960 | AX10: =SUM(AX6:AX9) -> 0 | AY10: =SUM(AY6:AY9) -> 0 | AZ10: =SUM(AZ6:AZ9) -> 0 | BA10: =SUM(BA6:BA9) -> 0

Sheet Sumant Tea&Coffee
B2: =Summary!R5&" Sumant Material Consumption for the Month of "& TEXT(Summary!R4," MMM YY") -> SOC Sumant Material Consumption for the Month of Feb 26
N4: Auto | O4: =TEXT(O5,"ddd") -> Sun | P4: =TEXT(P5,"ddd") -> Mon | Q4: =TEXT(Q5,"ddd") -> Tue | R4: =TEXT(R5,"ddd") -> Wed | S4: =TEXT(S5,"ddd") -> Thu | T4: =TEXT(T5,"ddd") -> Fri | U4: =TEXT(U5,"ddd") -> Sat | V4: =TEXT(V5,"ddd") -> Sun | ... AS4: =TEXT(AS5,"ddd") -> Tue | AT4: Auto | AU4: Auto | AV4: Auto | AW4: Auto | AX4: Auto | BA4: Auto
B5: Sr. No. | C5: Vendor | D5: Particulars | E5: Brand | F5: Units | G5: Rate | H5: Opening | I5: Order | J5: Mantri Order Taken | K5: WTC Order Taken | L5: Other Sources | M5: Remark | N5: Total Stock | O5: =Summary!R4 -> 46054 | P5: =O5+1 -> 46055 | Q5: =P5+1 -> 46056 | R5: =Q5+1 -> 46057 | S5: =R5+1 -> 46058 | T5: =S5+1 -> 46059 | U5: =T5+1 -> 46060 | V5: =U5+1 -> 46061 | W5: =V5+1 -> 46062 | ... AS5: =AR5+1 -> 46084 | AT5: Usage Stock | AU5: Closing Stock | AV5: Usage Amount | AW5: Closing Amount | AX5: Order Amount | AY5: CGST | AZ5: SGST | BA5: Order Amount With GST
B6: 1 | D6: Coffee beans | F6: Kg | G6: 1350 | H6: 3 | I6: 6 | N6: =SUM(H6:L6) -> 9 | R6: 1 | X6: 1 | AT6: =SUM(O6:AS6) -> 2 | AU6: =N6-AT6 -> 7 | AV6: =AT6*G6 -> 2700 | AW6: =AU6*G6 -> 9450 | AX6: =I6*G6 -> 8100 | BA6: =AX6*SUM(AY6:AZ6)%+AX6 -> 8100
B7: 2 | D7: Milk | F7: 1ltr | G7: 69.52 | H7: 78 | I7: 48 | N7: =SUM(H7:L7) -> 126 | P7: 1 | Q7: 1 | R7: 13 | S7: 1 | T7: 1 | W7: 1 | X7: 1 | Y7: 1 | Z7: 1 | AA7: 1 | AD7: 1 | AT7: =SUM(O7:AS7) -> 23 | AU7: =N7-AT7 -> 103 | AV7: =AT7*G7 -> 1598.96 | AW7: =AU7*G7 -> 7160.56 | AX7: =I7*G7 -> 3336.96 | BA7: =AX7*SUM(AY7:AZ7)%+AX7 -> 3336.96
B8: 3 | D8: Sugar Sachet White | F8: Kg | G8: 110 | H8: 10 | I8: 8 | N8: =SUM(H8:L8) -> 18 | T8: 1 | AD8: 1 | AT8: =SUM(O8:AS8) -> 2 | AU8: =N8-AT8 -> 16 | AV8: =AT8*G8 -> 220 | AW8: =AU8*G8 -> 1760 | AX8: =I8*G8 -> 880 | BA8: =AX8*SUM(AY8:AZ8)%+AX8 -> 880
B9: 4 | D9: Stirrer | F9: Nos | G9: 0.25 | H9: 1000 | I9: 2000 | N9: =SUM(H9:L9) -> 3000 | AT9: =SUM(O9:AS9) -> 0 | AU9: =N9-AT9 -> 3000 | AV9: =AT9*G9 -> 0 | AW9: =AU9*G9 -> 750 | AX9: =I9*G9 -> 500 | BA9: =AX9*SUM(AY9:AZ9)%+AX9 -> 500
B10: 7 | N10: =SUM(H10:L10) -> 0 | AT10: =SUM(O10:AS10) -> 0 | AU10: =N10-AT10 -> 0 | AV10: =AT10*G10 -> 0 | AW10: =AU10*G10 -> 0 | AX10: =I10*G10 -> 0 | BA10: =AX10*SUM(AY10:AZ10)%+AX10 -> 0
B11: 8 | N11: =SUM(H11:L11) -> 0 | AT11: =SUM(O11:AS11) -> 0 | AU11: =N11-AT11 -> 0 | AV11: =AT11*G11 -> 0 | AW11: =AU11*G11 -> 0 | AX11: =I11*G11 -> 0 | BA11: =AX11*SUM(AY11:AZ11)%+AX11 -> 0
D12: Total | H12: =SUM(H6:H11) -> 1091 | I12: =SUM(I6:I11) -> 2062 | N12: =SUM(N6:N11) -> 3153 | O12: =SUM(O6:O11) -> 0 | P12: =SUM(P6:P11) -> 1 | Q12: =SUM(Q6:Q11) -> 1 | R12: =SUM(R6:R11) -> 14 | S12: =SUM(S6:S11) -> 1 | T12: =SUM(T6:T11) -> 2 | U12: =SUM(U6:U11) -> 0 | ... AR12: =SUM(AR6:AR11) -> 0 | AT12: =SUM(AT6:AT11) -> 27 | AU12: =SUM(AU6:AU11) -> 3126 | AV12: =SUM(AV6:AV11) -> 4518.96 | AW12: =SUM(AW6:AW11) -> 19120.56 | AX12: =SUM(AX6:AX11) -> 12816.96 | AY12: =SUM(AY6:AY11) -> 0 | AZ12: =SUM(AZ6:AZ11) -> 0 | BA12: =SUM(BA6:BA11) -> 12816.96

Sheet Toner Consu
B2: =Summary!R5&" Toner Material Consumption for the month of "& TEXT(Summary!R4," MMM YY") -> SOC Toner Material Consumption for the month of Feb 26
N4: Auto | O4: =TEXT(O5,"ddd") -> Sun | P4: =TEXT(P5,"ddd") -> Mon | Q4: =TEXT(Q5,"ddd") -> Tue | R4: =TEXT(R5,"ddd") -> Wed | S4: =TEXT(S5,"ddd") -> Thu | T4: =TEXT(T5,"ddd") -> Fri | U4: =TEXT(U5,"ddd") -> Sat | V4: =TEXT(V5,"ddd") -> Sun | ... AS4: =TEXT(AS5,"ddd") -> Tue | AT4: Auto | AU4: Auto | AV4: Auto | AW4: Auto | AX4: Auto | BA4: Auto
B5: Sr. No. | C5: Vendor | D5: Particulars | E5: Company | F5: Units | G5: Rate | H5: Opening | I5: Order | J5: Mantri Order Taken | K5: WTC Order Taken | L5: Other Sources | M5: Remark | N5: Total Stock | O5: =Summary!R4 -> 46054 | P5: =O5+1 -> 46055 | Q5: =P5+1 -> 46056 | R5: =Q5+1 -> 46057 | S5: =R5+1 -> 46058 | T5: =S5+1 -> 46059 | U5: =T5+1 -> 46060 | V5: =U5+1 -> 46061 | W5: =V5+1 -> 46062 | ... AS5: =AR5+1 -> 46084 | AT5: Usage Stock | AU5: Closing Stock | AV5: Usage Amount | AW5: Closing Amount | AX5: Order Amount | AY5: CGST | AZ5: SGST | BA5: Order Amount With GST
B6: 1 | D6: Compiteble Toner Cartridje 388A | E6: KOS/I Tech/KRL | F6: Nos | G6: 400 | H6: 2 | N6: =SUM(H6:L6) -> 2 | W6: 1 | Z6: 1 | AT6: =SUM(O6:AS6) -> 2 | AU6: =N6-AT6 -> 0 | AV6: =AT6*G6 -> 800 | AW6: =AU6*G6 -> 0 | AX6: =I6*G6 -> 0 | BA6: =AX6*SUM(AY6:AZ6)%+AX6 -> 0
B7: 2 | D7: Compiteble Toner Cartridje 137a HP | E7: ANF/KFT/KCOB | F7: Nos | G7: 1200 | H7: 1 | I7: 2 | N7: =SUM(H7:L7) -> 3 | S7: 1 | AD7: 1 | AT7: =SUM(O7:AS7) -> 2 | AU7: =N7-AT7 -> 1 | AV7: =AT7*G7 -> 2400 | AW7: =AU7*G7 -> 1200 | AX7: =I7*G7 -> 2400 | BA7: =AX7*SUM(AY7:AZ7)%+AX7 -> 2400
B8: 3 | D8: Compiteble Toner Cartridje 110A | E8: Qualead | F8: Nos | G8: 1200 | H8: 4 | N8: =SUM(H8:L8) -> 4 | AT8: =SUM(O8:AS8) -> 0 | AU8: =N8-AT8 -> 4 | AV8: =AT8*G8 -> 0 | AW8: =AU8*G8 -> 4800 | AX8: =I8*G8 -> 0 | BA8: =AX8*SUM(AY8:AZ8)%+AX8 -> 0
B9: 4 | D9: Laser Toner Black | E9: K Aviation | F9: Nos | G9: 1200 | H9: 1 | N9: =SUM(H9:L9) -> 1 | R9: 1 | AT9: =SUM(O9:AS9) -> 1 | AU9: =N9-AT9 -> 0 | AV9: =AT9*G9 -> 1200 | AW9: =AU9*G9 -> 0 | AX9: =I9*G9 -> 0 | BA9: =AX9*SUM(AY9:AZ9)%+AX9 -> 0
B10: 5 | D10: Laser Toner Yellow | E10: K Aviation | F10: Nos | G10: 1200 | H10: 0 | N10: =SUM(H10:L10) -> 0 | AT10: =SUM(O10:AS10) -> 0 | AU10: =N10-AT10 -> 0 | AV10: =AT10*G10 -> 0 | AW10: =AU10*G10 -> 0 | AX10: =I10*G10 -> 0 | BA10: =AX10*SUM(AY10:AZ10)%+AX10 -> 0
B11: 6 | D11: Laser Toner Magenta | E11: K Aviation | F11: Nos | G11: 1200 | H11: 0 | N11: =SUM(H11:L11) -> 0 | AT11: =SUM(O11:AS11) -> 0 | AU11: =N11-AT11 -> 0 | AV11: =AT11*G11 -> 0 | AW11: =AU11*G11 -> 0 | AX11: =I11*G11 -> 0 | BA11: =AX11*SUM(AY11:AZ11)%+AX11 -> 0
B12: 7 | D12: Laser Toner Blue (Cyan) | E12: K Aviation | F12: Nos | G12: 1200 | H12: 0 | N12: =SUM(H12:L12) -> 0 | AT12: =SUM(O12:AS12) -> 0 | AU12: =N12-AT12 -> 0 | AV12: =AT12*G12 -> 0 | AW12: =AU12*G12 -> 0 | AX12: =I12*G12 -> 0 | BA12: =AX12*SUM(AY12:AZ12)%+AX12 -> 0
B13: 8 | D13: Epson 008 Black Ink | E13: Qualead | F13: Nos | G13: 920 | H13: 0 | N13: =SUM(H13:L13) -> 0 | AT13: =SUM(O13:AS13) -> 0 | AU13: =N13-AT13 -> 0 | AV13: =AT13*G13 -> 0 | AW13: =AU13*G13 -> 0 | AX13: =I13*G13 -> 0 | AY13: 9 | AZ13: 9 | BA13: =AX13*SUM(AY13:AZ13)%+AX13 -> 0
B14: 9 | D14: Epson 008 Colour Ink C,M,Y | E14: Qualead | F14: Nos | G14: 820 | H14: 0 | N14: =SUM(H14:L14) -> 0 | AT14: =SUM(O14:AS14) -> 0 | AU14: =N14-AT14 -> 0 | AV14: =AT14*G14 -> 0 | AW14: =AU14*G14 -> 0 | AX14: =I14*G14 -> 0 | AY14: 9 | AZ14: 9 | BA14: =AX14*SUM(AY14:AZ14)%+AX14 -> 0
D15: Total | H15: =SUM(H6:H14) -> 8 | I15: =SUM(I6:I14) -> 2 | N15: =SUM(N6:N14) -> 10 | O15: =SUM(O6:O14) -> 0 | P15: =SUM(P6:P14) -> 0 | Q15: =SUM(Q6:Q14) -> 0 | R15: =SUM(R6:R14) -> 1 | S15: =SUM(S6:S14) -> 1 | T15: =SUM(T6:T14) -> 0 | U15: =SUM(U6:U14) -> 0 | ... BA15: =SUM(BA6:BA14) -> 2400

Sheet Water
A2: =Summary!R5&" Water Report " & TEXT(Summary!R4,"MMMM-YYY") -> SOC Water Report February-2026
A3: Rate | B3: 35 | F3: Auto | G3: Auto | H3: Auto | J3: Auto
A4: Day | B4: Date | C4: Opening Balance | D4: Delivery Jar | E4: Collected Empty Jar | F4: Total Stock | G4: Total Usage | H4: Total Amount | I4: Emp Count | J4: Per head Cost
A5: =TEXT(B5,"DDD") -> Sun | B5: =Summary!R4 -> 46054 | C5: 10 | D5: 0 | E5: 0 | F5: =D5+C5 -> 10 | G5: =F5-C6 -> 0 | H5: =G5*$B$3 -> 0 | I5: 300 | J5: =I5/H5 -> #DIV/0!
A6: =TEXT(B6,"DDD") -> Mon | B6: =B5+1 -> 46055 | C6: 10 | D6: 30 | E6: 0 | F6: =D6+C6 -> 40 | G6: =F6-C7 -> 24 | H6: =G6*$B$3 -> 840 | I6: 300 | J6: =I6/H6 -> 0.35714286
A7: =TEXT(B7,"DDD") -> Tue | B7: =B6+1 -> 46056 | C7: 16 | D7: 18 | E7: 43 | F7: =D7+C7 -> 34 | G7: =F7-C8 -> 17 | H7: =G7*$B$3 -> 595 | I7: 300 | J7: =I7/H7 -> 0.50420168
A8: =TEXT(B8,"DDD") -> Wed | B8: =B7+1 -> 46057 | C8: 17 | D8: 19 | E8: 22 | F8: =D8+C8 -> 36 | G8: =F8-C9 -> 22 | H8: =G8*$B$3 -> 770 | I8: 300 | J8: =I8/H8 -> 0.38961039
A9: =TEXT(B9,"DDD") -> Thu | B9: =B8+1 -> 46058 | C9: 14 | D9: 18 | E9: 18 | F9: =D9+C9 -> 32 | G9: =F9-C10 -> 24 | H9: =G9*$B$3 -> 840 | I9: 300 | J9: =I9/H9 -> 0.35714286
A10: =TEXT(B10,"DDD") -> Fri | B10: =B9+1 -> 46059 | C10: 8 | D10: 30 | E10: 26 | F10: =D10+C10 -> 38 | G10: =F10-C11 -> 18 | H10: =G10*$B$3 -> 630 | I10: 5 | J10: =I10/H10 -> 0.0079365079
A11: =TEXT(B11,"DDD") -> Sat | B11: =B10+1 -> 46060 | C11: 20 | D11: 0 | E11: 0 | F11: =D11+C11 -> 20 | G11: =F11-C12 -> 2 | H11: =G11*$B$3 -> 70 | I11: 5 | J11: =I11/H11 -> 0.071428571
A12: =TEXT(B12,"DDD") -> Sun | B12: =B11+1 -> 46061 | C12: 18 | D12: 10 | E12: 0 | F12: =D12+C12 -> 28 | G12: =F12-C13 -> 3 | H12: =G12*$B$3 -> 105 | I12: 300 | J12: =I12/H12 -> 2.8571429
A13: =TEXT(B13,"DDD") -> Mon | B13: =B12+1 -> 46062 | C13: 25 | D13: 8 | E13: 15 | F13: =D13+C13 -> 33 | G13: =F13-C14 -> 24 | H13: =G13*$B$3 -> 840 | I13: 300 | J13: =I13/H13 -> 0.35714286
A14: =TEXT(B14,"DDD") -> Tue | B14: =B13+1 -> 46063 | C14: 9 | D14: 30 | E14: 35 | F14: =D14+C14 -> 39 | G14: =F14-C15 -> 19 | H14: =G14*$B$3 -> 665 | I14: 300 | J14: =I14/H14 -> 0.45112782
A15: =TEXT(B15,"DDD") -> Wed | B15: =B14+1 -> 46064 | C15: 20 | D15: 15 | E15: 0 | F15: =D15+C15 -> 35 | G15: =F15-C16 -> 22 | H15: =G15*$B$3 -> 770 | I15: 300 | J15: =I15/H15 -> 0.38961039
A16: =TEXT(B16,"DDD") -> Thu | B16: =B15+1 -> 46065 | C16: 13 | D16: 16 | E16: 36 | F16: =D16+C16 -> 29 | G16: =F16-C17 -> 19 | H16: =G16*$B$3 -> 665 | I16: 300 | J16: =I16/H16 -> 0.45112782
A17: =TEXT(B17,"DDD") -> Fri | B17: =B16+1 -> 46066 | C17: 10 | D17: 15 | E17: 23 | F17: =D17+C17 -> 25 | G17: =F17-C18 -> 22 | H17: =G17*$B$3 -> 770 | I17: 5 | J17: =I17/H17 -> 0.0064935065
... A21: =TEXT(B21,"DDD") -> Tue | B21: =B20+1 -> 46070 | C21: 27 | D21: 0 | E21: 23 | F21: =D21+C21 -> 27 | G21: =F21-C22 -> 24 | H21: =G21*$B$3 -> 840 | I21: 300 | J21: =I21/H21 -> 0.35714286
A22: =TEXT(B22,"DDD") -> Wed | B22: =B21+1 -> 46071 | C22: 3 | F22: =D22+C22 -> 3 | G22: =F22-C23 -> 3 | H22: =G22*$B$3 -> 105 | I22: 300 | J22: =I22/H22 -> 2.8571429
A23: =TEXT(B23,"DDD") -> Thu | B23: =B22+1 -> 46072 | F23: =D23+C23 -> 0 | G23: =F23-C24 -> 0 | H23: =G23*$B$3 -> 0 | I23: 300 | J23: =I23/H23 -> #DIV/0!
A24: =TEXT(B24,"DDD") -> Fri | B24: =B23+1 -> 46073 | F24: =D24+C24 -> 0 | G24: =F24-C25 -> 0 | H24: =G24*$B$3 -> 0 | I24: 5 | J24: =I24/H24 -> #DIV/0!
A25: =TEXT(B25,"DDD") -> Sat | B25: =B24+1 -> 46074 | F25: =D25+C25 -> 0 | G25: =F25-C26 -> 0 | H25: =G25*$B$3 -> 0 | I25: 5 | J25: =I25/H25 -> #DIV/0!
A26: =TEXT(B26,"DDD") -> Sun | B26: =B25+1 -> 46075 | F26: =D26+C26 -> 0 | G26: =F26-C27 -> 0 | H26: =G26*$B$3 -> 0 | I26: 300 | J26: =I26/H26 -> #DIV/0!
A27: =TEXT(B27,"DDD") -> Mon | B27: =B26+1 -> 46076 | F27: =D27+C27 -> 0 | G27: =F27-C28 -> 0 | H27: =G27*$B$3 -> 0 | I27: 300 | J27: =I27/H27 -> #DIV/0!
A28: =TEXT(B28,"DDD") -> Tue | B28: =B27+1 -> 46077 | F28: =D28+C28 -> 0 | G28: =F28-C29 -> 0 | H28: =G28*$B$3 -> 0 | I28: 300 | J28: =I28/H28 -> #DIV/0!
A29: =TEXT(B29,"DDD") -> Wed | B29: =B28+1 -> 46078 | F29: =D29+C29 -> 0 | G29: =F29-C30 -> 0 | H29: =G29*$B$3 -> 0 | I29: 300 | J29: =I29/H29 -> #DIV/0!
A30: =TEXT(B30,"DDD") -> Thu | B30: =B29+1 -> 46079 | F30: =D30+C30 -> 0 | G30: =F30-C31 -> 0 | H30: =G30*$B$3 -> 0 | I30: 300 | J30: =I30/H30 -> #DIV/0!
A31: =TEXT(B31,"DDD") -> Fri | B31: =B30+1 -> 46080 | F31: =D31+C31 -> 0 | G31: =F31-C32 -> 0 | H31: =G31*$B$3 -> 0 | I31: 5 | J31: =I31/H31 -> #DIV/0!
A32: =TEXT(B32,"DDD") -> Sat | B32: =B31+1 -> 46081 | F32: =D32+C32 -> 0 | G32: =F32-C33 -> 0 | H32: =G32*$B$3 -> 0 | I32: 5 | J32: =I32/H32 -> #DIV/0!
A33: =TEXT(B33,"DDD") -> Sun | B33: =B32+1 -> 46082 | F33: =D33+C33 -> 0 | G33: =F33-C34 -> 0 | H33: =G33*$B$3 -> 0 | I33: 300 | J33: =I33/H33 -> #DIV/0!
A34: =TEXT(B34,"DDD") -> Mon | B34: =B33+1 -> 46083 | F34: =D34+C34 -> 0 | G34: =F34-C35 -> 0 | H34: =G34*$B$3 -> 0 | I34: 300 | J34: =I34/H34 -> #DIV/0!
A35: =TEXT(B35,"DDD") -> Tue | B35: =B34+1 -> 46084 | F35: =D35+C35 -> 0 | G35: 0 | H35: =G35*$B$3 -> 0 | I35: 300 | J35: =I35/H35 -> #DIV/0!
C36: =SUM(C5:C35) -> 224 | D36: =SUM(D5:D35) -> 259 | E36: =SUM(E5:E35) -> 265 | F36: =SUM(F5:F35) -> 483 | G36: =SUM(G5:G35) -> 269 | H36: =G36*35 -> 9415
C39: Particulars | D39: Qty | E39: Amount | G39: Water Report
C40: Delivery Jar | D40: =D36 -> 259 | E40: =D40*35 -> 9065 | G40: Opening | H40: Delivery Jar | I40: USE | J40: Closing
C41: CGST | D41: 0.06 | E41: =E40*D41 -> 543.9 | G41: =C5 -> 10 | H41: =D36 -> 259 | I41: =G36 -> 269 | J41: =G41+H41-I41 -> 0
C42: SGST | D42: 0.06 | E42: =E40*D42 -> 543.9
C43: Total | E43: =E42+E41+E40 -> 10152.8

Sheet Gallant SG
A1: GALLANT PVT LTD | F1: Security Manpower Attendance for the Month of | AA1: =Summary!R4 -> 46054
A2: DAY | B2: 24 | F2: =TEXT(F3,"ddd") -> Sun | G2: =TEXT(G3,"ddd") -> Mon | H2: =TEXT(H3,"ddd") -> Tue | I2: =TEXT(I3,"ddd") -> Wed | J2: =TEXT(J3,"ddd") -> Thu | K2: =TEXT(K3,"ddd") -> Fri | L2: =TEXT(L3,"ddd") -> Sat | M2: =TEXT(M3,"ddd") -> Sun | ... AJ2: =TEXT(AJ3,"ddd") -> Tue
A3: Sr No. | B3: ID NO | C3: Employee Name | D3: Designation | E3: Per day Amt | F3: =Summary!R4 -> 46054 | G3: =F3+1 -> 46055 | H3: =G3+1 -> 46056 | I3: =H3+1 -> 46057 | J3: =I3+1 -> 46058 | K3: =J3+1 -> 46059 | L3: =K3+1 -> 46060 | M3: =L3+1 -> 46061 | N3: =M3+1 -> 46062 | ... AJ3: =AI3+1 -> 46084 | AK3: Present | AL3: Absent | AM3: WO | AN3: HD | AO3: Total Day [P+HD] | AP3: OT Hours | AQ3: OT Days | AR3: Total Working Days | AS3: TotalAmount | AT3: Remark
A4: =Summary!R5 -> SOC
A5: 1 | C5: Shivprasad Harijan | D5: S/G | E5: =18939.2/$B$2 -> 789.13333 | F5: WO | G5: P | H5: P | I5: P | J5: P | K5: P | L5: WO | M5: P | N5: P | O5: P | P5: P | Q5: P | R5: P | S5: P | T5: WO | U5: P | V5: P | W5: P | AK5: =COUNTIF(F5:AJ5,"P*") -> 15 | AL5: =COUNTIF(F5:AJ5,"A") -> 0 | AM5: =COUNTIF(F5:AJ5,"WO") -> 3 | AN5: =COUNTIF(F5:AJ5,"HD") -> 0 | AO5: =AK5+AN5 -> 15 | AP5: =(COUNTIF(F5:AJ5,"P12")*12) -> 0 | AQ5: =AP5/12 -> 0 | AR5: =AO5+AQ5 -> 15 | AS5: =AR5*E5 -> 11837
A6: 2 | C6: Mithilesh Singh | D6: S/G | E6: =18939.2/$B$2 -> 789.13333 | F6: WO | G6: P | H6: P | I6: P | J6: P | K6: P | L6: WO | M6: P | N6: P | O6: P | P6: P | Q6: P | R6: P | S6: WO | T6: P | U6: P | V6: P | W6: P | AK6: =COUNTIF(F6:AJ6,"P*") -> 15 | AL6: =COUNTIF(F6:AJ6,"A") -> 0 | AM6: =COUNTIF(F6:AJ6,"WO") -> 3 | AN6: =COUNTIF(F6:AJ6,"HD") -> 0 | AO6: =AK6+AN6 -> 15 | AP6: =(COUNTIF(F6:AJ6,"P12")*12) -> 0 | AQ6: =AP6/12 -> 0 | AR6: =AO6+AQ6 -> 15 | AS6: =AR6*E6 -> 11837
A7: 3 | C7: Gangadhar Gonekar | D7: S/G | E7: =18939.2/$B$2 -> 789.13333 | F7: WO | G7: P | H7: P | I7: P | J7: P | K7: P | L7: WO | M7: P | N7: P | O7: P | P7: P | Q7: P | R7: P | S7: WO | T7: P | U7: P | V7: P | AK7: =COUNTIF(F7:AJ7,"P*") -> 14 | AL7: =COUNTIF(F7:AJ7,"A") -> 0 | AM7: =COUNTIF(F7:AJ7,"WO") -> 3 | AN7: =COUNTIF(F7:AJ7,"HD") -> 0 | AO7: =AK7+AN7 -> 14 | AP7: =(COUNTIF(F7:AJ7,"P12")*12) -> 0 | AQ7: =AP7/12 -> 0 | AR7: =AO7+AQ7 -> 14 | AS7: =AR7*E7 -> 11047.867
A8: 4 | C8: Omkar Chavan | D8: S/G | E8: =18939.2/$B$2 -> 789.13333 | F8: A | AK8: =COUNTIF(F8:AJ8,"P*") -> 0 | AL8: =COUNTIF(F8:AJ8,"A") -> 1 | AM8: =COUNTIF(F8:AJ8,"WO") -> 0 | AN8: =COUNTIF(F8:AJ8,"HD") -> 0 | AO8: =AK8+AN8 -> 0 | AP8: =(COUNTIF(F8:AJ8,"P12")*12) -> 0 | AQ8: =AP8/12 -> 0 | AR8: =AO8+AQ8 -> 0 | AS8: =AR8*E8 -> 0
A9: 5 | D9: S/G | E9: =18939.2/$B$2 -> 789.13333 | AK9: =COUNTIF(F9:AJ9,"P*") -> 0 | AL9: =COUNTIF(F9:AJ9,"A") -> 0 | AM9: =COUNTIF(F9:AJ9,"WO") -> 0 | AN9: =COUNTIF(F9:AJ9,"HD") -> 0 | AO9: =AK9+AN9 -> 0 | AP9: =(COUNTIF(F9:AJ9,"P12")*12) -> 0 | AQ9: =AP9/12 -> 0 | AR9: =AO9+AQ9 -> 0 | AS9: =AR9*E9 -> 0
A10: 6 | D10: S/G | E10: =18939.2/$B$2 -> 789.13333 | AK10: =COUNTIF(F10:AJ10,"P*") -> 0 | AL10: =COUNTIF(F10:AJ10,"A") -> 0 | AM10: =COUNTIF(F10:AJ10,"WO") -> 0 | AN10: =COUNTIF(F10:AJ10,"HD") -> 0 | AO10: =AK10+AN10 -> 0 | AP10: =(COUNTIF(F10:AJ10,"P12")*12) -> 0 | AQ10: =AP10/12 -> 0 | AR10: =AO10+AQ10 -> 0 | AS10: =AR10*E10 -> 0
A11: 7 | D11: S/G | E11: =18939.2/$B$2 -> 789.13333 | AK11: =COUNTIF(F11:AJ11,"P*") -> 0 | AL11: =COUNTIF(F11:AJ11,"A") -> 0 | AM11: =COUNTIF(F11:AJ11,"WO") -> 0 | AN11: =COUNTIF(F11:AJ11,"HD") -> 0 | AO11: =AK11+AN11 -> 0 | AP11: =(COUNTIF(F11:AJ11,"P12")*12) -> 0 | AQ11: =AP11/12 -> 0 | AR11: =AO11+AQ11 -> 0 | AS11: =AR11*E11 -> 0
D12: Total - | F12: =COUNTIF(F5:F11,"P") -> 0 | G12: =COUNTIF(G5:G11,"P") -> 3 | H12: =COUNTIF(H5:H11,"P") -> 3 | I12: =COUNTIF(I5:I11,"P") -> 3 | J12: =COUNTIF(J5:J11,"P") -> 3 | K12: =COUNTIF(K5:K11,"P") -> 3 | L12: =COUNTIF(L5:L11,"P") -> 0 | M12: =COUNTIF(M5:M11,"P") -> 3 | ... AJ12: =COUNTIF(AJ5:AJ11,"P") -> 0 | AK12: =SUM(AK5:AK10) -> 44 | AL12: =SUM(AL5:AL10) -> 1 | AM12: =SUM(AM5:AM10) -> 9 | AN12: =SUM(AN5:AN10) -> 0 | AO12: =SUM(AO5:AO10) -> 44 | AP12: =SUM(AP5:AP10) -> 0 | AQ12: =SUM(AQ5:AQ10) -> 0 | AR12: =SUM(AR5:AR11) -> 44 | AS12: =SUM(AS5:AS10) -> 34721.867
C15: Designation | D15: Present Days | E15: Head Count | F15: Per Day | I15: Amounrt
C16: Security Guard | D16: =AR12 -> 44 | E16: 3 | F16: =E5 -> 789.13333 | I16: =F16*D16 -> 34721.867
C17: Total | D17: =SUM(D16) -> 44 | I17: =I16 -> 34721.867
D19: Service Charge | I19: =I17*10% -> 3472.1867
D20: Total + Service Charge | I20: =I19+I17 -> 38194.053
D21: GST | I21: =I20*18% -> 6874.9296
D22: Total + Service Charge + GST | I22: =I21+I20 -> 45068.983

Sheet OOPL SG 
A1: OOPL | E1: Security Manpower Attendance for the Month of | Z1: =Summary!R4 -> 46054
A2: Day | B2: 24 | E2: =TEXT(E3,"ddd") -> Sun | F2: =TEXT(F3,"ddd") -> Mon | G2: =TEXT(G3,"ddd") -> Tue | H2: =TEXT(H3,"ddd") -> Wed | I2: =TEXT(I3,"ddd") -> Thu | J2: =TEXT(J3,"ddd") -> Fri | K2: =TEXT(K3,"ddd") -> Sat | L2: =TEXT(L3,"ddd") -> Sun | ... AI2: =TEXT(AI3,"ddd") -> Tue
A3: Sr No. | B3: Employee Name | C3: Designation | D3: Per day amt | E3: =Z1 -> 46054 | F3: =E3+1 -> 46055 | G3: =F3+1 -> 46056 | H3: =G3+1 -> 46057 | I3: =H3+1 -> 46058 | J3: =I3+1 -> 46059 | K3: =J3+1 -> 46060 | L3: =K3+1 -> 46061 | M3: =L3+1 -> 46062 | ... AI3: =AH3+1 -> 46084 | AJ3: Present | AK3: Absent | AL3: WO | AM3: HD | AN3: Total Day [P+HD] | AO3: OT Hours | AP3: OT Days | AQ3: Total Working Days | AR3: TotalAmount | AS3: Remark
A4: =Summary!R5 -> SOC
A5: 1 | B5: Manisha Gaikwad | C5: L S/G | D5: =19220/$B$2 -> 800.83333 | E5: WO | F5: P | G5: P | H5: P | I5: P | J5: P | K5: P | L5: WO | M5: P | N5: P | O5: P | P5: P | Q5: P | R5: WO | S5: P | T5: P | U5: P | V5: P | AJ5: =COUNTIF(E5:AI5,"P*") -> 15 | AK5: =COUNTIF(E5:AI5,"A") -> 0 | AL5: =COUNTIF(E5:AI5,"WO") -> 3 | AM5: =COUNTIF(E5:AI5,"HD") -> 0 | AN5: =AJ5+AM5 -> 15 | AO5: =(COUNTIF(E5:AI5,"P12")*12) -> 0 | AP5: =AO5/12 -> 0 | AQ5: =AN5+AP5 -> 15 | AR5: =AQ5*D5 -> 12012.5
A6: 2 | B6: Diksha Ingole | C6: L S/G | D6: =19220/$B$2 -> 800.83333 | E6: WO | F6: P | G6: P | H6: P | I6: P | J6: P | K6: WO | L6: P | M6: P | N6: P | O6: P | P6: P | Q6: P | R6: WO | S6: P | T6: P | U6: P | AJ6: =COUNTIF(E6:AI6,"P*") -> 14 | AK6: =COUNTIF(E6:AI6,"A") -> 0 | AL6: =COUNTIF(E6:AI6,"WO") -> 3 | AM6: =COUNTIF(E6:AI6,"HD") -> 0 | AN6: =AJ6+AM6 -> 14 | AO6: =(COUNTIF(E6:AI6,"P12")*12) -> 0 | AP6: =AO6/12 -> 0 | AQ6: =AN6+AP6 -> 14 | AR6: =AQ6*D6 -> 11211.667
A7: 3 | B7: Pratiksha Shendge | C7: L S/G | D7: =19220/$B$2 -> 800.83333 | E7: WO | F7: P | G7: P | H7: P | I7: P | J7: P | K7: WO | L7: P | M7: P | N7: P | O7: P | P7: P | Q7: P | R7: P | S7: WO | T7: P | U7: P | V7: P | AJ7: =COUNTIF(E7:AI7,"P*") -> 15 | AK7: =COUNTIF(E7:AI7,"A") -> 0 | AL7: =COUNTIF(E7:AI7,"WO") -> 3 | AM7: =COUNTIF(E7:AI7,"HD") -> 0 | AN7: =AJ7+AM7 -> 15 | AO7: =(COUNTIF(E7:AI7,"P12")*12) -> 0 | AP7: =AO7/12 -> 0 | AQ7: =AN7+AP7 -> 15 | AR7: =AQ7*D7 -> 12012.5
A8: 4 | B8: Popi Mahanta | C8: L S/G | D8: =19220/$B$2 -> 800.83333 | E8: WO | F8: P | G8: P | H8: P | I8: P | J8: P | K8: P | L8: WO | M8: P | N8: P | O8: P | P8: P | Q8: P | R8: P | S8: WO | T8: P | U8: P | AJ8: =COUNTIF(E8:AI8,"P*") -> 14 | AK8: =COUNTIF(E8:AI8,"A") -> 0 | AL8: =COUNTIF(E8:AI8,"WO") -> 3 | AM8: =COUNTIF(E8:AI8,"HD") -> 0 | AN8: =AJ8+AM8 -> 14 | AO8: =(COUNTIF(E8:AI8,"P12")*12) -> 0 | AP8: =AO8/12 -> 0 | AQ8: =AN8+AP8 -> 14 | AR8: =AQ8*D8 -> 11211.667
A9: 5 | B9: Bhagwan Tatikundalwar | C9: S/G | D9: =19220/$B$2 -> 800.83333 | E9: WO | F9: P | G9: P | H9: P | I9: P | J9: P | K9: WO | L9: P | M9: P | N9: P | O9: P | P9: P | Q9: P | R9: WO | S9: P | T9: P | U9: P | V9: P | AJ9: =COUNTIF(E9:AI9,"P*") -> 15 | AK9: =COUNTIF(E9:AI9,"A") -> 0 | AL9: =COUNTIF(E9:AI9,"WO") -> 3 | AM9: =COUNTIF(E9:AI9,"HD") -> 0 | AN9: =AJ9+AM9 -> 15 | AO9: =(COUNTIF(E9:AI9,"P12")*12) -> 0 | AP9: =AO9/12 -> 0 | AQ9: =AN9+AP9 -> 15 | AR9: =AQ9*D9 -> 12012.5
A10: 6 | B10: Ram Machare | C10: S/G | D10: =19220/$B$2 -> 800.83333 | E10: WO | F10: P | G10: P | H10: P | I10: A | J10: A | K10: P | L10: WO | M10: P | N10: P | O10: P | P10: P | Q10: P | R10: WO | S10: P | T10: P | U10: P | AJ10: =COUNTIF(E10:AI10,"P*") -> 12 | AK10: =COUNTIF(E10:AI10,"A") -> 2 | AL10: =COUNTIF(E10:AI10,"WO") -> 3 | AM10: =COUNTIF(E10:AI10,"HD") -> 0 | AN10: =AJ10+AM10 -> 12 | AO10: =(COUNTIF(E10:AI10,"P12")*12) -> 0 | AP10: =AO10/12 -> 0 | AQ10: =AN10+AP10 -> 12 | AR10: =AQ10*D10 -> 9610
A11: 7 | B11: Balaji Sonkamble | C11: S/G | D11: =19220/$B$2 -> 800.83333 | E11: WO | F11: P | G11: P | H11: P | I11: P | J11: P | K11: WO | L11: P | M11: P | N11: P | O11: P | P11: P | Q11: P | R11: P | S11: WO | T11: P | U11: P | AJ11: =COUNTIF(E11:AI11,"P*") -> 14 | AK11: =COUNTIF(E11:AI11,"A") -> 0 | AL11: =COUNTIF(E11:AI11,"WO") -> 3 | AM11: =COUNTIF(E11:AI11,"HD") -> 0 | AN11: =AJ11+AM11 -> 14 | AO11: =(COUNTIF(E11:AI11,"P12")*12) -> 0 | AP11: =AO11/12 -> 0 | AQ11: =AN11+AP11 -> 14 | AR11: =AQ11*D11 -> 11211.667
A12: 8 | B12: Gopalkrushn Ankamwar | C12: S/G | D12: =19220/$B$2 -> 800.83333 | E12: WO | F12: P | G12: P | H12: P | I12: P | J12: P | K12: P | L12: WO | M12: A | N12: A | O12: A | P12: A | Q12: P | R12: P | S12: WO | T12: P | U12: P | V12: P | AJ12: =COUNTIF(E12:AI12,"P*") -> 11 | AK12: =COUNTIF(E12:AI12,"A") -> 4 | AL12: =COUNTIF(E12:AI12,"WO") -> 3 | AM12: =COUNTIF(E12:AI12,"HD") -> 0 | AN12: =AJ12+AM12 -> 11 | AO12: =(COUNTIF(E12:AI12,"P12")*12) -> 0 | AP12: =AO12/12 -> 0 | AQ12: =AN12+AP12 -> 11 | AR12: =AQ12*D12 -> 8809.1667
A13: 9 | C13: S/G | D13: =19220/$B$2 -> 800.83333 | AJ13: =COUNTIF(E13:AI13,"P*") -> 0 | AK13: =COUNTIF(E13:AI13,"A") -> 0 | AL13: =COUNTIF(E13:AI13,"WO") -> 0 | AM13: =COUNTIF(E13:AI13,"HD") -> 0 | AN13: =AJ13+AM13 -> 0 | AO13: =(COUNTIF(E13:AI13,"P12")*12) -> 0 | AP13: =AO13/12 -> 0 | AQ13: =AN13+AP13 -> 0 | AR13: =AQ13*D13 -> 0
C14: S/G | D14: =19220/$B$2 -> 800.83333 | AJ14: =COUNTIF(E14:AI14,"P*") -> 0 | AK14: =COUNTIF(E14:AI14,"A") -> 0 | AL14: =COUNTIF(E14:AI14,"WO") -> 0 | AM14: =COUNTIF(E14:AI14,"HD") -> 0 | AN14: =AJ14+AM14 -> 0 | AO14: =(COUNTIF(E14:AI14,"P12")*12) -> 0 | AP14: =AO14/12 -> 0 | AQ14: =AN14+AP14 -> 0 | AR14: =AQ14*D14 -> 0
C15: S/G | D15: =19220/$B$2 -> 800.83333 | AJ15: =COUNTIF(E15:AI15,"P*") -> 0 | AK15: =COUNTIF(E15:AI15,"A") -> 0 | AL15: =COUNTIF(E15:AI15,"WO") -> 0 | AM15: =COUNTIF(E15:AI15,"HD") -> 0 | AN15: =AJ15+AM15 -> 0 | AO15: =(COUNTIF(E15:AI15,"P12")*12) -> 0 | AP15: =AO15/12 -> 0 | AQ15: =AN15+AP15 -> 0 | AR15: =AQ15*D15 -> 0
E16: =COUNTIF(E5:E15,"P")+COUNTIF(E5:E15,"P12") -> 0 | F16: =COUNTIF(F5:F15,"P")+COUNTIF(F5:F15,"P12") -> 8 | G16: =COUNTIF(G5:G15,"P")+COUNTIF(G5:G15,"P12") -> 8 | H16: =COUNTIF(H5:H15,"P")+COUNTIF(H5:H15,"P12") -> 8 | I16: =COUNTIF(I5:I15,"P")+COUNTIF(I5:I15,"P12") -> 7 | J16: =COUNTIF(J5:J15,"P")+COUNTIF(J5:J15,"P12") -> 7 | K16: =COUNTIF(K5:K15,"P")+COUNTIF(K5:K15,"P12") -> 4 | L16: =COUNTIF(L5:L15,"P")+COUNTIF(L5:L15,"P12") -> 4 | ... AI16: =COUNTIF(AI5:AI15,"P")+COUNTIF(AI5:AI15,"P12") -> 0 | AJ16: =SUM(AJ5:AJ15) -> 110 | AK16: =SUM(AK5:AK15) -> 6 | AL16: =SUM(AL5:AL15) -> 24 | AM16: =SUM(AM5:AM15) -> 0 | AN16: =SUM(AN5:AN15) -> 110 | AO16: =SUM(AO5:AO15) -> 0 | AP16: =SUM(AP5:AP15) -> 0 | AQ16: =SUM(AQ5:AQ15) -> 110 | ... AS16: =SUM(AS5:AS15) -> 0
B18: Designation | C18: Present Days | D18: Head Count | E18: Per Day | H18: Amounrt
B19: Security Guard | C19: =AQ16 -> 110 | D19: 9 | E19: =D5 -> 800.83333 | H19: =E19*C19 -> 88091.667
B20: deduction (Fine) | H20: 0
B21: Total | C21: =SUM(C19) -> 110 | H21: =H19-H20 -> 88091.667
C23: Service Charge | H23: =H21*7% -> 6166.4167
C24: Total + Service Charge | H24: =H23+H21 -> 94258.083
C25: GST | H25: =H24*18% -> 16966.455
C26: Total + Service Charge + GST | H26: =H25+H24 -> 111224.54

Sheet Imperial HK
A1: =Summary!R5 -> SOC | E1: Housekeeping Manpower Attendance for the month of | AA1: =Summary!R4 -> 46054 | AJ1: IMPERIAL SERVICES
A2: DAY | B2: 24 | E2: =TEXT(E3,"ddd") -> Sun | F2: =TEXT(F3,"ddd") -> Mon | G2: =TEXT(G3,"ddd") -> Tue | H2: =TEXT(H3,"ddd") -> Wed | I2: =TEXT(I3,"ddd") -> Thu | J2: =TEXT(J3,"ddd") -> Fri | K2: =TEXT(K3,"ddd") -> Sat | L2: =TEXT(L3,"ddd") -> Sun | ... AI2: =TEXT(AI3,"ddd") -> Tue
A3: Sr No | B3: Employee Name | C3: Designation | D3: Per Day | E3: =AA1 -> 46054 | F3: =E3+1 -> 46055 | G3: =F3+1 -> 46056 | H3: =G3+1 -> 46057 | I3: =H3+1 -> 46058 | J3: =I3+1 -> 46059 | K3: =J3+1 -> 46060 | L3: =K3+1 -> 46061 | M3: =L3+1 -> 46062 | ... AI3: =AH3+1 -> 46084 | AJ3: Present | AK3: Absent | AL3: WO | AM3: HD | AN3: Total Day [P+W/O+HD] | AO3: OT Hours | AP3: OT Days | AQ3: Total Working Days | AR3: Total Amount | AS3: Remark
A4: 1 | B4: Adesh Nikam | C4: Pantry Boy | D4: =20597.37/$B$2 -> 858.22375 | E4: WO | F4: P | G4: P | H4: P | I4: P | J4: P | K4: WO | L4: P | M4: P3 | N4: P2 | O4: P2 | P4: P2 | Q4: P6 | R4: P | S4: WO | T4: P7 | U4: P4 | V4: P | AJ4: =COUNTIF(E4:AI4,"P*") -> 15 | AK4: =COUNTIF(E4:AI4,"A") -> 0 | AL4: =COUNTIF(E4:AI4,"WO") -> 3 | AM4: =COUNTIF(E4:AI4,"HD") -> 0 | AN4: =AJ4+AM4 -> 15 | AO4: =(COUNTIF(E4:AI4,"P1")*1)+(COUNTIF(E4:AI4,"P2")*2)+(COUNTIF(E4:AI4,"P3")*3)+(COUNTIF(E4:AI4,"P4")*4)+(COUNTIF(E4:AI4,"P5")*5)+(COUNTIF(E4:AI4,"P6")*6)+(COUNTIF(E4:AI4,"P7")*7)+(COUNTIF(E4:AI4,"P8")*8) -> 26 | AP4: =AO4/8 -> 3.25 | AQ4: =AN4+AP4 -> 18.25 | AR4: =AQ4*D4 -> 15662.583
A5: 2 | B5: Bapu Waghmare | C5: Pantry Boy | D5: =18597/$B$2 -> 774.875 | E5: WO | F5: P | G5: P | H5: P | I5: P | J5: P | K5: P | L5: P | M5: P2 | N5: P2 | O5: P | P5: P | Q5: A | R5: P | S5: WO | T5: A | U5: A | AJ5: =COUNTIF(E5:AI5,"P*") -> 12 | AK5: =COUNTIF(E5:AI5,"A") -> 3 | AL5: =COUNTIF(E5:AI5,"WO") -> 2 | AM5: =COUNTIF(E5:AI5,"HD") -> 0 | AN5: =AJ5+AM5 -> 12 | AO5: =(COUNTIF(E5:AI5,"P1")*1)+(COUNTIF(E5:AI5,"P2")*2)+(COUNTIF(E5:AI5,"P3")*3)+(COUNTIF(E5:AI5,"P4")*4)+(COUNTIF(E5:AI5,"P5")*5)+(COUNTIF(E5:AI5,"P6")*6)+(COUNTIF(E5:AI5,"P7")*7)+(COUNTIF(E5:AI5,"P8")*8) -> 4 | AP5: =AO5/8 -> 0.5 | AQ5: =AN5+AP5 -> 12.5 | AR5: =AQ5*D5 -> 9685.9375
A6: 3 | B6: Madhav Tekkam | C6: Hk Boy | D6: =17335.24/$B$2 -> 722.30167 | E6: P | F6: P | G6: P | H6: P6 | I6: P6 | J6: P6 | K6: P | L6: P | M6: P6 | N6: P6 | O6: P6 | P6: P6 | Q6: P6 | R6: P | S6: P | T6: P4 | U6: P | V6: P | AJ6: =COUNTIF(E6:AI6,"P*") -> 18 | AK6: =COUNTIF(E6:AI6,"A") -> 0 | AL6: =COUNTIF(E6:AI6,"WO") -> 0 | AM6: =COUNTIF(E6:AI6,"HD") -> 0 | AN6: =AJ6+AM6 -> 18 | AO6: =(COUNTIF(E6:AI6,"P1")*1)+(COUNTIF(E6:AI6,"P2")*2)+(COUNTIF(E6:AI6,"P3")*3)+(COUNTIF(E6:AI6,"P4")*4)+(COUNTIF(E6:AI6,"P5")*5)+(COUNTIF(E6:AI6,"P6")*6)+(COUNTIF(E6:AI6,"P7")*7)+(COUNTIF(E6:AI6,"P8")*8) -> 52 | AP6: =AO6/8 -> 6.5 | AQ6: =AN6+AP6 -> 24.5 | AR6: =AQ6*D6 -> 17696.391
A7: 4 | B7: Bhayyasaheb Sonkamble | C7: Hk Boy | D7: =17335.24/$B$2 -> 722.30167 | E7: WO | F7: P | G7: P | H7: A | I7: A | J7: A | K7: A | L7: A | M7: A | N7: A | O7: A | P7: A | Q7: A | R7: A | S7: A | T7: P | U7: P | AJ7: =COUNTIF(E7:AI7,"P*") -> 4 | AK7: =COUNTIF(E7:AI7,"A") -> 12 | AL7: =COUNTIF(E7:AI7,"WO") -> 1 | AM7: =COUNTIF(E7:AI7,"HD") -> 0 | AN7: =AJ7+AM7 -> 4 | AO7: =(COUNTIF(E7:AI7,"P1")*1)+(COUNTIF(E7:AI7,"P2")*2)+(COUNTIF(E7:AI7,"P3")*3)+(COUNTIF(E7:AI7,"P4")*4)+(COUNTIF(E7:AI7,"P5")*5)+(COUNTIF(E7:AI7,"P6")*6)+(COUNTIF(E7:AI7,"P7")*7)+(COUNTIF(E7:AI7,"P8")*8) -> 0 | AP7: =AO7/8 -> 0 | AQ7: =AN7+AP7 -> 4 | AR7: =AQ7*D7 -> 2889.2067
A8: 5 | B8: Laxmi Kardak | C8: CM | D8: =17335.24/$B$2 -> 722.30167 | E8: WO | F8: P | G8: P | H8: P | I8: P | J8: P | K8: P | L8: P | M8: P | N8: P | O8: P | P8: P | Q8: P | R8: A | S8: A | T8: A | U8: A | AJ8: =COUNTIF(E8:AI8,"P*") -> 12 | AK8: =COUNTIF(E8:AI8,"A") -> 4 | AL8: =COUNTIF(E8:AI8,"WO") -> 1 | AM8: =COUNTIF(E8:AI8,"HD") -> 0 | AN8: =AJ8+AM8 -> 12 | AO8: =(COUNTIF(E8:AI8,"P1")*1)+(COUNTIF(E8:AI8,"P2")*2)+(COUNTIF(E8:AI8,"P3")*3)+(COUNTIF(E8:AI8,"P4")*4)+(COUNTIF(E8:AI8,"P5")*5)+(COUNTIF(E8:AI8,"P6")*6)+(COUNTIF(E8:AI8,"P7")*7)+(COUNTIF(E8:AI8,"P8")*8) -> 0 | AP8: =AO8/8 -> 0 | AQ8: =AN8+AP8 -> 12 | AR8: =AQ8*D8 -> 8667.62
A9: 6 | B9: Saroj Shukla | C9: C/M | D9: =17335.24/$B$2 -> 722.30167 | E9: WO | F9: P | G9: P | H9: P | I9: P | J9: P | K9: P | L9: P | M9: P | N9: P | O9: P | P9: P | Q9: P | R9: P | S9: WO | T9: P | U9: P | AJ9: =COUNTIF(E9:AI9,"P*") -> 15 | AK9: =COUNTIF(E9:AI9,"A") -> 0 | AL9: =COUNTIF(E9:AI9,"WO") -> 2 | AM9: =COUNTIF(E9:AI9,"HD") -> 0 | AN9: =AJ9+AM9 -> 15 | AO9: =(COUNTIF(E9:AI9,"P1")*1)+(COUNTIF(E9:AI9,"P2")*2)+(COUNTIF(E9:AI9,"P3")*3)+(COUNTIF(E9:AI9,"P4")*4)+(COUNTIF(E9:AI9,"P5")*5)+(COUNTIF(E9:AI9,"P6")*6)+(COUNTIF(E9:AI9,"P7")*7)+(COUNTIF(E9:AI9,"P8")*8) -> 0 | AP9: =AO9/8 -> 0 | AQ9: =AN9+AP9 -> 15 | AR9: =AQ9*D9 -> 10834.525
A10: 7 | B10: Sangeeta Vishwakarma | C10: C/M | D10: =17335.24/$B$2 -> 722.30167 | E10: WO | F10: P | G10: P | H10: P | I10: P | J10: P | K10: P | L10: P | M10: P | N10: P | O10: P | P10: P | Q10: P | R10: WO | S10: P | T10: P | U10: P | V10: P | AJ10: =COUNTIF(E10:AI10,"P*") -> 16 | AK10: =COUNTIF(E10:AI10,"A") -> 0 | AL10: =COUNTIF(E10:AI10,"WO") -> 2 | AM10: =COUNTIF(E10:AI10,"HD") -> 0 | AN10: =AJ10+AM10 -> 16 | AO10: =(COUNTIF(E10:AI10,"P1")*1)+(COUNTIF(E10:AI10,"P2")*2)+(COUNTIF(E10:AI10,"P3")*3)+(COUNTIF(E10:AI10,"P4")*4)+(COUNTIF(E10:AI10,"P5")*5)+(COUNTIF(E10:AI10,"P6")*6)+(COUNTIF(E10:AI10,"P7")*7)+(COUNTIF(E10:AI10,"P8")*8) -> 0 | AP10: =AO10/8 -> 0 | AQ10: =AN10+AP10 -> 16 | AR10: =AQ10*D10 -> 11556.827
A11: 8 | B11: Kaushalya Pawar | C11: C/M | D11: =17335.24/$B$2 -> 722.30167 | E11: WO | F11: P | G11: P | H11: P | I11: P | J11: P | K11: A | L11: A | M11: P | N11: P | O11: P | P11: P | Q11: P | R11: P | S11: WO | T11: P | U11: P | AJ11: =COUNTIF(E11:AI11,"P*") -> 13 | AK11: =COUNTIF(E11:AI11,"A") -> 2 | AL11: =COUNTIF(E11:AI11,"WO") -> 2 | AM11: =COUNTIF(E11:AI11,"HD") -> 0 | AN11: =AJ11+AM11 -> 13 | AO11: =(COUNTIF(E11:AI11,"P1")*1)+(COUNTIF(E11:AI11,"P2")*2)+(COUNTIF(E11:AI11,"P3")*3)+(COUNTIF(E11:AI11,"P4")*4)+(COUNTIF(E11:AI11,"P5")*5)+(COUNTIF(E11:AI11,"P6")*6)+(COUNTIF(E11:AI11,"P7")*7)+(COUNTIF(E11:AI11,"P8")*8) -> 0 | AP11: =AO11/8 -> 0 | AQ11: =AN11+AP11 -> 13 | AR11: =AQ11*D11 -> 9389.9217
A12: 9 | B12: Gaurav Dake | C12: Hk Boy | D12: =17335.24/$B$2 -> 722.30167 | E12: WO | F12: P | G12: P | H12: P | I12: P | J12: P | K12: WO | L12: P | M12: P | N12: P | O12: A | P12: A | Q12: A | R12: A | S12: A | T12: P | U12: P | AJ12: =COUNTIF(E12:AI12,"P*") -> 10 | AK12: =COUNTIF(E12:AI12,"A") -> 5 | AL12: =COUNTIF(E12:AI12,"WO") -> 2 | AM12: =COUNTIF(E12:AI12,"HD") -> 0 | AN12: =AJ12+AM12 -> 10 | AO12: =(COUNTIF(E12:AI12,"P1")*1)+(COUNTIF(E12:AI12,"P2")*2)+(COUNTIF(E12:AI12,"P3")*3)+(COUNTIF(E12:AI12,"P4")*4)+(COUNTIF(E12:AI12,"P5")*5)+(COUNTIF(E12:AI12,"P6")*6)+(COUNTIF(E12:AI12,"P7")*7)+(COUNTIF(E12:AI12,"P8")*8) -> 0 | AP12: =AO12/8 -> 0 | AQ12: =AN12+AP12 -> 10 | AR12: =AQ12*D12 -> 7223.0167
A13: 10 | B13: Ravindra Kale | C13: Hk Boy | D13: =17335.24/$B$2 -> 722.30167 | E13: WO | F13: P | G13: P | H13: P | I13: P | J13: P | K13: WO | L13: P | M13: P | N13: P | O13: P | P13: P | Q13: P | R13: WO | S13: P | T13: P | U13: P | AJ13: =COUNTIF(E13:AI13,"P*") -> 14 | AK13: =COUNTIF(E13:AI13,"A") -> 0 | AL13: =COUNTIF(E13:AI13,"WO") -> 3 | AM13: =COUNTIF(E13:AI13,"HD") -> 0 | AN13: =AJ13+AM13 -> 14 | AO13: =(COUNTIF(E13:AI13,"P1")*1)+(COUNTIF(E13:AI13,"P2")*2)+(COUNTIF(E13:AI13,"P3")*3)+(COUNTIF(E13:AI13,"P4")*4)+(COUNTIF(E13:AI13,"P5")*5)+(COUNTIF(E13:AI13,"P6")*6)+(COUNTIF(E13:AI13,"P7")*7)+(COUNTIF(E13:AI13,"P8")*8) -> 0 | AP13: =AO13/8 -> 0 | AQ13: =AN13+AP13 -> 14 | AR13: =AQ13*D13 -> 10112.223
A14: 11 | B14: Hanumant | C14: Hk Boy | D14: =17335.24/$B$2 -> 722.30167 | E14: WO | F14: A | G14: A | H14: A | I14: P | J14: P | K14: A | L14: A | M14: A | N14: A | O14: A | P14: A | Q14: A | R14: P | S14: P | T14: A | U14: P | AJ14: =COUNTIF(E14:AI14,"P*") -> 5 | AK14: =COUNTIF(E14:AI14,"A") -> 11 | AL14: =COUNTIF(E14:AI14,"WO") -> 1 | AM14: =COUNTIF(E14:AI14,"HD") -> 0 | AN14: =AJ14+AM14 -> 5 | AO14: =(COUNTIF(E14:AI14,"P1")*1)+(COUNTIF(E14:AI14,"P2")*2)+(COUNTIF(E14:AI14,"P3")*3)+(COUNTIF(E14:AI14,"P4")*4)+(COUNTIF(E14:AI14,"P5")*5)+(COUNTIF(E14:AI14,"P6")*6)+(COUNTIF(E14:AI14,"P7")*7)+(COUNTIF(E14:AI14,"P8")*8) -> 0 | AP14: =AO14/8 -> 0 | AQ14: =AN14+AP14 -> 5 | AR14: =AQ14*D14 -> 3611.5083
A15: 12 | B15: Rushikesh Khandagale | C15: Hk Boy | D15: =17335.24/$B$2 -> 722.30167 | E15: A | F15: A | G15: A | H15: A | I15: A | J15: A | K15: P | L15: A | M15: P | N15: A | O15: A | P15: A | Q15: A | R15: A | S15: A | T15: A | U15: A | AJ15: =COUNTIF(E15:AI15,"P*") -> 2 | AK15: =COUNTIF(E15:AI15,"A") -> 15 | AL15: =COUNTIF(E15:AI15,"WO") -> 0 | AM15: =COUNTIF(E15:AI15,"HD") -> 0 | AN15: =AJ15+AM15 -> 2 | AO15: =(COUNTIF(E15:AI15,"P1")*1)+(COUNTIF(E15:AI15,"P2")*2)+(COUNTIF(E15:AI15,"P3")*3)+(COUNTIF(E15:AI15,"P4")*4)+(COUNTIF(E15:AI15,"P5")*5)+(COUNTIF(E15:AI15,"P6")*6)+(COUNTIF(E15:AI15,"P7")*7)+(COUNTIF(E15:AI15,"P8")*8) -> 0 | AP15: =AO15/8 -> 0 | AQ15: =AN15+AP15 -> 2 | AR15: =AQ15*D15 -> 1444.6033
A16: 13 | B16: Ashok Singh | C16: Hk Boy | D16: =17335.24/$B$2 -> 722.30167 | E16: A | F16: A | G16: A | H16: A | I16: A | J16: A | K16: A | L16: A | M16: A | N16: A | O16: P | P16: P | Q16: P | R16: A | S16: A | T16: A | U16: A | AJ16: =COUNTIF(E16:AI16,"P*") -> 3 | AK16: =COUNTIF(E16:AI16,"A") -> 14 | AL16: =COUNTIF(E16:AI16,"WO") -> 0 | AM16: =COUNTIF(E16:AI16,"HD") -> 0 | AN16: =AJ16+AM16 -> 3 | AO16: =(COUNTIF(E16:AI16,"P1")*1)+(COUNTIF(E16:AI16,"P2")*2)+(COUNTIF(E16:AI16,"P3")*3)+(COUNTIF(E16:AI16,"P4")*4)+(COUNTIF(E16:AI16,"P5")*5)+(COUNTIF(E16:AI16,"P6")*6)+(COUNTIF(E16:AI16,"P7")*7)+(COUNTIF(E16:AI16,"P8")*8) -> 0 | AP16: =AO16/8 -> 0 | AQ16: =AN16+AP16 -> 3 | AR16: =AQ16*D16 -> 2166.905
A17: 14 | B17: Rajendra Jadhav | C17: Hk Boy | D17: =17335.24/$B$2 -> 722.30167 | E17: A | F17: A | G17: A | H17: A | I17: A | J17: A | K17: A | L17: A | M17: A | N17: A | O17: A | P17: P | Q17: A | R17: A | S17: A | T17: A | U17: A | AJ17: =COUNTIF(E17:AI17,"P*") -> 1 | AK17: =COUNTIF(E17:AI17,"A") -> 16 | AL17: =COUNTIF(E17:AI17,"WO") -> 0 | AM17: =COUNTIF(E17:AI17,"HD") -> 0 | AN17: =AJ17+AM17 -> 1 | AO17: =(COUNTIF(E17:AI17,"P1")*1)+(COUNTIF(E17:AI17,"P2")*2)+(COUNTIF(E17:AI17,"P3")*3)+(COUNTIF(E17:AI17,"P4")*4)+(COUNTIF(E17:AI17,"P5")*5)+(COUNTIF(E17:AI17,"P6")*6)+(COUNTIF(E17:AI17,"P7")*7)+(COUNTIF(E17:AI17,"P8")*8) -> 0 | AP17: =AO17/8 -> 0 | AQ17: =AN17+AP17 -> 1 | AR17: =AQ17*D17 -> 722.30167
A18: 15 | B18: Jagdev | C18: Hk Boy | D18: =17335.24/$B$2 -> 722.30167 | E18: A | F18: A | G18: A | H18: A | I18: A | J18: A | K18: A | L18: A | M18: A | N18: A | O18: A | P18: A | Q18: P | R18: A | S18: A | T18: A | U18: A | AJ18: =COUNTIF(E18:AI18,"P*") -> 1 | AK18: =COUNTIF(E18:AI18,"A") -> 16 | AL18: =COUNTIF(E18:AI18,"WO") -> 0 | AM18: =COUNTIF(E18:AI18,"HD") -> 0 | AN18: =AJ18+AM18 -> 1 | AO18: =(COUNTIF(E18:AI18,"P1")*1)+(COUNTIF(E18:AI18,"P2")*2)+(COUNTIF(E18:AI18,"P3")*3)+(COUNTIF(E18:AI18,"P4")*4)+(COUNTIF(E18:AI18,"P5")*5)+(COUNTIF(E18:AI18,"P6")*6)+(COUNTIF(E18:AI18,"P7")*7)+(COUNTIF(E18:AI18,"P8")*8) -> 0 | AP18: =AO18/8 -> 0 | AQ18: =AN18+AP18 -> 1 | AR18: =AQ18*D18 -> 722.30167
A19: 16 | B19: Sahil Dake | C19: Hk Boy | D19: =17335.24/$B$2 -> 722.30167 | E19: A | F19: A | G19: A | H19: A | I19: A | J19: A | K19: A | L19: A | M19: A | N19: A | O19: A | P19: A | Q19: A | R19: A | S19: P | T19: A | U19: A | AJ19: =COUNTIF(E19:AI19,"P*") -> 1 | AK19: =COUNTIF(E19:AI19,"A") -> 16 | AL19: =COUNTIF(E19:AI19,"WO") -> 0 | AM19: =COUNTIF(E19:AI19,"HD") -> 0 | AN19: =AJ19+AM19 -> 1 | AO19: =(COUNTIF(E19:AI19,"P1")*1)+(COUNTIF(E19:AI19,"P2")*2)+(COUNTIF(E19:AI19,"P3")*3)+(COUNTIF(E19:AI19,"P4")*4)+(COUNTIF(E19:AI19,"P5")*5)+(COUNTIF(E19:AI19,"P6")*6)+(COUNTIF(E19:AI19,"P7")*7)+(COUNTIF(E19:AI19,"P8")*8) -> 0 | AP19: =AO19/8 -> 0 | AQ19: =AN19+AP19 -> 1 | AR19: =AQ19*D19 -> 722.30167
A20: 17 | D20: =17335.24/$B$2 -> 722.30167 | AJ20: =COUNTIF(E20:AI20,"P*") -> 0 | AK20: =COUNTIF(E20:AI20,"A") -> 0 | AL20: =COUNTIF(E20:AI20,"WO") -> 0 | AM20: =COUNTIF(E20:AI20,"HD") -> 0 | AN20: =AJ20+AM20 -> 0 | AO20: =(COUNTIF(E20:AI20,"P1")*1)+(COUNTIF(E20:AI20,"P2")*2)+(COUNTIF(E20:AI20,"P3")*3)+(COUNTIF(E20:AI20,"P4")*4)+(COUNTIF(E20:AI20,"P5")*5)+(COUNTIF(E20:AI20,"P6")*6)+(COUNTIF(E20:AI20,"P7")*7)+(COUNTIF(E20:AI20,"P8")*8) -> 0 | AP20: =AO20/8 -> 0 | AQ20: =AN20+AP20 -> 0 | AR20: =AQ20*D20 -> 0
A21: 18 | D21: =17335.24/$B$2 -> 722.30167 | AJ21: =COUNTIF(E21:AI21,"P*") -> 0 | AK21: =COUNTIF(E21:AI21,"A") -> 0 | AL21: =COUNTIF(E21:AI21,"WO") -> 0 | AM21: =COUNTIF(E21:AI21,"HD") -> 0 | AN21: =AJ21+AM21 -> 0 | AO21: =(COUNTIF(E21:AI21,"P1")*1)+(COUNTIF(E21:AI21,"P2")*2)+(COUNTIF(E21:AI21,"P3")*3)+(COUNTIF(E21:AI21,"P4")*4)+(COUNTIF(E21:AI21,"P5")*5)+(COUNTIF(E21:AI21,"P6")*6)+(COUNTIF(E21:AI21,"P7")*7)+(COUNTIF(E21:AI21,"P8")*8) -> 0 | AP21: =AO21/8 -> 0 | AQ21: =AN21+AP21 -> 0 | AR21: =AQ21*D21 -> 0
A22: 19 | D22: =17335.24/$B$2 -> 722.30167 | AJ22: =COUNTIF(E22:AI22,"P*") -> 0 | AK22: =COUNTIF(E22:AI22,"A") -> 0 | AL22: =COUNTIF(E22:AI22,"WO") -> 0 | AM22: =COUNTIF(E22:AI22,"HD") -> 0 | AN22: =AJ22+AM22 -> 0 | AO22: =(COUNTIF(E22:AI22,"P1")*1)+(COUNTIF(E22:AI22,"P2")*2)+(COUNTIF(E22:AI22,"P3")*3)+(COUNTIF(E22:AI22,"P4")*4)+(COUNTIF(E22:AI22,"P5")*5)+(COUNTIF(E22:AI22,"P6")*6)+(COUNTIF(E22:AI22,"P7")*7)+(COUNTIF(E22:AI22,"P8")*8) -> 0 | AP22: =AO22/8 -> 0 | AQ22: =AN22+AP22 -> 0 | AR22: =AQ22*D22 -> 0
E23: =COUNTIF(E4:E22,"p8")*2+COUNTIF(E4:E22,"P")+COUNTIF(E4:E22,"P4")*1.5 -> 1 | F23: =COUNTIF(F4:F22,"p8")*2+COUNTIF(F4:F22,"P")+COUNTIF(F4:F22,"P4")*1.5 -> 10 | G23: =COUNTIF(G4:G22,"p8")*2+COUNTIF(G4:G22,"P")+COUNTIF(G4:G22,"P4")*1.5 -> 10 | H23: =COUNTIF(H4:H22,"p8")*2+COUNTIF(H4:H22,"P")+COUNTIF(H4:H22,"P4")*1.5 -> 8 | I23: =COUNTIF(I4:I22,"p8")*2+COUNTIF(I4:I22,"P")+COUNTIF(I4:I22,"P4")*1.5 -> 9 | J23: =COUNTIF(J4:J22,"p8")*2+COUNTIF(J4:J22,"P")+COUNTIF(J4:J22,"P4")*1.5 -> 9 | K23: =COUNTIF(K4:K22,"p8")*2+COUNTIF(K4:K22,"P")+COUNTIF(K4:K22,"P4")*1.5 -> 6 | L23: =COUNTIF(L4:L22,"p8")*2+COUNTIF(L4:L22,"P")+COUNTIF(L4:L22,"P4")*1.5 -> 8 | ... AI23: =COUNTIF(AI4:AI22,"p8")*2+COUNTIF(AI4:AI22,"P")+COUNTIF(AI4:AI22,"P4")*1.5 -> 0 | AJ23: =SUM(AJ4:AJ22) -> 142 | AK23: =SUM(AK4:AK22) -> 114 | AL23: =SUM(AL4:AL22) -> 19 | AM23: =SUM(AM4:AM22) -> 0 | AN23: =SUM(AN4:AN22) -> 142 | AO23: =SUM(AO4:AO22) -> 82 | AP23: =SUM(AP4:AP22) -> 10.25 | AQ23: =SUM(AQ4:AQ22) -> 152.25 | AR23: =SUM(AR4:AR22) -> 113108.17
B25: Designation | C25: Present Days | D25: Head count | E25: Per day | H25: Amount
B26: PB1 | C26: =AQ4 -> 18.25 | D26: 1 | E26: =D4 -> 858.22375 | H26: =E26*C26 -> 15662.583
B27: PB | C27: =SUM(AQ5) -> 12.5 | D27: 1 | E27: =D5 -> 774.875 | H27: =E27*C27 -> 9685.9375
B28: Hk Boy | C28: =SUM(AQ6:AQ8) -> 40.5 | D28: 5 | E28: =D6 -> 722.30167 | H28: =E28*C28 -> 29253.218
B29: CM | C29: =SUM(AQ9:AQ11) -> 44 | D29: 4 | E29: =D9 -> 722.30167 | H29: =E29*C29 -> 31781.273
B30: Total | C30: =SUM(C26:C29) -> 115.25 | D30: =D29+D28+D27+D26 -> 11 | H30: =SUM(H26:L29) -> 86383.012
C31: Service Charge | H31: =H30*15% -> 12957.452
C32: Total + Service Charge | H32: =H31+H30 -> 99340.464
C33: GST | H33: =H32*9% -> 8940.6417
C34: GST | H34: =H32*9% -> 8940.6417
C35: Total + Service Charge + GST | H35: =H34+H33+H32 -> 117221.75

Sheet New Meter
A1: Mantri Office New DG Meter Reading- May - 2024 | L1: Mantri Office New EB Meter Reading- May - 2024
A2: Date | B2: Time | C2: DG KWH | F2: DG KVAH | L2: DATE | M2: Time | N2: EB KWH | Q2: Total Unit | T2: EB KVAH | W2: Total Unit
C3: Opening | D3: Closening | E3: Cons | F3: Opening | G3: Closening | H3: Cons | I3: Rate | J3: Amount | N3: Opening | O3: Closening | P3: CONS | R3: Rate | S3: Amount | T3: Opening | U3: Closening | V3: CONS | X3: Rate | Y3: Amount
A4: 45426 | B4: 0 | C4: 0 | D4: 1 | E4: 40 | F4: 0 | G4: 1 | H4: 40 | I4: 40 | J4: =I4*G4 -> 40 | L4: 45426 | M4: 0 | N4: 0 | O4: 22 | P4: 880 | Q4: =O4-N4 -> 22 | R4: 40 | S4: =R4*O4 -> 880 | T4: 0 | U4: 23 | V4: 920 | W4: =U4-T4 -> 23 | X4: 40 | Y4: =X4*W4 -> 920
A5: 45427 | B5: 0 | C5: 1 | D5: 1 | E5: 0 | F5: 1 | G5: 1 | H5: 0 | I5: 40 | J5: 0 | L5: 45427 | M5: 0 | N5: 22 | O5: 31 | P5: 360 | Q5: =O5-N5 -> 9 | R5: 40 | S5: =R5*Q5 -> 360 | T5: 23 | U5: 33 | V5: 400 | W5: =U5-T5 -> 10 | X5: 40 | Y5: =X5*W5 -> 400
A6: 45428 | B6: 0 | C6: 1 | D6: 1 | E6: 0 | F6: 1 | G6: 1 | H6: 0 | I6: 40 | J6: 0 | L6: 45428 | M6: 0 | N6: 31 | O6: 40 | P6: 360 | Q6: =O6-N6 -> 9 | R6: 40 | S6: =R6*Q6 -> 360 | T6: 33 | U6: 42 | V6: 360 | W6: =U6-T6 -> 9 | X6: 40 | Y6: =X6*W6 -> 360
A7: 45429 | B7: 0 | C7: 1 | D7: 1 | E7: 0 | F7: 1 | G7: 1 | H7: 0 | I7: 40 | J7: 0 | L7: 45429 | M7: 0 | N7: 40 | O7: 49 | P7: 360 | Q7: =O7-N7 -> 9 | R7: 40 | S7: =R7*Q7 -> 360 | T7: 42 | U7: 52 | V7: 400 | W7: =U7-T7 -> 10 | X7: 40 | Y7: =X7*W7 -> 400
A8: 45430 | B8: 0 | C8: 1 | D8: 1 | E8: 0 | F8: 1 | G8: 1 | H8: 0 | I8: 40 | J8: 0 | L8: 45430 | M8: 0 | N8: 49 | O8: 57 | P8: 320 | Q8: =O8-N8 -> 8 | R8: 40 | S8: =R8*Q8 -> 320 | T8: 52 | U8: 60 | V8: 320 | W8: =U8-T8 -> 8 | X8: 40 | Y8: =X8*W8 -> 320
A9: 45431 | B9: 0 | C9: 1 | L9: 45431 | M9: 0 | N9: 57 | P9: -2280 | Q9: =O9-N9 -> -57 | R9: 40 | S9: =R9*Q9 -> -2280 | T9: 60 | V9: -2400 | W9: =U9-T9 -> -60 | X9: 40 | Y9: =X9*W9 -> -2400
X10: 40 | Y10: =X10*W10 -> 0
